Workbook

Sheet Dashboard
A1: 🏢 CBRE | YEARLY EVENT OPERATIONS DASHBOARD
A2: Downtown-3 & Downtown-4 Facilities • 2026 Event Planning, Capacity Analytics & Operations Management
A4: OPERATIONS CALENDAR BOOKING POLICY & STATUS GUIDE:
B5: 🟢 GREEN: Calendar Booking Done / Completed | G5: 🟡 YELLOW: Booking Pending (Upcoming / Action Required) | M5: 🔴 RED: Event Canceled by Organizer | R5: 📑 Open Master Tracker ↗
B7: TOTAL EVENTS (2026) | D7: EVENTS CONDUCTED (DONE) | F7: 🌟 BIG EVENTS (100+) | H7: 👥 SMALL EVENTS (<100) | J7: TOTAL ATTENDEES | L7: DOWNTOWN-3 EVENTS | N7: DOWNTOWN-4 EVENTS | P7: 📨 TOTAL FEEDBACK SENT | R7: ⚪ FEEDBACK NOT REQUIRED
B8: =B25+I28 -> 1786 | D8: =C25+J28 -> 1298 | F8: =P25 -> 148 | H8: =Q25 -> 1709 | J8: =F25+M28 -> 63482.333 | L8: =B25 -> 605 | N8: =I28 -> 1181 | P8: =R25+S25 -> 77 | R8: =COUNTIF(Master_Event_Tracker_2026!$T$3:$T$5000, "Not Required") -> 1808
B9: DT-3 & DT-4 combined | D9: 🟢 Done / Confirmed | F9: 100+ Pax (Feedback Applicable) | H9: < 100 Pax (Routine Events) | J9: 👥 Expected Pax | L9: 🏢 DT-3 Facility | N9: 🏢 DT-4 Facility | P9: DT-3: 12 | DT-4: 37 | R9: Routine Events / NA
A11: 🏢 DOWNTOWN-3 (DT-3) MONTHLY EVENT TRACKER & NAVIGATION | H11: 🏢 DOWNTOWN-4 (DT-4) MONTHLY EVENT TRACKER & NAVIGATION | O11: 📋 MONTHWISE EVENT SCALE & DT-3 / DT-4 FEEDBACK TRACKER
A12: Month (Click to Open) | B12: Total Events | C12: 🟢 Confirmed | D12: 🟡 Pending | E12: 🔴 Canceled | F12: Total Pax | H12: Month (Click to Open) | I12: Total Events | J12: 🟢 Confirmed | K12: 🟡 Pending | L12: 🔴 Canceled | M12: Total Pax | O12: Month | P12: 🌟 Big (100+) | Q12: 👥 Small (<100) | R12: 📨 DT-3 FB Sent | S12: 📨 DT-4 FB Sent
A13: Jan 2026 ↗ | B13: =COUNTIF('DT-3 Jan26'!$O$3:$O$500, "<>") -> 48 | C13: =COUNTIF('DT-3 Jan26'!$O$3:$O$500, "Confirmed (Done)") -> 45 | D13: =COUNTIF('DT-3 Jan26'!$O$3:$O$500, "Pending Calendar Booking") -> 0 | E13: =COUNTIF('DT-3 Jan26'!$O$3:$O$500, "Canceled") -> 3 | F13: =SUM('DT-3 Jan26'!$F$3:$F$500) -> 1190 | H13: Jan 2026 ↗ | I13: =COUNTIF('DT-4 Jan26'!$P$3:$P$500, "<>") -> 61 | J13: =COUNTIF('DT-4 Jan26'!$P$3:$P$500, "Confirmed (Done)") -> 54 | K13: =COUNTIF('DT-4 Jan26'!$P$3:$P$500, "Pending Calendar Booking") -> 0 | L13: =COUNTIF('DT-4 Jan26'!$P$3:$P$500, "Canceled") -> 7 | M13: =SUM('DT-4 Jan26'!$G$3:$G$500) -> 2851.3333 | O13: Jan 2026 | P13: =COUNTIFS(Master_Event_Tracker_2026!$C$3:$C$5000, "Jan", Master_Event_Tracker_2026!$L$3:$L$5000, "Big Event") -> 7 | Q13: =COUNTIFS(Master_Event_Tracker_2026!$C$3:$C$5000, "Jan", Master_Event_Tracker_2026!$L$3:$L$5000, "Small Event") -> 140 | R13: =COUNTIF('DT-3 Jan26'!$P$3:$P$500, "Form sent") -> 0 | S13: =COUNTIF('DT-4 Jan26'!$Q$3:$Q$500, "Form sent") -> 0
A14: Feb 2026 ↗ | B14: =COUNTIF('DT-3 Feb26'!$O$3:$O$500, "<>") -> 48 | C14: =COUNTIF('DT-3 Feb26'!$O$3:$O$500, "Confirmed (Done)") -> 44 | D14: =COUNTIF('DT-3 Feb26'!$O$3:$O$500, "Pending Calendar Booking") -> 0 | E14: =COUNTIF('DT-3 Feb26'!$O$3:$O$500, "Canceled") -> 4 | F14: =SUM('DT-3 Feb26'!$F$3:$F$500) -> 1497 | H14: Feb 2026 ↗ | I14: =COUNTIF('DT-4 Feb26'!$P$3:$P$500, "<>") -> 119 | J14: =COUNTIF('DT-4 Feb26'!$P$3:$P$500, "Confirmed (Done)") -> 107 | K14: =COUNTIF('DT-4 Feb26'!$P$3:$P$500, "Pending Calendar Booking") -> 0 | L14: =COUNTIF('DT-4 Feb26'!$P$3:$P$500, "Canceled") -> 12 | M14: =SUM('DT-4 Feb26'!$G$3:$G$500) -> 4731 | O14: Feb 2026 | P14: =COUNTIFS(Master_Event_Tracker_2026!$C$3:$C$5000, "Feb", Master_Event_Tracker_2026!$L$3:$L$5000, "Big Event") -> 22 | Q14: =COUNTIFS(Master_Event_Tracker_2026!$C$3:$C$5000, "Feb", Master_Event_Tracker_2026!$L$3:$L$5000, "Small Event") -> 183 | R14: =COUNTIF('DT-3 Feb26'!$P$3:$P$500, "Form sent") -> 0 | S14: =COUNTIF('DT-4 Feb26'!$Q$3:$Q$500, "Form sent") -> 0
A15: Mar 2026 ↗ | B15: =COUNTIF('DT-3 Mar26'!$O$3:$O$500, "<>") -> 59 | C15: =COUNTIF('DT-3 Mar26'!$O$3:$O$500, "Confirmed (Done)") -> 58 | D15: =COUNTIF('DT-3 Mar26'!$O$3:$O$500, "Pending Calendar Booking") -> 0 | E15: =COUNTIF('DT-3 Mar26'!$O$3:$O$500, "Canceled") -> 1 | F15: =SUM('DT-3 Mar26'!$F$3:$F$500) -> 1910 | H15: Mar 2026 ↗ | I15: =COUNTIF('DT-4 Mar26'!$P$3:$P$500, "<>") -> 118 | J15: =COUNTIF('DT-4 Mar26'!$P$3:$P$500, "Confirmed (Done)") -> 112 | K15: =COUNTIF('DT-4 Mar26'!$P$3:$P$500, "Pending Calendar Booking") -> 0 | L15: =COUNTIF('DT-4 Mar26'!$P$3:$P$500, "Canceled") -> 6 | M15: =SUM('DT-4 Mar26'!$G$3:$G$500) -> 4180 | O15: Mar 2026 | P15: =COUNTIFS(Master_Event_Tracker_2026!$C$3:$C$5000, "Mar", Master_Event_Tracker_2026!$L$3:$L$5000, "Big Event") -> 19 | Q15: =COUNTIFS(Master_Event_Tracker_2026!$C$3:$C$5000, "Mar", Master_Event_Tracker_2026!$L$3:$L$5000, "Small Event") -> 196 | R15: =COUNTIF('DT-3 Mar26'!$P$3:$P$500, "Form sent") -> 0 | S15: =COUNTIF('DT-4 Mar26'!$Q$3:$Q$500, "Form sent") -> 0
A16: Apr 2026 ↗ | B16: =COUNTIF('DT-3 Apr26'!$O$3:$O$500, "<>") -> 53 | C16: =COUNTIF('DT-3 Apr26'!$O$3:$O$500, "Confirmed (Done)") -> 51 | D16: =COUNTIF('DT-3 Apr26'!$O$3:$O$500, "Pending Calendar Booking") -> 0 | E16: =COUNTIF('DT-3 Apr26'!$O$3:$O$500, "Canceled") -> 2 | F16: =SUM('DT-3 Apr26'!$F$3:$F$500) -> 1713 | H16: Apr 2026 ↗ | I16: =COUNTIF('DT-4 Apr26'!$P$3:$P$500, "<>") -> 68 | J16: =COUNTIF('DT-4 Apr26'!$P$3:$P$500, "Confirmed (Done)") -> 61 | K16: =COUNTIF('DT-4 Apr26'!$P$3:$P$500, "Pending Calendar Booking") -> 0 | L16: =COUNTIF('DT-4 Apr26'!$P$3:$P$500, "Canceled") -> 7 | M16: =SUM('DT-4 Apr26'!$G$3:$G$500) -> 3063 | O16: Apr 2026 | P16: =COUNTIFS(Master_Event_Tracker_2026!$C$3:$C$5000, "Apr", Master_Event_Tracker_2026!$L$3:$L$5000, "Big Event") -> 13 | Q16: =COUNTIFS(Master_Event_Tracker_2026!$C$3:$C$5000, "Apr", Master_Event_Tracker_2026!$L$3:$L$5000, "Small Event") -> 108 | R16: =COUNTIF('DT-3 Apr26'!$P$3:$P$500, "Form sent") -> 0 | S16: =COUNTIF('DT-4 Apr26'!$Q$3:$Q$500, "Form sent") -> 0
A17: May 2026 ↗ | B17: =COUNTIF('DT-3 May26'!$O$3:$O$500, "<>") -> 48 | C17: =COUNTIF('DT-3 May26'!$O$3:$O$500, "Confirmed (Done)") -> 45 | D17: =COUNTIF('DT-3 May26'!$O$3:$O$500, "Pending Calendar Booking") -> 0 | E17: =COUNTIF('DT-3 May26'!$O$3:$O$500, "Canceled") -> 3 | F17: =SUM('DT-3 May26'!$F$3:$F$500) -> 1200 | H17: May 2026 ↗ | I17: =COUNTIF('DT-4 May26'!$P$3:$P$500, "<>") -> 92 | J17: =COUNTIF('DT-4 May26'!$P$3:$P$500, "Confirmed (Done)") -> 89 | K17: =COUNTIF('DT-4 May26'!$P$3:$P$500, "Pending Calendar Booking") -> 0 | L17: =COUNTIF('DT-4 May26'!$P$3:$P$500, "Canceled") -> 3 | M17: =SUM('DT-4 May26'!$G$3:$G$500) -> 4474 | O17: May 2026 | P17: =COUNTIFS(Master_Event_Tracker_2026!$C$3:$C$5000, "May", Master_Event_Tracker_2026!$L$3:$L$5000, "Big Event") -> 16 | Q17: =COUNTIFS(Master_Event_Tracker_2026!$C$3:$C$5000, "May", Master_Event_Tracker_2026!$L$3:$L$5000, "Small Event") -> 124 | R17: =COUNTIF('DT-3 May26'!$P$3:$P$500, "Form sent") -> 0 | S17: =COUNTIF('DT-4 May26'!$Q$3:$Q$500, "Form sent") -> 0
A18: Jun 2026 ↗ | B18: =COUNTIF('DT-3 Jun26'!$O$3:$O$500, "<>") -> 48 | C18: =COUNTIF('DT-3 Jun26'!$O$3:$O$500, "Confirmed (Done)") -> 45 | D18: =COUNTIF('DT-3 Jun26'!$O$3:$O$500, "Pending Calendar Booking") -> 0 | E18: =COUNTIF('DT-3 Jun26'!$O$3:$O$500, "Canceled") -> 3 | F18: =SUM('DT-3 Jun26'!$F$3:$F$500) -> 1217 | H18: Jun 2026 ↗ | I18: =COUNTIF('DT-4 Jun26'!$P$3:$P$500, "<>") -> 118 | J18: =COUNTIF('DT-4 Jun26'!$P$3:$P$500, "Confirmed (Done)") -> 109 | K18: =COUNTIF('DT-4 Jun26'!$P$3:$P$500, "Pending Calendar Booking") -> 0 | L18: =COUNTIF('DT-4 Jun26'!$P$3:$P$500, "Canceled") -> 9 | M18: =SUM('DT-4 Jun26'!$G$3:$G$500) -> 4958 | O18: Jun 2026 | P18: =COUNTIFS(Master_Event_Tracker_2026!$C$3:$C$5000, "Jun", Master_Event_Tracker_2026!$L$3:$L$5000, "Big Event") -> 14 | Q18: =COUNTIFS(Master_Event_Tracker_2026!$C$3:$C$5000, "Jun", Master_Event_Tracker_2026!$L$3:$L$5000, "Small Event") -> 152 | R18: =COUNTIF('DT-3 Jun26'!$P$3:$P$500, "Form sent") -> 0 | S18: =COUNTIF('DT-4 Jun26'!$Q$3:$Q$500, "Form sent") -> 0
A19: Jul 2026 ↗ | B19: =COUNTIF('DT-3 Jul26'!$O$3:$O$500, "<>") -> 64 | C19: =COUNTIF('DT-3 Jul26'!$O$3:$O$500, "Confirmed (Done)") -> 59 | D19: =COUNTIF('DT-3 Jul26'!$O$3:$O$500, "Pending Calendar Booking") -> 0 | E19: =COUNTIF('DT-3 Jul26'!$O$3:$O$500, "Canceled") -> 5 | F19: =SUM('DT-3 Jul26'!$F$3:$F$500) -> 1682 | H19: Jul 2026 ↗ | I19: =COUNTIF('DT-4 Jul26'!$P$3:$P$500, "<>") -> 177 | J19: =COUNTIF('DT-4 Jul26'!$P$3:$P$500, "Confirmed (Done)") -> 147 | K19: =COUNTIF('DT-4 Jul26'!$P$3:$P$500, "Pending Calendar Booking") -> 0 | L19: =COUNTIF('DT-4 Jul26'!$P$3:$P$500, "Canceled") -> 30 | M19: =SUM('DT-4 Jul26'!$G$3:$G$500) -> 7266 | O19: Jul 2026 | P19: =COUNTIFS(Master_Event_Tracker_2026!$C$3:$C$5000, "Jul", Master_Event_Tracker_2026!$L$3:$L$5000, "Big Event") -> 25 | Q19: =COUNTIFS(Master_Event_Tracker_2026!$C$3:$C$5000, "Jul", Master_Event_Tracker_2026!$L$3:$L$5000, "Small Event") -> 216 | R19: =COUNTIF('DT-3 Jul26'!$P$3:$P$500, "Form sent") -> 0 | S19: =COUNTIF('DT-4 Jul26'!$Q$3:$Q$500, "Form sent") -> 0
A20: Aug 2026 ↗ | B20: =COUNTIF('DT-3 Aug26'!$O$3:$O$501, "<>") -> 51 | C20: =COUNTIF('DT-3 Aug26'!$O$3:$O$501, "Confirmed (Done)") -> 38 | D20: =COUNTIF('DT-3 Aug26'!$O$3:$O$501, "Pending Calendar Booking") -> 3 | E20: =COUNTIF('DT-3 Aug26'!$O$3:$O$501, "Canceled") -> 10 | F20: =SUM('DT-3 Aug26'!$F$3:$F$501) -> 1868 | H20: Aug 2026 ↗ | I20: =COUNTIF('DT-4 Aug26'!$P$3:$P$505, "<>") -> 133 | J20: =COUNTIF('DT-4 Aug26'!$P$3:$P$505, "Confirmed (Done)") -> 109 | K20: =COUNTIF('DT-4 Aug26'!$P$3:$P$505, "Pending Calendar Booking") -> 0 | L20: =COUNTIF('DT-4 Aug26'!$P$3:$P$505, "Canceled") -> 24 | M20: =SUM('DT-4 Aug26'!$G$3:$G$505) -> 6113 | O20: Aug 2026 | P20: =COUNTIFS(Master_Event_Tracker_2026!$C$3:$C$5000, "Aug", Master_Event_Tracker_2026!$L$3:$L$5000, "Big Event") -> 21 | Q20: =COUNTIFS(Master_Event_Tracker_2026!$C$3:$C$5000, "Aug", Master_Event_Tracker_2026!$L$3:$L$5000, "Small Event") -> 162 | R20: =COUNTIF('DT-3 Aug26'!$P$3:$P$501, "Form sent") -> 12 | S20: =COUNTIF('DT-4 Aug26'!$Q$3:$Q$505, "Form sent") -> 65
A21: Sep 2026 ↗ | B21: =COUNTIF('DT-3 Sep26'!$O$3:$O$505, "<>") -> 42 | C21: =COUNTIF('DT-3 Sep26'!$O$3:$O$505, "Confirmed (Done)") -> 22 | D21: =COUNTIF('DT-3 Sep26'!$O$3:$O$505, "Pending Calendar Booking") -> 20 | E21: =COUNTIF('DT-3 Sep26'!$O$3:$O$505, "Canceled") -> 0 | F21: =SUM('DT-3 Sep26'!$F$3:$F$505) -> 1174 | H21: Sep 2026 ↗ | I21: =COUNTIF('DT-4 Sep26'!$P$3:$P$554, "<>") -> 136 | J21: =COUNTIF('DT-4 Sep26'!$P$3:$P$554, "Confirmed (Done)") -> 101 | K21: =COUNTIF('DT-4 Sep26'!$P$3:$P$554, "Pending Calendar Booking") -> 33 | L21: =COUNTIF('DT-4 Sep26'!$P$3:$P$554, "Canceled") -> 2 | M21: =SUM('DT-4 Sep26'!$G$3:$G$554) -> 5687 | O21: Sep 2026 | P21: =COUNTIFS(Master_Event_Tracker_2026!$C$3:$C$5000, "Sep", Master_Event_Tracker_2026!$L$3:$L$5000, "Big Event") -> 8 | Q21: =COUNTIFS(Master_Event_Tracker_2026!$C$3:$C$5000, "Sep", Master_Event_Tracker_2026!$L$3:$L$5000, "Small Event") -> 143 | R21: =COUNTIF('DT-3 Sep26'!$P$3:$P$505, "Form sent") -> 0 | S21: =COUNTIF('DT-4 Sep26'!$Q$3:$Q$554, "Form sent") -> 0
A22: Oct 2026 ↗ | B22: =COUNTIF('DT-3 Oct26'!$O$3:$O$500, "<>") -> 48 | C22: =COUNTIF('DT-3 Oct26'!$O$3:$O$500, "Confirmed (Done)") -> 0 | D22: =COUNTIF('DT-3 Oct26'!$O$3:$O$500, "Pending Calendar Booking") -> 48 | E22: =COUNTIF('DT-3 Oct26'!$O$3:$O$500, "Canceled") -> 0 | F22: =SUM('DT-3 Oct26'!$F$3:$F$500) -> 85 | H22: Oct 2026 ↗ | I22: =COUNTIF('DT-4 Oct26'!$P$3:$P$507, "<>") -> 55 | J22: =COUNTIF('DT-4 Oct26'!$P$3:$P$507, "Confirmed (Done)") -> 2 | K22: =COUNTIF('DT-4 Oct26'!$P$3:$P$507, "Pending Calendar Booking") -> 53 | L22: =COUNTIF('DT-4 Oct26'!$P$3:$P$507, "Canceled") -> 0 | M22: =SUM('DT-4 Oct26'!$G$3:$G$507) -> 1398 | O22: Oct 2026 | P22: =COUNTIFS(Master_Event_Tracker_2026!$C$3:$C$5000, "Oct", Master_Event_Tracker_2026!$L$3:$L$5000, "Big Event") -> 0 | Q22: =COUNTIFS(Master_Event_Tracker_2026!$C$3:$C$5000, "Oct", Master_Event_Tracker_2026!$L$3:$L$5000, "Small Event") -> 96 | R22: =COUNTIF('DT-3 Oct26'!$P$3:$P$500, "Form sent") -> 0 | S22: =COUNTIF('DT-4 Oct26'!$Q$3:$Q$507, "Form sent") -> 0
A23: Nov 2026 ↗ | B23: =COUNTIF('DT-3 Nov26'!$O$3:$O$500, "<>") -> 48 | C23: =COUNTIF('DT-3 Nov26'!$O$3:$O$500, "Confirmed (Done)") -> 0 | D23: =COUNTIF('DT-3 Nov26'!$O$3:$O$500, "Pending Calendar Booking") -> 48 | E23: =COUNTIF('DT-3 Nov26'!$O$3:$O$500, "Canceled") -> 0 | F23: =SUM('DT-3 Nov26'!$F$3:$F$500) -> 200 | H23: Nov 2026 ↗ | I23: =COUNTIF('DT-4 Nov26'!$P$3:$P$505, "<>") -> 53 | J23: =COUNTIF('DT-4 Nov26'!$P$3:$P$505, "Confirmed (Done)") -> 0 | K23: =COUNTIF('DT-4 Nov26'!$P$3:$P$505, "Pending Calendar Booking") -> 53 | L23: =COUNTIF('DT-4 Nov26'!$P$3:$P$505, "Canceled") -> 0 | M23: =SUM('DT-4 Nov26'!$G$3:$G$505) -> 1365 | O23: Nov 2026 | P23: =COUNTIFS(Master_Event_Tracker_2026!$C$3:$C$5000, "Nov", Master_Event_Tracker_2026!$L$3:$L$5000, "Big Event") -> 3 | Q23: =COUNTIFS(Master_Event_Tracker_2026!$C$3:$C$5000, "Nov", Master_Event_Tracker_2026!$L$3:$L$5000, "Small Event") -> 93 | R23: =COUNTIF('DT-3 Nov26'!$P$3:$P$500, "Form sent") -> 0 | S23: =COUNTIF('DT-4 Nov26'!$Q$3:$Q$505, "Form sent") -> 0
A24: Dec 2026 ↗ | B24: =COUNTIF('DT-3 Dec26'!$O$3:$O$500, "<>") -> 48 | C24: =COUNTIF('DT-3 Dec26'!$O$3:$O$500, "Confirmed (Done)") -> 0 | D24: =COUNTIF('DT-3 Dec26'!$O$3:$O$500, "Pending Calendar Booking") -> 48 | E24: =COUNTIF('DT-3 Dec26'!$O$3:$O$500, "Canceled") -> 0 | F24: =SUM('DT-3 Dec26'!$F$3:$F$500) -> 50 | H24: Dec 2026 ↗ | I24: =COUNTIF('DT-4 Dec26'!$P$3:$P$503, "<>") -> 51 | J24: =COUNTIF('DT-4 Dec26'!$P$3:$P$503, "Confirmed (Done)") -> 0 | K24: =COUNTIF('DT-4 Dec26'!$P$3:$P$503, "Pending Calendar Booking") -> 51 | L24: =COUNTIF('DT-4 Dec26'!$P$3:$P$503, "Canceled") -> 0 | M24: =SUM('DT-4 Dec26'!$G$3:$G$503) -> 1010 | O24: Dec 2026 | P24: =COUNTIFS(Master_Event_Tracker_2026!$C$3:$C$5000, "Dec", Master_Event_Tracker_2026!$L$3:$L$5000, "Big Event") -> 0 | Q24: =COUNTIFS(Master_Event_Tracker_2026!$C$3:$C$5000, "Dec", Master_Event_Tracker_2026!$L$3:$L$5000, "Small Event") -> 96 | R24: =COUNTIF('DT-3 Dec26'!$P$3:$P$500, "Form sent") -> 0 | S24: =COUNTIF('DT-4 Dec26'!$Q$3:$Q$503, "Form sent") -> 0
A25: DT-3 Full Year Total | B25: =SUM(B13:B24) -> 605 | C25: =SUM(C13:C24) -> 407 | D25: =SUM(D13:D24) -> 167 | E25: =SUM(E13:E24) -> 31 | F25: =SUM(F13:F24) -> 13786 | H25: Jan '27 ↗ | I25: =COUNTIF('DT-4 Jan27'!$P$3:$P$503, "<>") -> 41 | J25: =COUNTIF('DT-4 Jan27'!$P$3:$P$503, "Confirmed (Done)") -> 8 | K25: =COUNTIF('DT-4 Jan27'!$P$3:$P$503, "Pending Calendar Booking") -> 33 | L25: =COUNTIF('DT-4 Jan27'!$P$3:$P$503, "Canceled") -> 0 | M25: =SUM('DT-4 Jan27'!$G$3:$G$503) -> 800 | O25: Full Year Total | P25: =SUM(P13:P24) -> 148 | Q25: =SUM(Q13:Q24) -> 1709 | R25: =SUM(R13:R24) -> 12 | S25: =SUM(S13:S24) -> 65
H26: Feb '27 ↗ | I26: =COUNTIF('DT-4 Feb27'!$P$3:$P$504, "<>") -> 42 | J26: =COUNTIF('DT-4 Feb27'!$P$3:$P$504, "Confirmed (Done)") -> 8 | K26: =COUNTIF('DT-4 Feb27'!$P$3:$P$504, "Pending Calendar Booking") -> 34 | L26: =COUNTIF('DT-4 Feb27'!$P$3:$P$504, "Canceled") -> 0 | M26: =SUM('DT-4 Feb27'!$G$3:$G$504) -> 850
H27: Mar '27 ↗ | I27: =COUNTIF('DT-4 Mar27'!$P$3:$P$503, "<>") -> 41 | J27: =COUNTIF('DT-4 Mar27'!$P$3:$P$503, "Confirmed (Done)") -> 8 | K27: =COUNTIF('DT-4 Mar27'!$P$3:$P$503, "Pending Calendar Booking") -> 33 | L27: =COUNTIF('DT-4 Mar27'!$P$3:$P$503, "Canceled") -> 0 | M27: =SUM('DT-4 Mar27'!$G$3:$G$503) -> 950 | O27: Event Scale Metric | P27: Summary | R27: Feedback Breakdown | S27: Count
H28: DT-4 2026 Subtotal | I28: =SUM(I13:I24) -> 1181 | J28: =SUM(J13:J24) -> 891 | K28: =SUM(K13:K24) -> 190 | L28: =SUM(L13:L24) -> 100 | M28: =SUM(M13:M27) -> 49696.333 | O28: 🏆 Events Conducted | P28: =E45 -> 1298 | R28: 🏢 DT-3 Feedback Sent | S28: =R25 -> 12
O29: 🌟 Big Events (100+) | P29: =P25 -> 148 | R29: 🏢 DT-4 Feedback Sent | S29: =S25 -> 65
O30: 👥 Small Events (<100) | P30: =Q25 -> 1709 | R30: 📨 Total Feedback Sent | S30: =R25+S25 -> 77
A31: 📊 2026 COMBINED MONTHLY EVENTS SUMMARY | K31: 🔍 INTERACTIVE MONTH SELECTION & DEEP DIVE
A32: Month | B32: DT-3 Events | C32: DT-4 Events | D32: Total Events | E32: 🟢 Confirmed | F32: 🟡 Pending | G32: 🔴 Canceled | H32: Confirmed % | I32: Total Pax | K32: 📅 SELECT MONTH: | M32: Jan | P32: 🟢 Live Auto-Calculated Drilldown
A33: Jan | B33: =B13 -> 48 | C33: =I13 -> 61 | D33: =B33+C33 -> 109 | E33: =C13+J13 -> 99 | F33: =D13+K13 -> 0 | G33: =E13+L13 -> 10 | H33: =IFERROR(E33/(E33+F33), 0) -> 1 | I33: =F13+M13 -> 4041.3333 | K33: TOTAL EVENTS | M33: CONFIRMED (DONE) | P33: PENDING BOOKING | S33: CANCELED
A34: Feb | B34: =B14 -> 48 | C34: =I14 -> 119 | D34: =B34+C34 -> 167 | E34: =C14+J14 -> 151 | F34: =D14+K14 -> 0 | G34: =E14+L14 -> 16 | H34: =IFERROR(E34/(E34+F34), 0) -> 1 | I34: =F14+M14 -> 6228 | K34: =IF($M$32="Full Year 2026", D45, IFERROR(INDEX($D$33:$D$44, MATCH($M$32, $A$33:$A$44, 0)), 0)) -> 109 | M34: =IF($M$32="Full Year 2026", E45, IFERROR(INDEX($E$33:$E$44, MATCH($M$32, $A$33:$A$44, 0)), 0)) -> 99 | P34: =IF($M$32="Full Year 2026", F45, IFERROR(INDEX($F$33:$F$44, MATCH($M$32, $A$33:$A$44, 0)), 0)) -> 0 | S34: =IF($M$32="Full Year 2026", G45, IFERROR(INDEX($G$33:$G$44, MATCH($M$32, $A$33:$A$44, 0)), 0)) -> 10
A35: Mar | B35: =B15 -> 59 | C35: =I15 -> 118 | D35: =B35+C35 -> 177 | E35: =C15+J15 -> 170 | F35: =D15+K15 -> 0 | G35: =E15+L15 -> 7 | H35: =IFERROR(E35/(E35+F35), 0) -> 1 | I35: =F15+M15 -> 6090 | K35: CONFIRMED % RATE | M35: TOTAL ATTENDEES (PAX) | P35: DT-3 EVENTS | R35: DT-4 EVENTS
A36: Apr | B36: =B16 -> 53 | C36: =I16 -> 68 | D36: =B36+C36 -> 121 | E36: =C16+J16 -> 112 | F36: =D16+K16 -> 0 | G36: =E16+L16 -> 9 | H36: =IFERROR(E36/(E36+F36), 0) -> 1 | I36: =F16+M16 -> 4776 | K36: =IF($M$32="Full Year 2026", H45, IFERROR(INDEX($H$33:$H$44, MATCH($M$32, $A$33:$A$44, 0)), 0)) -> 1 | M36: =IF($M$32="Full Year 2026", I45, IFERROR(INDEX($I$33:$I$44, MATCH($M$32, $A$33:$A$44, 0)), 0)) -> 4041.3333 | P36: =IF($M$32="Full Year 2026", B45, IFERROR(INDEX($B$33:$B$44, MATCH($M$32, $A$33:$A$44, 0)), 0)) -> 48 | R36: =IF($M$32="Full Year 2026", C45, IFERROR(INDEX($C$33:$C$44, MATCH($M$32, $A$33:$A$44, 0)), 0)) -> 61
A37: May | B37: =B17 -> 48 | C37: =I17 -> 92 | D37: =B37+C37 -> 140 | E37: =C17+J17 -> 134 | F37: =D17+K17 -> 0 | G37: =E17+L17 -> 6 | H37: =IFERROR(E37/(E37+F37), 0) -> 1 | I37: =F17+M17 -> 5674 | K37: 🌟 BIG (100+): | M37: =IF($M$32="Full Year 2026", P25, IFERROR(INDEX($P$13:$P$24, MATCH($M$32, $A$33:$A$44, 0)), 0)) -> 7 | N37: 👥 SMALL (<100): | P37: =IF($M$32="Full Year 2026", Q25, IFERROR(INDEX($Q$13:$Q$24, MATCH($M$32, $A$33:$A$44, 0)), 0)) -> 140 | Q37: 📨 DT3 / DT4 FB: | S37: =IF($M$32="Full Year 2026", R25&"/"&S25, IFERROR(INDEX($R$13:$R$24, MATCH($M$32, $A$33:$A$44, 0))&"/"&INDEX($S$13:$S$24, MATCH($M$32, $A$33:$A$44, 0)), "0/0")) -> 0/0
A38: Jun | B38: =B18 -> 48 | C38: =I18 -> 118 | D38: =B38+C38 -> 166 | E38: =C18+J18 -> 154 | F38: =D18+K18 -> 0 | G38: =E18+L18 -> 12 | H38: =IFERROR(E38/(E38+F38), 0) -> 1 | I38: =F18+M18 -> 6175 | K38: 🚀 QUICK NAVIGATION TO MONTHLY TRACKERS
A39: Jul | B39: =B19 -> 64 | C39: =I19 -> 177 | D39: =B39+C39 -> 241 | E39: =C19+J19 -> 206 | F39: =D19+K19 -> 0 | G39: =E19+L19 -> 35 | H39: =IFERROR(E39/(E39+F39), 0) -> 1 | I39: =F19+M19 -> 8948 | K39: 💡 HOW TO USE THIS DASHBOARD: 1. Change the Month dropdown above (M32) to instantly update the Monthly Deep Dive KPIs. 2. Click any Month in the DT-3 / DT-4 tables (Rows 13-27) to jump directly to that month's sheet. 3. In any monthly sheet, click '🏠 ⮌ RETURN TO DASHBOARD' (A1) to return back here. 4. Event Scale: Big Event (100+ pax) vs Small Event (<100 pax). Feedback forms recorded for previous entries are preserved; routine events are marked 'Not Required'.
A40: Aug | B40: =B20 -> 51 | C40: =I20 -> 133 | D40: =B40+C40 -> 184 | E40: =C20+J20 -> 147 | F40: =D20+K20 -> 3 | G40: =E20+L20 -> 34 | H40: =IFERROR(E40/(E40+F40), 0) -> 0.98 | I40: =F20+M20 -> 7981
A41: Sep | B41: =B21 -> 42 | C41: =I21 -> 136 | D41: =B41+C41 -> 178 | E41: =C21+J21 -> 123 | F41: =D21+K21 -> 53 | G41: =E21+L21 -> 2 | H41: =IFERROR(E41/(E41+F41), 0) -> 0.69886364 | I41: =F21+M21 -> 6861
A42: Oct | B42: =B22 -> 48 | C42: =I22 -> 55 | D42: =B42+C42 -> 103 | E42: =C22+J22 -> 2 | F42: =D22+K22 -> 101 | G42: =E22+L22 -> 0 | H42: =IFERROR(E42/(E42+F42), 0) -> 0.019417476 | I42: =F22+M22 -> 1483
A43: Nov | B43: =B23 -> 48 | C43: =I23 -> 53 | D43: =B43+C43 -> 101 | E43: =C23+J23 -> 0 | F43: =D23+K23 -> 101 | G43: =E23+L23 -> 0 | H43: =IFERROR(E43/(E43+F43), 0) -> 0 | I43: =F23+M23 -> 1565
A44: Dec | B44: =B24 -> 48 | C44: =I24 -> 51 | D44: =B44+C44 -> 99 | E44: =C24+J24 -> 0 | F44: =D24+K24 -> 99 | G44: =E24+L24 -> 0 | H44: =IFERROR(E44/(E44+F44), 0) -> 0 | I44: =F24+M24 -> 1060
A45: Full Year 2026 Total | B45: =SUM(B33:B44) -> 605 | C45: =SUM(C33:C44) -> 1181 | D45: =SUM(D33:D44) -> 1786 | E45: =SUM(E33:E44) -> 1298 | F45: =SUM(F33:F44) -> 357 | G45: =SUM(G33:G44) -> 131 | H45: =IFERROR(E45/(E45+F45), 0) -> 0.78429003 | I45: =SUM(I33:I44) -> 60882.333
A47: 📍 FACILITY SPACE & VENUE UTILIZATION | F47: 🎯 EVENT CATEGORY & PURPOSE DISTRIBUTION | K47: 📜 FEEDBACK FORM POLICY & APPLICABILITY RULES GUIDE
A48: Key Venue / Space | B48: Building | C48: Events | D48: Total Pax | F48: Event Category | G48: Total Events | H48: Confirmed | I48: Total Pax | K48: Event Category / Tier | M48: Applicable Event Scope | O48: Pax Scale | P48: Feedback Form Rule | R48: Operations Guidelines & Rationale
A49: Innovation Hub | B49: Downtown-4 | C49: =COUNTIFS(Master_Event_Tracker_2026!$H$3:$H$5000, "*Innovation Hub*", Master_Event_Tracker_2026!$F$3:$F$5000, "Downtown-4") -> 173 | D49: =SUMIFS(Master_Event_Tracker_2026!$K$3:$K$5000, Master_Event_Tracker_2026!$H$3:$H$5000, "*Innovation Hub*", Master_Event_Tracker_2026!$F$3:$F$5000, "Downtown-4") -> 9624 | F49: Townhall & All-Hands | G49: =COUNTIF(Master_Event_Tracker_2026!$J$3:$J$5000, "Townhall & All-Hands") -> 186 | H49: =COUNTIFS(Master_Event_Tracker_2026!$J$3:$J$5000, "Townhall & All-Hands", Master_Event_Tracker_2026!$S$3:$S$5000, "Confirmed (Done)") -> 144 | I49: =SUMIF(Master_Event_Tracker_2026!$J$3:$J$5000, "Townhall & All-Hands", Master_Event_Tracker_2026!$K$3:$K$5000) -> 17345 | K49: 🌟 Tier 1: Major Townhalls | M49: All-Hands, Leadership Forums, Quarterly Townhalls | O49: 100+ Pax | P49: 📨 Form Sent (Mandatory) | R49: High stakeholder visibility & heavy AV/Cafeteria resource utilization.
A50: Cafeteria (L-1) | B50: Downtown-4 | C50: =COUNTIFS(Master_Event_Tracker_2026!$H$3:$H$5000, "*Cafeteria*", Master_Event_Tracker_2026!$F$3:$F$5000, "Downtown-4") -> 47 | D50: =SUMIFS(Master_Event_Tracker_2026!$K$3:$K$5000, Master_Event_Tracker_2026!$H$3:$H$5000, "*Cafeteria*", Master_Event_Tracker_2026!$F$3:$F$5000, "Downtown-4") -> 5640 | F50: Training & Enablement | G50: =COUNTIF(Master_Event_Tracker_2026!$J$3:$J$5000, "Training & Enablement") -> 210 | H50: =COUNTIFS(Master_Event_Tracker_2026!$J$3:$J$5000, "Training & Enablement", Master_Event_Tracker_2026!$S$3:$S$5000, "Confirmed (Done)") -> 104 | I50: =SUMIF(Master_Event_Tracker_2026!$J$3:$J$5000, "Training & Enablement", Master_Event_Tracker_2026!$K$3:$K$5000) -> 6278 | K50: 🌟 Tier 1: Site Celebrations | M50: Independence Day, Women Empowerment, Cultural Meets | O50: 100+ Pax | P50: 📨 Form Sent (Mandatory) | R50: Measure employee engagement, catering satisfaction & event experience.
A51: Hackable Area | B51: Downtown-4 | C51: =COUNTIFS(Master_Event_Tracker_2026!$H$3:$H$5000, "*Hackable*", Master_Event_Tracker_2026!$F$3:$F$5000, "Downtown-4") -> 106 | D51: =SUMIFS(Master_Event_Tracker_2026!$K$3:$K$5000, Master_Event_Tracker_2026!$H$3:$H$5000, "*Hackable*", Master_Event_Tracker_2026!$F$3:$F$5000, "Downtown-4") -> 4303 | F51: Induction & Onboarding | G51: =COUNTIF(Master_Event_Tracker_2026!$J$3:$J$5000, "Induction & Onboarding") -> 98 | H51: =COUNTIFS(Master_Event_Tracker_2026!$J$3:$J$5000, "Induction & Onboarding", Master_Event_Tracker_2026!$S$3:$S$5000, "Confirmed (Done)") -> 80 | I51: =SUMIF(Master_Event_Tracker_2026!$J$3:$J$5000, "Induction & Onboarding", Master_Event_Tracker_2026!$K$3:$K$5000) -> 3730 | K51: 🌟 Tier 1: Strategic R&R | M51: Personal Banking R&R, PEB R&R, Annual Rewards | O51: 70 - 150+ | P51: 📨 Form Sent (Mandatory) | R51: Recognize team achievements and track event organization feedback.
A52: Social Hub Areas | B52: Downtown-4 | C52: =COUNTIFS(Master_Event_Tracker_2026!$H$3:$H$5000, "*Social Hub*", Master_Event_Tracker_2026!$F$3:$F$5000, "Downtown-4") -> 114 | D52: =SUMIFS(Master_Event_Tracker_2026!$K$3:$K$5000, Master_Event_Tracker_2026!$H$3:$H$5000, "*Social Hub*", Master_Event_Tracker_2026!$F$3:$F$5000, "Downtown-4") -> 3964 | F52: Assessment & Hiring | G52: =COUNTIF(Master_Event_Tracker_2026!$J$3:$J$5000, "Assessment & Hiring") -> 133 | H52: =COUNTIFS(Master_Event_Tracker_2026!$J$3:$J$5000, "Assessment & Hiring", Master_Event_Tracker_2026!$S$3:$S$5000, "Confirmed (Done)") -> 107 | I52: =SUMIF(Master_Event_Tracker_2026!$J$3:$J$5000, "Assessment & Hiring", Master_Event_Tracker_2026!$K$3:$K$5000) -> 5809 | K52: 🎓 Tier 2: Tech Workshops | M52: Copilot Hacks, CSA Agentic AI, Gender Equity Forums | O52: 25 - 80 Pax | P52: 📨 Form Sent (Recommended) | R52: Evaluate curriculum depth, technical trainer effectiveness & lab setup.
A53: Cafeteria (L-5) | B53: Downtown-4 | C53: =COUNTIFS(Master_Event_Tracker_2026!$H$3:$H$5000, "*Cafeteria*", Master_Event_Tracker_2026!$F$3:$F$5000, "Downtown-4") -> 47 | D53: =SUMIFS(Master_Event_Tracker_2026!$K$3:$K$5000, Master_Event_Tracker_2026!$H$3:$H$5000, "*Cafeteria*", Master_Event_Tracker_2026!$F$3:$F$5000, "Downtown-4") -> 5640 | F53: Leadership & VIP Visit | G53: =COUNTIF(Master_Event_Tracker_2026!$J$3:$J$5000, "Leadership & VIP Visit") -> 131 | H53: =COUNTIFS(Master_Event_Tracker_2026!$J$3:$J$5000, "Leadership & VIP Visit", Master_Event_Tracker_2026!$S$3:$S$5000, "Confirmed (Done)") -> 114 | I53: =SUMIF(Master_Event_Tracker_2026!$J$3:$J$5000, "Leadership & VIP Visit", Master_Event_Tracker_2026!$K$3:$K$5000) -> 2383 | K53: 🎓 Tier 2: Leadership Dev. | M53: People Leader Essentials, Think Like a Business, ALT | O53: 20 - 50 Pax | P53: 📨 Form Sent (Recommended) | R53: Track capability enhancement & leadership training effectiveness.
A54: Meeting Rooms (405, 506, VC) | B54: Downtown-4 | C54: =COUNTIFS(Master_Event_Tracker_2026!$H$3:$H$5000, "*MR*", Master_Event_Tracker_2026!$F$3:$F$5000, "Downtown-4") -> 32 | D54: =SUMIFS(Master_Event_Tracker_2026!$K$3:$K$5000, Master_Event_Tracker_2026!$H$3:$H$5000, "*MR*", Master_Event_Tracker_2026!$F$3:$F$5000, "Downtown-4") -> 239 | F54: Social & Team Connect | G54: =COUNTIF(Master_Event_Tracker_2026!$J$3:$J$5000, "Social & Team Connect") -> 113 | H54: =COUNTIFS(Master_Event_Tracker_2026!$J$3:$J$5000, "Social & Team Connect", Master_Event_Tracker_2026!$S$3:$S$5000, "Confirmed (Done)") -> 101 | I54: =SUMIF(Master_Event_Tracker_2026!$J$3:$J$5000, "Social & Team Connect", Master_Event_Tracker_2026!$K$3:$K$5000) -> 4948 | K54: 🎓 Tier 2: New Hire Induction | M54: New Joiners Induction, Grads Training, Immersion | O54: 25 - 70 Pax | P54: 📨 Form Sent (Recommended) | R54: Ensure seamless onboarding experience & facilities support feedback.
A55: Cafeteria Breakout | B55: Downtown-3 | C55: =COUNTIFS(Master_Event_Tracker_2026!$H$3:$H$5000, "*Cafeteria*", Master_Event_Tracker_2026!$F$3:$F$5000, "Downtown-3") -> 37 | D55: =SUMIFS(Master_Event_Tracker_2026!$K$3:$K$5000, Master_Event_Tracker_2026!$H$3:$H$5000, "*Cafeteria*", Master_Event_Tracker_2026!$F$3:$F$5000, "Downtown-3") -> 4017 | F55: Tech & Innovation | G55: =COUNTIF(Master_Event_Tracker_2026!$J$3:$J$5000, "Tech & Innovation") -> 64 | H55: =COUNTIFS(Master_Event_Tracker_2026!$J$3:$J$5000, "Tech & Innovation", Master_Event_Tracker_2026!$S$3:$S$5000, "Confirmed (Done)") -> 54 | I55: =SUMIF(Master_Event_Tracker_2026!$J$3:$J$5000, "Tech & Innovation", Master_Event_Tracker_2026!$K$3:$K$5000) -> 3052 | K55: ⚪ Tier 3: VIP / AU Visits | M55: AU Visitors & Senior Executive Visits (Sweta M, Allan Ha) | O55: 1 - 5 Pax | P55: ⚪ Not Required (Excluded) | R55: Escorted executive meetings; survey collection is NOT applicable.
A56: Breakout Area | B56: Downtown-3 | C56: =COUNTIFS(Master_Event_Tracker_2026!$H$3:$H$5000, "*Breakout*", Master_Event_Tracker_2026!$F$3:$F$5000, "Downtown-3") -> 212 | D56: =SUMIFS(Master_Event_Tracker_2026!$K$3:$K$5000, Master_Event_Tracker_2026!$H$3:$H$5000, "*Breakout*", Master_Event_Tracker_2026!$F$3:$F$5000, "Downtown-3") -> 9153 | F56: Dry Run & Rehearsal | G56: =COUNTIF(Master_Event_Tracker_2026!$J$3:$J$5000, "Dry Run & Rehearsal") -> 3 | H56: =COUNTIFS(Master_Event_Tracker_2026!$J$3:$J$5000, "Dry Run & Rehearsal", Master_Event_Tracker_2026!$S$3:$S$5000, "Confirmed (Done)") -> 3 | I56: =SUMIF(Master_Event_Tracker_2026!$J$3:$J$5000, "Dry Run & Rehearsal", Master_Event_Tracker_2026!$K$3:$K$5000) -> 5 | K56: ⚪ Tier 3: Assessments | M56: Codility Assessments, Technical Tests, Hiring Drives | O56: 20 - 50 Pax | P56: ⚪ Not Required (Excluded) | R56: Recruitment technical assessments; feedback survey is NOT applicable.
A57: Meeting Rooms (107, 305/306) | B57: Downtown-3 | C57: =COUNTIFS(Master_Event_Tracker_2026!$H$3:$H$5000, "*MR*", Master_Event_Tracker_2026!$F$3:$F$5000, "Downtown-3") -> 85 | D57: =SUMIFS(Master_Event_Tracker_2026!$K$3:$K$5000, Master_Event_Tracker_2026!$H$3:$H$5000, "*MR*", Master_Event_Tracker_2026!$F$3:$F$5000, "Downtown-3") -> 2428 | F57: Team Meeting & Workshop | G57: =COUNTIF(Master_Event_Tracker_2026!$J$3:$J$5000, "Team Meeting & Workshop") -> 919 | H57: =COUNTIFS(Master_Event_Tracker_2026!$J$3:$J$5000, "Team Meeting & Workshop", Master_Event_Tracker_2026!$S$3:$S$5000, "Confirmed (Done)") -> 485 | I57: =SUMIF(Master_Event_Tracker_2026!$J$3:$J$5000, "Team Meeting & Workshop", Master_Event_Tracker_2026!$K$3:$K$5000) -> 14678 | K57: ⚪ Tier 3: Logistics & Routine | M57: Visitor Lunch setups, Bank Helpdesk, Daily Standups | O57: 1 - 15 Pax | P57: ⚪ Not Required (Excluded) | R57: Routine facilities operational tasks; feedback surveys are excluded.
A58: Top Venues Subtotal | C58: =SUM(C49:C57) -> 853 | D58: =SUM(D49:D57) -> 45008 | F58: Total Events Tracked | G58: =SUM(G49:G57) -> 1857 | H58: =SUM(H49:H57) -> 1192 | I58: =SUM(I49:I57) -> 58228 | K58: 💡 RULE SUMMARY: Feedback is required for Big Events (100+ Pax) & major workshops; routine syncs, AU visits & hiring tests are marked 'Not Required'.
A61: ⚡ PRIORITY ACTION ITEMS: UPCOMING PENDING CALENDAR BOOKINGS (POST AUG 21) | K61: 📊 LIVE AUTOMATED FEEDBACK & EVENT SCALE PERFORMANCE
A62: Event ID | B62: Date | C62: Day | D62: Building | E62: Location | F62: Event Title | G62: Pax | H62: Booked By | I62: Status | K62: Operations Breakdown | M62: Total Events | O62: 🟢 Done | P62: 📨 Form Sent | R62: ⚪ Not Required | S62: Feedback %
A63: EVT-2026-1117 | B63: 46260 | C63: Wed | D63: Downtown-4 | E63: L-5 | F63: Grads training | G63: 50 | H63: Pragyasingh.kadyan@nab.com.au | I63: 🟡 Pending Booking | K63: 🌟 Big Events (100+ Pax) | M63: =COUNTIF(Master_Event_Tracker_2026!$L$3:$L$5000, "Big Event") -> 148 | O63: =COUNTIFS(Master_Event_Tracker_2026!$L$3:$L$5000, "Big Event", Master_Event_Tracker_2026!$S$3:$S$5000, "Confirmed (Done)") -> 112 | P63: =COUNTIFS(Master_Event_Tracker_2026!$L$3:$L$5000, "Big Event", Master_Event_Tracker_2026!$T$3:$T$5000, "Form sent") -> 8 | R63: =COUNTIFS(Master_Event_Tracker_2026!$L$3:$L$5000, "Big Event", Master_Event_Tracker_2026!$T$3:$T$5000, "Not Required") -> 140 | S63: =IFERROR(P63/O63, 0) -> 0.071428571
A64: EVT-2026-1118 | B64: 46260 | C64: Wed | D64: Downtown-4 | E64: L-4 | F64: Grads training | G64: 25 | H64: Ekta.sahrma@nab.com.au | I64: 🟡 Pending Booking | K64: 👥 Small Events (<100 Pax) | M64: =COUNTIF(Master_Event_Tracker_2026!$L$3:$L$5000, "Small Event") -> 1709 | O64: =COUNTIFS(Master_Event_Tracker_2026!$L$3:$L$5000, "Small Event", Master_Event_Tracker_2026!$S$3:$S$5000, "Confirmed (Done)") -> 1080 | P64: =COUNTIFS(Master_Event_Tracker_2026!$L$3:$L$5000, "Small Event", Master_Event_Tracker_2026!$T$3:$T$5000, "Form sent") -> 41 | R64: =COUNTIFS(Master_Event_Tracker_2026!$L$3:$L$5000, "Small Event", Master_Event_Tracker_2026!$T$3:$T$5000, "Not Required") -> 1668 | S64: =IFERROR(P64/O64, 0) -> 0.037962963
A65: EVT-2026-1122 | B65: 46260 | C65: Wed | D65: Downtown-4 | E65: L-5 | F65: Potluck For Payments Ops | G65: 80 | H65: Rupika.nagpal@nab.com.au | I65: 🟡 Pending Booking | K65: 🏢 Downtown-3 Operations | M65: =COUNTIF(Master_Event_Tracker_2026!$F$3:$F$5000, "Downtown-3") -> 621 | O65: =COUNTIFS(Master_Event_Tracker_2026!$F$3:$F$5000, "Downtown-3", Master_Event_Tracker_2026!$S$3:$S$5000, "Confirmed (Done)") -> 394 | P65: =COUNTIFS(Master_Event_Tracker_2026!$F$3:$F$5000, "Downtown-3", Master_Event_Tracker_2026!$T$3:$T$5000, "Form sent") -> 12 | R65: =COUNTIFS(Master_Event_Tracker_2026!$F$3:$F$5000, "Downtown-3", Master_Event_Tracker_2026!$T$3:$T$5000, "Not Required") -> 609 | S65: =IFERROR(P65/O65, 0) -> 0.030456853
A66: EVT-2026-1126 | B66: 46261 | C66: Thu | D66: Downtown-4 | E66: L-5 | F66: Codility Assesment | G66: 50 | H66: Rupika.nagpal@nab.com.au | I66: 🟡 Pending Booking | K66: 🏢 Downtown-4 Operations | M66: =COUNTIF(Master_Event_Tracker_2026!$F$3:$F$5000, "Downtown-4") -> 1236 | O66: =COUNTIFS(Master_Event_Tracker_2026!$F$3:$F$5000, "Downtown-4", Master_Event_Tracker_2026!$S$3:$S$5000, "Confirmed (Done)") -> 798 | P66: =COUNTIFS(Master_Event_Tracker_2026!$F$3:$F$5000, "Downtown-4", Master_Event_Tracker_2026!$T$3:$T$5000, "Form sent") -> 37 | R66: =COUNTIFS(Master_Event_Tracker_2026!$F$3:$F$5000, "Downtown-4", Master_Event_Tracker_2026!$T$3:$T$5000, "Not Required") -> 1199 | S66: =IFERROR(P66/O66, 0) -> 0.046365915
A67: EVT-2026-1130 | B67: 46262 | C67: Fri | D67: Downtown-4 | E67: L-5 | F67: Codility Assesment | G67: 50 | H67: Tarun.bajaj@nab.com.au | I67: 🟡 Pending Booking | K67: 🏆 Full Year Combined Total | M67: =COUNTIF(Master_Event_Tracker_2026!$L$3:$L$5000, "<>") -> 1857 | O67: =COUNTIF(Master_Event_Tracker_2026!$S$3:$S$5000, "Confirmed (Done)") -> 1192 | P67: =COUNTIF(Master_Event_Tracker_2026!$T$3:$T$5000, "Form sent") -> 49 | R67: =COUNTIF(Master_Event_Tracker_2026!$T$3:$T$5000, "Not Required") -> 1808 | S67: =IFERROR(P67/O67, 0) -> 0.041107383
A68: EVT-2026-1135 | B68: 46265 | C68: Mon | D68: Downtown-4 | E68: L-5 | F68: Codility Assesment | G68: 50 | H68: Tarun.bajaj@nab.com.au | I68: 🟡 Pending Booking | K68: 📌 NOTE: All formulas on this dashboard update dynamically as new event records and feedback statuses are logged.
A69: EVT-2026-1140 | B69: 46266 | C69: Tue | D69: Downtown-4 | E69: L-1 | F69: Townhall Session | G69: 100 | H69: Operations Team | I69: 🟡 Pending Booking
A70: EVT-2026-1145 | B70: 46268 | C70: Thu | D70: Downtown-4 | E70: L-5 | F70: Tech Enablement Workshop | G70: 60 | H70: Tech Lead | I70: 🟡 Pending Booking
A71: EVT-2026-1150 | B71: 46272 | C71: Mon | D71: Downtown-3 | E71: MR-305 & 306 | F71: New Joiners Induction | G71: 40 | H71: Deshraj | I71: 🟡 Pending Booking
A72: EVT-2026-1155 | B72: 46275 | C72: Thu | D72: Downtown-3 | E72: Cafeteria | F72: Quarterly R&R Meet | G72: 75 | H72: HR Team | I72: 🟡 Pending Booking

Sheet Master_Event_Tracker_2026
A1: 🏠 ⮌ BACK TO DASHBOARD | D1: MASTER EVENT OPERATIONS DATABASE • FULL YEAR 2026 (DOWNTOWN-3 & DOWNTOWN-4) | Q1: 🟢 Green: Confirmed | 🟡 Yellow: Pending | 🔴 Red: Canceled
A2: Event ID | B2: Year | C2: Month | D2: Event Date | E2: Day | F2: Building | G2: Floor | H2: Location | I2: Event Title / Purpose | J2: Category | K2: Capacity / Pax | L2: Event Scale | M2: Start Time | N2: End Time | O2: F&B Support | P2: Logistic Support | Q2: Booked By | R2: Requester Email | S2: Calendar Booking Status | T2: Feedback Form | U2: Booking Date | V2: Remarks | W2: Booking Taken By
A3: =IF(OR(D3<>"",H3<>"",I3<>"",Q3<>"",S3<>""), "EVT-" & TEXT(B3, "0000") & "-" & TEXT(COUNTIF(OFFSET($A$1, 1, 0, ROW()-2, 1), "EVT*") + 1, "0000"), "") -> EVT-2026-0001 | B3: 2026 | C3: Jan | D3: 46023 | E3: Thu | F3: Downtown-3 | G3: General | J3: Team Meeting & Workshop | K3: 0 | L3: Small Event | S3: Confirmed (Done) | T3: Not Required
A4: =IF(OR(D4<>"",H4<>"",I4<>"",Q4<>"",S4<>""), "EVT-" & TEXT(B4, "0000") & "-" & TEXT(COUNTIF(OFFSET($A$1, 1, 0, ROW()-2, 1), "EVT*") + 1, "0000"), "") -> EVT-2026-0002 | B4: 2026 | C4: Jan | D4: 46024 | E4: Fri | F4: Downtown-3 | G4: General | J4: Team Meeting & Workshop | K4: 0 | L4: Small Event | S4: Confirmed (Done) | T4: Not Required
A5: =IF(OR(D5<>"",H5<>"",I5<>"",Q5<>"",S5<>""), "EVT-" & TEXT(B5, "0000") & "-" & TEXT(COUNTIF(OFFSET($A$1, 1, 0, ROW()-2, 1), "EVT*") + 1, "0000"), "") -> EVT-2026-0003 | B5: 2026 | C5: Jan | D5: 46025 | E5: Sat | F5: Downtown-3 | G5: General | J5: Team Meeting & Workshop | K5: 0 | L5: Small Event | S5: Confirmed (Done) | T5: Not Required
A6: =IF(OR(D6<>"",H6<>"",I6<>"",Q6<>"",S6<>""), "EVT-" & TEXT(B6, "0000") & "-" & TEXT(COUNTIF(OFFSET($A$1, 1, 0, ROW()-2, 1), "EVT*") + 1, "0000"), "") -> EVT-2026-0004 | B6: 2026 | C6: Jan | D6: 46026 | E6: Sun | F6: Downtown-3 | G6: General | J6: Team Meeting & Workshop | K6: 0 | L6: Small Event | S6: Confirmed (Done) | T6: Not Required
A7: =IF(OR(D7<>"",H7<>"",I7<>"",Q7<>"",S7<>""), "EVT-" & TEXT(B7, "0000") & "-" & TEXT(COUNTIF(OFFSET($A$1, 1, 0, ROW()-2, 1), "EVT*") + 1, "0000"), "") -> EVT-2026-0005 | B7: 2026 | C7: Jan | D7: 46027 | E7: Mon | F7: Downtown-3 | G7: L-5 | H7: MR-305 & 306 | I7: Induction Session | J7: Induction & Onboarding | K7: 35 | L7: Small Event | M7: 08:00 AM | N7: 05:00 PM | O7: Lunch | Q7: Deshraj | S7: Confirmed (Done) | T7: Not Required | U7: 46001 | V7: Classroom set up with power extension-
A8: =IF(OR(D8<>"",H8<>"",I8<>"",Q8<>"",S8<>""), "EVT-" & TEXT(B8, "0000") & "-" & TEXT(COUNTIF(OFFSET($A$1, 1, 0, ROW()-2, 1), "EVT*") + 1, "0000"), "") -> EVT-2026-0006 | B8: 2026 | C8: Jan | D8: 46027 | E8: Mon | F8: Downtown-3 | G8: General | H8: Breakout Area | I8: Induction Session | J8: Induction & Onboarding | K8: 35 | L8: Small Event | M8: 08:00 AM | N8: 05:00 PM | O8: Lunch | Q8: Deshraj | S8: Confirmed (Done) | T8: Not Required | V8: Classroom set up with power extension-
A9: =IF(OR(D9<>"",H9<>"",I9<>"",Q9<>"",S9<>""), "EVT-" & TEXT(B9, "0000") & "-" & TEXT(COUNTIF(OFFSET($A$1, 1, 0, ROW()-2, 1), "EVT*") + 1, "0000"), "") -> EVT-2026-0007 | B9: 2026 | C9: Jan | D9: 46028 | E9: Tue | F9: Downtown-3 | G9: General | J9: Team Meeting & Workshop | K9: 0 | L9: Small Event | S9: Confirmed (Done) | T9: Not Required
A10: =IF(OR(D10<>"",H10<>"",I10<>"",Q10<>"",S10<>""), "EVT-" & TEXT(B10, "0000") & "-" & TEXT(COUNTIF(OFFSET($A$1, 1, 0, ROW()-2, 1), "EVT*") + 1, "0000"), "") -> EVT-2026-0008 | B10: 2026 | C10: Jan | D10: 46029 | E10: Wed | F10: Downtown-3 | G10: General | J10: Team Meeting & Workshop | K10: 0 | L10: Small Event | S10: Confirmed (Done) | T10: Not Required
A11: =IF(OR(D11<>"",H11<>"",I11<>"",Q11<>"",S11<>""), "EVT-" & TEXT(B11, "0000") & "-" & TEXT(COUNTIF(OFFSET($A$1, 1, 0, ROW()-2, 1), "EVT*") + 1, "0000"), "") -> EVT-2026-0009 | B11: 2026 | C11: Jan | D11: 46030 | E11: Thu | F11: Downtown-3 | G11: General | J11: Team Meeting & Workshop | K11: 0 | L11: Small Event | S11: Confirmed (Done) | T11: Not Required
A12: =IF(OR(D12<>"",H12<>"",I12<>"",Q12<>"",S12<>""), "EVT-" & TEXT(B12, "0000") & "-" & TEXT(COUNTIF(OFFSET($A$1, 1, 0, ROW()-2, 1), "EVT*") + 1, "0000"), "") -> EVT-2026-0010 | B12: 2026 | C12: Jan | D12: 46031 | E12: Fri | F12: Downtown-3 | G12: General | J12: Team Meeting & Workshop | K12: 0 | L12: Small Event | S12: Confirmed (Done) | T12: Not Required
A13: =IF(OR(D13<>"",H13<>"",I13<>"",Q13<>"",S13<>""), "EVT-" & TEXT(B13, "0000") & "-" & TEXT(COUNTIF(OFFSET($A$1, 1, 0, ROW()-2, 1), "EVT*") + 1, "0000"), "") -> EVT-2026-0011 | B13: 2026 | C13: Jan | D13: 46032 | E13: Sat | F13: Downtown-3 | G13: L-5 | H13: MR-305 & 306 | I13: Driver's Training | J13: Training & Enablement | K13: 20 | L13: Small Event | M13: 10:00 AM | N13: 01:00 PM | O13: Snacks | Q13: Prem Chaudhary | S13: Confirmed (Done) | T13: Not Required | V13: Arranged the snacks- Cup Cakes, Samosa and tea
A14: =IF(OR(D14<>"",H14<>"",I14<>"",Q14<>"",S14<>""), "EVT-" & TEXT(B14, "0000") & "-" & TEXT(COUNTIF(OFFSET($A$1, 1, 0, ROW()-2, 1), "EVT*") + 1, "0000"), "") -> EVT-2026-0012 | B14: 2026 | C14: Jan | D14: 46032 | E14: Sat | F14: Downtown-3 | G14: General | H14: Hiring drive | I14: ZONE C, D and E | J14: Assessment & Hiring | K14: 0 | L14: Small Event | M14: 08:30 AM | N14: 05:00 PM | Q14: Manoj Thakral | S14: Confirmed (Done) | T14: Not Required | V14: List will be shared shortly.
A15: =IF(OR(D15<>"",H15<>"",I15<>"",Q15<>"",S15<>""), "EVT-" & TEXT(B15, "0000") & "-" & TEXT(COUNTIF(OFFSET($A$1, 1, 0, ROW()-2, 1), "EVT*") + 1, "0000"), "") -> EVT-2026-0013 | B15: 2026 | C15: Jan | D15: 46033 | E15: Sun | F15: Downtown-3 | G15: General | J15: Team Meeting & Workshop | K15: 0 | L15: Small Event | S15: Confirmed (Done) | T15: Not Required
A16: =IF(OR(D16<>"",H16<>"",I16<>"",Q16<>"",S16<>""), "EVT-" & TEXT(B16, "0000") & "-" & TEXT(COUNTIF(OFFSET($A$1, 1, 0, ROW()-2, 1), "EVT*") + 1, "0000"), "") -> EVT-2026-0014 | B16: 2026 | C16: Jan | D16: 46034 | E16: Mon | F16: Downtown-3 | G16: L-5 | H16: MR-305 & 306 | I16: Inductin Session | J16: Team Meeting & Workshop | K16: 40 | L16: Small Event | M16: 08:00 AM | N16: 05:00 PM | O16: Lunch | Q16: Deshraj | S16: Confirmed (Done) | T16: Not Required | V16: Classroom set up with power extension
A17: =IF(OR(D17<>"",H17<>"",I17<>"",Q17<>"",S17<>""), "EVT-" & TEXT(B17, "0000") & "-" & TEXT(COUNTIF(OFFSET($A$1, 1, 0, ROW()-2, 1), "EVT*") + 1, "0000"), "") -> EVT-2026-0015 | B17: 2026 | C17: Jan | D17: 46034 | E17: Mon | F17: Downtown-3 | G17: General | H17: Breakout Area | I17: Inductin Session | J17: Team Meeting & Workshop | K17: 20 | L17: Small Event | M17: 08:00 AM | N17: 05:00 PM | O17: Lunch | Q17: Deshraj | S17: Confirmed (Done) | T17: Not Required | V17: Classroom set up and require one table and one chair for the facilitator
A18: =IF(OR(D18<>"",H18<>"",I18<>"",Q18<>"",S18<>""), "EVT-" & TEXT(B18, "0000") & "-" & TEXT(COUNTIF(OFFSET($A$1, 1, 0, ROW()-2, 1), "EVT*") + 1, "0000"), "") -> EVT-2026-0016 | B18: 2026 | C18: Jan | D18: 46035 | E18: Tue | F18: Downtown-3 | G18: General | J18: Team Meeting & Workshop | K18: 0 | L18: Small Event | S18: Confirmed (Done) | T18: Not Required | V18: TBC
A19: =IF(OR(D19<>"",H19<>"",I19<>"",Q19<>"",S19<>""), "EVT-" & TEXT(B19, "0000") & "-" & TEXT(COUNTIF(OFFSET($A$1, 1, 0, ROW()-2, 1), "EVT*") + 1, "0000"), "") -> EVT-2026-0017 | B19: 2026 | C19: Jan | D19: 46036 | E19: Wed | F19: Downtown-3 | G19: L-5 | H19: MR-305 & 306 | I19: Inductin Session | J19: Team Meeting & Workshop | K19: 25 | L19: Small Event | M19: 08:00 AM | N19: 05:00 PM | O19: Lunch | Q19: Deshraj | S19: Confirmed (Done) | T19: Not Required
A20: =IF(OR(D20<>"",H20<>"",I20<>"",Q20<>"",S20<>""), "EVT-" & TEXT(B20, "0000") & "-" & TEXT(COUNTIF(OFFSET($A$1, 1, 0, ROW()-2, 1), "EVT*") + 1, "0000"), "") -> EVT-2026-0018 | B20: 2026 | C20: Jan | D20: 46036 | E20: Wed | F20: Downtown-3 | G20: General | H20: Breakout Area | J20: Team Meeting & Workshop | K20: 0 | L20: Small Event | S20: Confirmed (Done) | T20: Not Required
A21: =IF(OR(D21<>"",H21<>"",I21<>"",Q21<>"",S21<>""), "EVT-" & TEXT(B21, "0000") & "-" & TEXT(COUNTIF(OFFSET($A$1, 1, 0, ROW()-2, 1), "EVT*") + 1, "0000"), "") -> EVT-2026-0019 | B21: 2026 | C21: Jan | D21: 46037 | E21: Thu | F21: Downtown-3 | G21: L-5 | H21: MR-305 & 306 | I21: Communicating with Impact (FCO + Nom) | J21: Team Meeting & Workshop | K21: 25 | L21: Small Event | M21: 02:30 PM | N21: 04:30 PM | Q21: Deshraj | S21: Confirmed (Done) | T21: Not Required | V21: Cluster Set up- add onlyone chair and one chair+table for the facilitator
A22: =IF(OR(D22<>"",H22<>"",I22<>"",Q22<>"",S22<>""), "EVT-" & TEXT(B22, "0000") & "-" & TEXT(COUNTIF(OFFSET($A$1, 1, 0, ROW()-2, 1), "EVT*") + 1, "0000"), "") -> EVT-2026-0020 | B22: 2026 | C22: Jan | D22: 46037 | E22: Thu | F22: Downtown-3 | G22: General | H22: Cafeteria + Breakout Area | I22: Risk Awareness session for Enterprise Data team | J22: Team Meeting & Workshop | K22: 200 | L22: Big Event | M22: 03:00 PM | N22: 04:00 PM | Q22: Maanshu Chugh | S22: Confirmed (Done) | T22: Not Required | U22: 46028 | V22: Theater style
A23: =IF(OR(D23<>"",H23<>"",I23<>"",Q23<>"",S23<>""), "EVT-" & TEXT(B23, "0000") & "-" & TEXT(COUNTIF(OFFSET($A$1, 1, 0, ROW()-2, 1), "EVT*") + 1, "0000"), "") -> EVT-2026-0021 | B23: 2026 | C23: Jan | D23: 46038 | E23: Fri | F23: Downtown-3 | G23: General | H23: Cafeteria | I23: Culture Immersion NH + Nominations | J23: Team Meeting & Workshop | K23: 50 | L23: Small Event | M23: 03:00 PM | N23: 04:30 PM | Q23: Deshraj | S23: Confirmed (Done) | T23: Not Required | V23: Theater style
A24: =IF(OR(D24<>"",H24<>"",I24<>"",Q24<>"",S24<>""), "EVT-" & TEXT(B24, "0000") & "-" & TEXT(COUNTIF(OFFSET($A$1, 1, 0, ROW()-2, 1), "EVT*") + 1, "0000"), "") -> EVT-2026-0022 | B24: 2026 | C24: Jan | D24: 46039 | E24: Sat | F24: Downtown-3 | G24: General | I24: Hiring Drive | J24: Assessment & Hiring | K24: 0 | L24: Small Event | M24: 08:00 AM | N24: 05:00 PM | Q24: Mohit Mishra/ Monika Nigam | S24: Confirmed (Done) | T24: Not Required
A25: =IF(OR(D25<>"",H25<>"",I25<>"",Q25<>"",S25<>""), "EVT-" & TEXT(B25, "0000") & "-" & TEXT(COUNTIF(OFFSET($A$1, 1, 0, ROW()-2, 1), "EVT*") + 1, "0000"), "") -> EVT-2026-0023 | B25: 2026 | C25: Jan | D25: 46040 | E25: Sun | F25: Downtown-3 | G25: General | J25: Team Meeting & Workshop | K25: 0 | L25: Small Event | S25: Confirmed (Done) | T25: Not Required
A26: =IF(OR(D26<>"",H26<>"",I26<>"",Q26<>"",S26<>""), "EVT-" & TEXT(B26, "0000") & "-" & TEXT(COUNTIF(OFFSET($A$1, 1, 0, ROW()-2, 1), "EVT*") + 1, "0000"), "") -> EVT-2026-0024 | B26: 2026 | C26: Jan | D26: 46041 | E26: Mon | F26: Downtown-3 | G26: L-5 | H26: MR-305 & 306 | I26: Induction Session (perm -305 and 306) contractors- (breakout area) | J26: Induction & Onboarding | K26: 70 | L26: Small Event | M26: 08:00 AM | N26: 05:00 PM | O26: Lunch | Q26: Deshraj | S26: Confirmed (Done) | T26: Not Required | U26: 46001 | V26: Classroom set up
A27: =IF(OR(D27<>"",H27<>"",I27<>"",Q27<>"",S27<>""), "EVT-" & TEXT(B27, "0000") & "-" & TEXT(COUNTIF(OFFSET($A$1, 1, 0, ROW()-2, 1), "EVT*") + 1, "0000"), "") -> EVT-2026-0025 | B27: 2026 | C27: Jan | D27: 46041 | E27: Mon | F27: Downtown-3 | G27: General | H27: Breakout Area | J27: Team Meeting & Workshop | K27: 0 | L27: Small Event | Q27: Deshraj | S27: Confirmed (Done) | T27: Not Required | V27: Classroom set up
A28: =IF(OR(D28<>"",H28<>"",I28<>"",Q28<>"",S28<>""), "EVT-" & TEXT(B28, "0000") & "-" & TEXT(COUNTIF(OFFSET($A$1, 1, 0, ROW()-2, 1), "EVT*") + 1, "0000"), "") -> EVT-2026-0026 | B28: 2026 | C28: Jan | D28: 46042 | E28: Tue | F28: Downtown-3 | G28: L-5 | H28: MR-305 & 306 | I28: ALT Workshop 2 | J28: Team Meeting & Workshop | K28: 0 | L28: Small Event | M28: 08:30 AM | N28: 04:30 PM | O28: Tea, cookies and Food Arrnagement | Q28: Deshraj | S28: Confirmed (Done) | T28: Not Required | U28: 46364 | V28: Cluster Set Up- Two white boards required
A29: =IF(OR(D29<>"",H29<>"",I29<>"",Q29<>"",S29<>""), "EVT-" & TEXT(B29, "0000") & "-" & TEXT(COUNTIF(OFFSET($A$1, 1, 0, ROW()-2, 1), "EVT*") + 1, "0000"), "") -> EVT-2026-0027 | B29: 2026 | C29: Jan | D29: 46042 | E29: Tue | F29: Downtown-3 | G29: General | J29: Team Meeting & Workshop | K29: 0 | L29: Small Event | S29: Confirmed (Done) | T29: Not Required | V29: Cluster set up
A30: =IF(OR(D30<>"",H30<>"",I30<>"",Q30<>"",S30<>""), "EVT-" & TEXT(B30, "0000") & "-" & TEXT(COUNTIF(OFFSET($A$1, 1, 0, ROW()-2, 1), "EVT*") + 1, "0000"), "") -> EVT-2026-0028 | B30: 2026 | C30: Jan | D30: 46042 | E30: Tue | F30: Downtown-3 | G30: General | H30: Breakout Area | I30: Internal Sourcing Training | J30: Training & Enablement | K30: 30 | L30: Small Event | M30: 02:00 PM | N30: 04:00 PM | Q30: Tushar Mudgil | S30: Confirmed (Done) | T30: Not Required | U30: 46035 | V30: Theater set up
A31: =IF(OR(D31<>"",H31<>"",I31<>"",Q31<>"",S31<>""), "EVT-" & TEXT(B31, "0000") & "-" & TEXT(COUNTIF(OFFSET($A$1, 1, 0, ROW()-2, 1), "EVT*") + 1, "0000"), "") -> EVT-2026-0029 | B31: 2026 | C31: Jan | D31: 46043 | E31: Wed | F31: Downtown-3 | G31: General | H31: Breakout Area | I31: Internal Sourcing Training | J31: Training & Enablement | K31: 30 | L31: Small Event | M31: 02:00 PM | N31: 04:00 PM | Q31: Tushar Mudgil | S31: Canceled | T31: Not Required | U31: 46035 | V31: Theater set up
A32: =IF(OR(D32<>"",H32<>"",I32<>"",Q32<>"",S32<>""), "EVT-" & TEXT(B32, "0000") & "-" & TEXT(COUNTIF(OFFSET($A$1, 1, 0, ROW()-2, 1), "EVT*") + 1, "0000"), "") -> EVT-2026-0030 | B32: 2026 | C32: Jan | D32: 46044 | E32: Thu | F32: Downtown-3 | G32: General | H32: Breakou Area | I32: Q1 R&R Ceremony (Business Lending) | J32: Team Meeting & Workshop | K32: 70 | L32: Small Event | M32: 09:30 AM | N32: 10:15 AM | Q32: Jackie Jose | S32: Canceled | T32: Not Required | U32: 46035 | V32: Theater style | W32: Moved to DT-4 Hackable space
A33: =IF(OR(D33<>"",H33<>"",I33<>"",Q33<>"",S33<>""), "EVT-" & TEXT(B33, "0000") & "-" & TEXT(COUNTIF(OFFSET($A$1, 1, 0, ROW()-2, 1), "EVT*") + 1, "0000"), "") -> EVT-2026-0031 | B33: 2026 | C33: Jan | D33: 46044 | E33: Thu | F33: Downtown-3 | G33: General | J33: Team Meeting & Workshop | K33: 0 | L33: Small Event | S33: Confirmed (Done) | T33: Not Required | V33: Theater style
A34: =IF(OR(D34<>"",H34<>"",I34<>"",Q34<>"",S34<>""), "EVT-" & TEXT(B34, "0000") & "-" & TEXT(COUNTIF(OFFSET($A$1, 1, 0, ROW()-2, 1), "EVT*") + 1, "0000"), "") -> EVT-2026-0032 | B34: 2026 | C34: Jan | D34: 46044 | E34: Thu | F34: Downtown-3 | G34: General | H34: Breakou Area | I34: DCO Fun Crew – Republic Day Event” | J34: Team Meeting & Workshop | K34: 60 | L34: Small Event | M34: 03:00 PM | N34: 04:30 PM | Q34: Arpan Relan | S34: Confirmed (Done) | T34: Not Required | U34: 46027 | V34: Theater Style
A35: =IF(OR(D35<>"",H35<>"",I35<>"",Q35<>"",S35<>""), "EVT-" & TEXT(B35, "0000") & "-" & TEXT(COUNTIF(OFFSET($A$1, 1, 0, ROW()-2, 1), "EVT*") + 1, "0000"), "") -> EVT-2026-0033 | B35: 2026 | C35: Jan | D35: 46045 | E35: Fri | F35: Downtown-3 | G35: General | H35: Social Hub 2 | I35: Lunch | J35: Social & Team Connect | K35: 0 | L35: Small Event | Q35: Sameer Duttta | S35: Confirmed (Done) | T35: Not Required | U35: 46044 | V35: Sameer will share the details /
A36: =IF(OR(D36<>"",H36<>"",I36<>"",Q36<>"",S36<>""), "EVT-" & TEXT(B36, "0000") & "-" & TEXT(COUNTIF(OFFSET($A$1, 1, 0, ROW()-2, 1), "EVT*") + 1, "0000"), "") -> EVT-2026-0034 | B36: 2026 | C36: Jan | D36: 46046 | E36: Sat | F36: Downtown-3 | G36: General | I36: Hiring Drive | J36: Assessment & Hiring | K36: 0 | L36: Small Event | M36: 08:00 AM | N36: 05:00 PM | Q36: Eisha Mittal | S36: Confirmed (Done) | T36: Not Required | U36: 46031
A37: =IF(OR(D37<>"",H37<>"",I37<>"",Q37<>"",S37<>""), "EVT-" & TEXT(B37, "0000") & "-" & TEXT(COUNTIF(OFFSET($A$1, 1, 0, ROW()-2, 1), "EVT*") + 1, "0000"), "") -> EVT-2026-0035 | B37: 2026 | C37: Jan | D37: 46047 | E37: Sun | F37: Downtown-3 | G37: General | J37: Team Meeting & Workshop | K37: 0 | L37: Small Event | S37: Confirmed (Done) | T37: Not Required
A38: =IF(OR(D38<>"",H38<>"",I38<>"",Q38<>"",S38<>""), "EVT-" & TEXT(B38, "0000") & "-" & TEXT(COUNTIF(OFFSET($A$1, 1, 0, ROW()-2, 1), "EVT*") + 1, "0000"), "") -> EVT-2026-0036 | B38: 2026 | C38: Jan | D38: 46049 | E38: Tue | F38: Downtown-3 | G38: L-5 | H38: MR-305 and 306 | I38: Induction Session (perm -305 and 306) contractors- (breakout area) | J38: Induction & Onboarding | K38: 0 | L38: Small Event | M38: 08:00 AM | N38: 05:00 PM | O38: Lunch | Q38: Deshraj | S38: Confirmed (Done) | T38: Not Required | V38: Classroom set up
A39: =IF(OR(D39<>"",H39<>"",I39<>"",Q39<>"",S39<>""), "EVT-" & TEXT(B39, "0000") & "-" & TEXT(COUNTIF(OFFSET($A$1, 1, 0, ROW()-2, 1), "EVT*") + 1, "0000"), "") -> EVT-2026-0037 | B39: 2026 | C39: Jan | D39: 46049 | E39: Tue | F39: Downtown-3 | G39: General | H39: Breakout Area | I39: DL Workshop | J39: Team Meeting & Workshop | K39: 0 | L39: Small Event | M39: 08:00 AM | N39: 05:00 PM | O39: Snacks+Lunch | Q39: Deshraj | S39: Confirmed (Done) | T39: Not Required | V39: Classroom set up
A40: =IF(OR(D40<>"",H40<>"",I40<>"",Q40<>"",S40<>""), "EVT-" & TEXT(B40, "0000") & "-" & TEXT(COUNTIF(OFFSET($A$1, 1, 0, ROW()-2, 1), "EVT*") + 1, "0000"), "") -> EVT-2026-0038 | B40: 2026 | C40: Jan | D40: 46050 | E40: Wed | F40: Downtown-3 | G40: L-5 | H40: MR-305 and 306 | I40: DL Workshop | J40: Team Meeting & Workshop | K40: 0 | L40: Small Event | M40: 08:00 AM | N40: 05:00 PM | O40: Snacks+Lunch | Q40: Deshraj | S40: Confirmed (Done) | T40: Not Required | V40: Classroom set up
A41: =IF(OR(D41<>"",H41<>"",I41<>"",Q41<>"",S41<>""), "EVT-" & TEXT(B41, "0000") & "-" & TEXT(COUNTIF(OFFSET($A$1, 1, 0, ROW()-2, 1), "EVT*") + 1, "0000"), "") -> EVT-2026-0039 | B41: 2026 | C41: Jan | D41: 46051 | E41: Thu | F41: Downtown-3 | G41: General | H41: Breakout Area | I41: All hands meeting for Enterprise Operations Tech | J41: Townhall & All-Hands | K41: 50 | L41: Small Event | M41: 11:00 AM | N41: 12:00 PM | Q41: Ajay Sutrave | S41: Confirmed (Done) | T41: Not Required | V41: Theater style
A42: =IF(OR(D42<>"",H42<>"",I42<>"",Q42<>"",S42<>""), "EVT-" & TEXT(B42, "0000") & "-" & TEXT(COUNTIF(OFFSET($A$1, 1, 0, ROW()-2, 1), "EVT*") + 1, "0000"), "") -> EVT-2026-0040 | B42: 2026 | C42: Jan | D42: 46051 | E42: Thu | F42: Downtown-3 | G42: General | H42: Cafeteria + Breakout Area | I42: Risk Awareness Session - Enterprise Technology Team | J42: Tech & Innovation | K42: 200 | L42: Big Event | M42: 03:00 PM | N42: 04:30 PM | Q42: Maanshu Chugh | S42: Confirmed (Done) | T42: Not Required | V42: Theater style
A43: =IF(OR(D43<>"",H43<>"",I43<>"",Q43<>"",S43<>""), "EVT-" & TEXT(B43, "0000") & "-" & TEXT(COUNTIF(OFFSET($A$1, 1, 0, ROW()-2, 1), "EVT*") + 1, "0000"), "") -> EVT-2026-0041 | B43: 2026 | C43: Jan | D43: 46051 | E43: Thu | F43: Downtown-3 | G43: General | H43: Breakout Area | I43: Finance Townhall | J43: Townhall & All-Hands | K43: 50 | L43: Small Event | M43: 02:00 PM | N43: 04:00 PM | Q43: Anju Verma | S43: Canceled | T43: Not Required | V43: Theater Style | W43: Moved the event on 3rd Feb'26
A44: =IF(OR(D44<>"",H44<>"",I44<>"",Q44<>"",S44<>""), "EVT-" & TEXT(B44, "0000") & "-" & TEXT(COUNTIF(OFFSET($A$1, 1, 0, ROW()-2, 1), "EVT*") + 1, "0000"), "") -> EVT-2026-0042 | B44: 2026 | C44: Jan | D44: 46052 | E44: Fri | F44: Downtown-3 | G44: General | H44: Cafeteria | I44: T&EO Global Town Halls 2026 | J44: Townhall & All-Hands | K44: 0 | L44: Small Event | M44: 09:00 AM | N44: 10:00 AM | Q44: Prerena Malik | S44: Confirmed (Done) | T44: Not Required
A45: =IF(OR(D45<>"",H45<>"",I45<>"",Q45<>"",S45<>""), "EVT-" & TEXT(B45, "0000") & "-" & TEXT(COUNTIF(OFFSET($A$1, 1, 0, ROW()-2, 1), "EVT*") + 1, "0000"), "") -> EVT-2026-0043 | B45: 2026 | C45: Jan | D45: 46052 | E45: Fri | F45: Downtown-3 | G45: General | H45: Cafeteria | I45: CQiB Felicitation | J45: Team Meeting & Workshop | K45: 180 | L45: Big Event | M45: 03:00 PM | N45: 04:00 PM | Q45: Deshraj | S45: Confirmed (Done) | T45: Not Required | U45: 46032 | V45: theater style
A46: =IF(OR(D46<>"",H46<>"",I46<>"",Q46<>"",S46<>""), "EVT-" & TEXT(B46, "0000") & "-" & TEXT(COUNTIF(OFFSET($A$1, 1, 0, ROW()-2, 1), "EVT*") + 1, "0000"), "") -> EVT-2026-0044 | B46: 2026 | C46: Jan | D46: 46053 | E46: Sat | F46: Downtown-3 | G46: L-1 | H46: No hiring drive on 31st due to the family day | J46: Assessment & Hiring | K46: 0 | L46: Small Event | S46: Confirmed (Done) | T46: Not Required
A47: =IF(OR(D47<>"",H47<>"",I47<>"",Q47<>"",S47<>""), "EVT-" & TEXT(B47, "0000") & "-" & TEXT(COUNTIF(OFFSET($A$1, 1, 0, ROW()-2, 1), "EVT*") + 1, "0000"), "") -> EVT-2026-0045 | B47: 2026 | C47: Jan | F47: Downtown-3 | G47: General | J47: Team Meeting & Workshop | K47: 0 | L47: Small Event | S47: Confirmed (Done) | T47: Not Required
A48: =IF(OR(D48<>"",H48<>"",I48<>"",Q48<>"",S48<>""), "EVT-" & TEXT(B48, "0000") & "-" & TEXT(COUNTIF(OFFSET($A$1, 1, 0, ROW()-2, 1), "EVT*") + 1, "0000"), "") -> EVT-2026-0046 | B48: 2026 | C48: Jan | F48: Downtown-3 | G48: General | J48: Team Meeting & Workshop | K48: 0 | L48: Small Event | S48: Confirmed (Done) | T48: Not Required
A49: =IF(OR(D49<>"",H49<>"",I49<>"",Q49<>"",S49<>""), "EVT-" & TEXT(B49, "0000") & "-" & TEXT(COUNTIF(OFFSET($A$1, 1, 0, ROW()-2, 1), "EVT*") + 1, "0000"), "") -> EVT-2026-0047 | B49: 2026 | C49: Jan | F49: Downtown-3 | G49: General | J49: Team Meeting & Workshop | K49: 0 | L49: Small Event | S49: Confirmed (Done) | T49: Not Required
A50: =IF(OR(D50<>"",H50<>"",I50<>"",Q50<>"",S50<>""), "EVT-" & TEXT(B50, "0000") & "-" & TEXT(COUNTIF(OFFSET($A$1, 1, 0, ROW()-2, 1), "EVT*") + 1, "0000"), "") -> EVT-2026-0048 | B50: 2026 | C50: Jan | F50: Downtown-3 | G50: General | J50: Team Meeting & Workshop | K50: 0 | L50: Small Event | S50: Confirmed (Done) | T50: Not Required
A51: =IF(OR(D51<>"",H51<>"",I51<>"",Q51<>"",S51<>""), "EVT-" & TEXT(B51, "0000") & "-" & TEXT(COUNTIF(OFFSET($A$1, 1, 0, ROW()-2, 1), "EVT*") + 1, "0000"), "") -> EVT-2026-0049 | B51: 2026 | C51: Jan | D51: 46023 | E51: Thu | F51: Downtown-4 | G51: 5th Floor | H51: Hackable Area | I51: Training | J51: Training & Enablement | K51: 35 | L51: Small Event | M51: 08:00 AM | N51: 05:00 PM | P51: nO | Q51: Binu | S51: Confirmed (Done) | T51: Not Required | U51: 45992 | V51: Classroom set up and require the Power extension
A52: =IF(OR(D52<>"",H52<>"",I52<>"",Q52<>"",S52<>""), "EVT-" & TEXT(B52, "0000") & "-" & TEXT(COUNTIF(OFFSET($A$1, 1, 0, ROW()-2, 1), "EVT*") + 1, "0000"), "") -> EVT-2026-0050 | B52: 2026 | C52: Jan | D52: 46023 | E52: Thu | F52: Downtown-4 | G52: 5th Floor | H52: Zone E Breakout Area | I52: Training | J52: Training & Enablement | K52: 35 | L52: Small Event | M52: 08:00 AM | N52: 05:00 PM | P52: nO | Q52: Binu | S52: Confirmed (Done) | T52: Not Required | U52: 45992 | V52: Classroom set up and require the Power extension
A53: =IF(OR(D53<>"",H53<>"",I53<>"",Q53<>"",S53<>""), "EVT-" & TEXT(B53, "0000") & "-" & TEXT(COUNTIF(OFFSET($A$1, 1, 0, ROW()-2, 1), "EVT*") + 1, "0000"), "") -> EVT-2026-0051 | B53: 2026 | C53: Jan | D53: 46024 | E53: Fri | F53: Downtown-4 | J53: Team Meeting & Workshop | K53: 0 | L53: Small Event | S53: Confirmed (Done) | T53: Not Required
A54: =IF(OR(D54<>"",H54<>"",I54<>"",Q54<>"",S54<>""), "EVT-" & TEXT(B54, "0000") & "-" & TEXT(COUNTIF(OFFSET($A$1, 1, 0, ROW()-2, 1), "EVT*") + 1, "0000"), "") -> EVT-2026-0052 | B54: 2026 | C54: Jan | D54: 46025 | E54: Sat | F54: Downtown-4 | J54: Team Meeting & Workshop | K54: 0 | L54: Small Event | S54: Confirmed (Done) | T54: Not Required
A55: =IF(OR(D55<>"",H55<>"",I55<>"",Q55<>"",S55<>""), "EVT-" & TEXT(B55, "0000") & "-" & TEXT(COUNTIF(OFFSET($A$1, 1, 0, ROW()-2, 1), "EVT*") + 1, "0000"), "") -> EVT-2026-0053 | B55: 2026 | C55: Jan | D55: 46026 | E55: Sun | F55: Downtown-4 | J55: Team Meeting & Workshop | K55: 0 | L55: Small Event | S55: Confirmed (Done) | T55: Not Required
A56: =IF(OR(D56<>"",H56<>"",I56<>"",Q56<>"",S56<>""), "EVT-" & TEXT(B56, "0000") & "-" & TEXT(COUNTIF(OFFSET($A$1, 1, 0, ROW()-2, 1), "EVT*") + 1, "0000"), "") -> EVT-2026-0054 | B56: 2026 | C56: Jan | D56: 46027 | E56: Mon | F56: Downtown-4 | J56: Team Meeting & Workshop | K56: 0 | L56: Small Event | S56: Confirmed (Done) | T56: Not Required
A57: =IF(OR(D57<>"",H57<>"",I57<>"",Q57<>"",S57<>""), "EVT-" & TEXT(B57, "0000") & "-" & TEXT(COUNTIF(OFFSET($A$1, 1, 0, ROW()-2, 1), "EVT*") + 1, "0000"), "") -> EVT-2026-0055 | B57: 2026 | C57: Jan | D57: 46028 | E57: Tue | F57: Downtown-4 | G57: L-4 | H57: Zone E Breakout Area | I57: Codility | J57: Assessment & Hiring | K57: 50 | L57: Small Event | M57: 01:30 PM | N57: 04:00 PM | Q57: Parul Wadhera | S57: Confirmed (Done) | T57: Not Required | U57: 46008 | V57: Classroom set up
A58: =IF(OR(D58<>"",H58<>"",I58<>"",Q58<>"",S58<>""), "EVT-" & TEXT(B58, "0000") & "-" & TEXT(COUNTIF(OFFSET($A$1, 1, 0, ROW()-2, 1), "EVT*") + 1, "0000"), "") -> EVT-2026-0056 | B58: 2026 | C58: Jan | D58: 46029 | E58: Wed | F58: Downtown-4 | J58: Team Meeting & Workshop | K58: 0 | L58: Small Event | S58: Confirmed (Done) | T58: Not Required
A59: =IF(OR(D59<>"",H59<>"",I59<>"",Q59<>"",S59<>""), "EVT-" & TEXT(B59, "0000") & "-" & TEXT(COUNTIF(OFFSET($A$1, 1, 0, ROW()-2, 1), "EVT*") + 1, "0000"), "") -> EVT-2026-0057 | B59: 2026 | C59: Jan | D59: 46030 | E59: Thu | F59: Downtown-4 | J59: Team Meeting & Workshop | K59: 0 | L59: Small Event | S59: Confirmed (Done) | T59: Not Required
A60: =IF(OR(D60<>"",H60<>"",I60<>"",Q60<>"",S60<>""), "EVT-" & TEXT(B60, "0000") & "-" & TEXT(COUNTIF(OFFSET($A$1, 1, 0, ROW()-2, 1), "EVT*") + 1, "0000"), "") -> EVT-2026-0058 | B60: 2026 | C60: Jan | D60: 46031 | E60: Fri | F60: Downtown-4 | J60: Team Meeting & Workshop | K60: 0 | L60: Small Event | S60: Confirmed (Done) | T60: Not Required
A61: =IF(OR(D61<>"",H61<>"",I61<>"",Q61<>"",S61<>""), "EVT-" & TEXT(B61, "0000") & "-" & TEXT(COUNTIF(OFFSET($A$1, 1, 0, ROW()-2, 1), "EVT*") + 1, "0000"), "") -> EVT-2026-0059 | B61: 2026 | C61: Jan | D61: 46032 | E61: Sat | F61: Downtown-4 | J61: Team Meeting & Workshop | K61: 0 | L61: Small Event | S61: Confirmed (Done) | T61: Not Required
A62: =IF(OR(D62<>"",H62<>"",I62<>"",Q62<>"",S62<>""), "EVT-" & TEXT(B62, "0000") & "-" & TEXT(COUNTIF(OFFSET($A$1, 1, 0, ROW()-2, 1), "EVT*") + 1, "0000"), "") -> EVT-2026-0060 | B62: 2026 | C62: Jan | D62: 46033 | E62: Sun | F62: Downtown-4 | J62: Team Meeting & Workshop | K62: 0 | L62: Small Event | S62: Confirmed (Done) | T62: Not Required
A63: =IF(OR(D63<>"",H63<>"",I63<>"",Q63<>"",S63<>""), "EVT-" & TEXT(B63, "0000") & "-" & TEXT(COUNTIF(OFFSET($A$1, 1, 0, ROW()-2, 1), "EVT*") + 1, "0000"), "") -> EVT-2026-0061 | B63: 2026 | C63: Jan | D63: 46034 | E63: Mon | F63: Downtown-4 | J63: Team Meeting & Workshop | K63: 0 | L63: Small Event | S63: Confirmed (Done) | T63: Not Required
A64: =IF(OR(D64<>"",H64<>"",I64<>"",Q64<>"",S64<>""), "EVT-" & TEXT(B64, "0000") & "-" & TEXT(COUNTIF(OFFSET($A$1, 1, 0, ROW()-2, 1), "EVT*") + 1, "0000"), "") -> EVT-2026-0062 | B64: 2026 | C64: Jan | D64: 46035 | E64: Tue | F64: Downtown-4 | G64: L-4 | H64: Zone E Breakout Area | I64: Codility | J64: Assessment & Hiring | K64: 50 | L64: Small Event | M64: 01:30 PM | N64: 04:00 PM | Q64: Parul Wadhera | S64: Confirmed (Done) | T64: Not Required | U64: 46008 | V64: Classroom set up
A65: =IF(OR(D65<>"",H65<>"",I65<>"",Q65<>"",S65<>""), "EVT-" & TEXT(B65, "0000") & "-" & TEXT(COUNTIF(OFFSET($A$1, 1, 0, ROW()-2, 1), "EVT*") + 1, "0000"), "") -> EVT-2026-0063 | B65: 2026 | C65: Jan | D65: 46037 | E65: Thu | F65: Downtown-4 | G65: L-4 | H65: Zone E Breakout Area | I65: Codility | J65: Assessment & Hiring | K65: 50 | L65: Small Event | M65: 01:30 PM | N65: 04:00 PM | Q65: Parul Wadhera | S65: Confirmed (Done) | T65: Not Required
A66: =IF(OR(D66<>"",H66<>"",I66<>"",Q66<>"",S66<>""), "EVT-" & TEXT(B66, "0000") & "-" & TEXT(COUNTIF(OFFSET($A$1, 1, 0, ROW()-2, 1), "EVT*") + 1, "0000"), "") -> EVT-2026-0064 | B66: 2026 | C66: Jan | D66: 46037 | E66: Thu | F66: Downtown-4 | G66: L-1 | H66: Innovation ARea | I66: Townhall | J66: Townhall & All-Hands | K66: 200 | L66: Big Event | M66: 11:00 AM | N66: 12:30 PM | Q66: Kriti Kapoor | S66: Confirmed (Done) | T66: Not Required | U66: 46036 | V66: Theater Style
A67: =IF(OR(D67<>"",H67<>"",I67<>"",Q67<>"",S67<>""), "EVT-" & TEXT(B67, "0000") & "-" & TEXT(COUNTIF(OFFSET($A$1, 1, 0, ROW()-2, 1), "EVT*") + 1, "0000"), "") -> EVT-2026-0065 | B67: 2026 | C67: Jan | D67: 46037 | E67: Thu | F67: Downtown-4 | G67: L-4 | H67: Zone E Breakout Area | I67: Codility | J67: Assessment & Hiring | K67: 50 | L67: Small Event | M67: 02:00 PM | N67: 04:00 PM | Q67: Parul Wadhera | S67: Confirmed (Done) | T67: Not Required
A68: =IF(OR(D68<>"",H68<>"",I68<>"",Q68<>"",S68<>""), "EVT-" & TEXT(B68, "0000") & "-" & TEXT(COUNTIF(OFFSET($A$1, 1, 0, ROW()-2, 1), "EVT*") + 1, "0000"), "") -> EVT-2026-0066 | B68: 2026 | C68: Jan | D68: 46038 | E68: Fri | F68: Downtown-4 | G68: L-5 | H68: Cafeteria | I68: Department Townhall | J68: Townhall & All-Hands | K68: 60 | L68: Small Event | M68: 04:00 PM | N68: 05:00 PM | Q68: Prateek Gupta | S68: Confirmed (Done) | T68: Not Required | U68: 46029 | V68: Theater style
A69: =IF(OR(D69<>"",H69<>"",I69<>"",Q69<>"",S69<>""), "EVT-" & TEXT(B69, "0000") & "-" & TEXT(COUNTIF(OFFSET($A$1, 1, 0, ROW()-2, 1), "EVT*") + 1, "0000"), "") -> EVT-2026-0067 | B69: 2026 | C69: Jan | D69: 46038 | E69: Fri | F69: Downtown-4 | G69: L-4 | H69: Zone E Breakout Area | I69: Smart Bytes | J69: Team Meeting & Workshop | K69: 30 | L69: Small Event | M69: 03:00 PM | N69: 03:30 PM | Q69: Somaya | S69: Confirmed (Done) | T69: Not Required | U69: 46029 | V69: Theater Style
A70: =IF(OR(D70<>"",H70<>"",I70<>"",Q70<>"",S70<>""), "EVT-" & TEXT(B70, "0000") & "-" & TEXT(COUNTIF(OFFSET($A$1, 1, 0, ROW()-2, 1), "EVT*") + 1, "0000"), "") -> EVT-2026-0068 | B70: 2026 | C70: Jan | D70: 46039 | E70: Sat | F70: Downtown-4 | G70: Hiring Drive | J70: Team Meeting & Workshop | K70: 0 | L70: Small Event | M70: 05:00 PM | P70: Eisha Mittal- | Q70: 2026-01-09 00:00:00 | S70: Confirmed (Done) | T70: Not Required | U70: waiting for the final number of the candidates from Mohit, if numbers are increased then we can keep Eisha hiring drive in Dt-4
A71: =IF(OR(D71<>"",H71<>"",I71<>"",Q71<>"",S71<>""), "EVT-" & TEXT(B71, "0000") & "-" & TEXT(COUNTIF(OFFSET($A$1, 1, 0, ROW()-2, 1), "EVT*") + 1, "0000"), "") -> EVT-2026-0069 | B71: 2026 | C71: Jan | D71: 46040 | E71: Sun | F71: Downtown-4 | J71: Team Meeting & Workshop | K71: 0 | L71: Small Event | S71: Confirmed (Done) | T71: Not Required
A72: =IF(OR(D72<>"",H72<>"",I72<>"",Q72<>"",S72<>""), "EVT-" & TEXT(B72, "0000") & "-" & TEXT(COUNTIF(OFFSET($A$1, 1, 0, ROW()-2, 1), "EVT*") + 1, "0000"), "") -> EVT-2026-0070 | B72: 2026 | C72: Jan | D72: 46041 | E72: Mon | F72: Downtown-4 | G72: L-5 | H72: Hackable Area | I72: Fraud Operations- Internal Meeting | J72: Tech & Innovation | K72: 16 | L72: Small Event | M72: 11:00 AM | N72: 12:00 PM | Q72: Manu Singh | S72: Confirmed (Done) | T72: Not Required | V72: Theater style
A73: =IF(OR(D73<>"",H73<>"",I73<>"",Q73<>"",S73<>""), "EVT-" & TEXT(B73, "0000") & "-" & TEXT(COUNTIF(OFFSET($A$1, 1, 0, ROW()-2, 1), "EVT*") + 1, "0000"), "") -> EVT-2026-0071 | B73: 2026 | C73: Jan | D73: 46041 | E73: Mon | F73: Downtown-4 | G73: L-5 | H73: Hackable Area | I73: Introduction sesion Paul cookie- Tech | J73: Tech & Innovation | K73: 70 | L73: Small Event | M73: 02:30 PM | N73: 03:30 PM | Q73: Rupika Nagpal | S73: Confirmed (Done) | T73: Not Required | V73: Theater Style
A74: =IF(OR(D74<>"",H74<>"",I74<>"",Q74<>"",S74<>""), "EVT-" & TEXT(B74, "0000") & "-" & TEXT(COUNTIF(OFFSET($A$1, 1, 0, ROW()-2, 1), "EVT*") + 1, "0000"), "") -> EVT-2026-0072 | B74: 2026 | C74: Jan | D74: 46041 | E74: Mon | F74: Downtown-4 | G74: L-4 | H74: Zone E Breakout Area | I74: Tech Onboarding - | J74: Induction & Onboarding | K74: 30 | L74: Small Event | M74: 02:00 PM | N74: 05:00 PM | P74: No | Q74: Soamya | S74: Confirmed (Done) | T74: Not Required | U74: 46008 | V74: Theater style
A75: =IF(OR(D75<>"",H75<>"",I75<>"",Q75<>"",S75<>""), "EVT-" & TEXT(B75, "0000") & "-" & TEXT(COUNTIF(OFFSET($A$1, 1, 0, ROW()-2, 1), "EVT*") + 1, "0000"), "") -> EVT-2026-0073 | B75: 2026 | C75: Jan | D75: 46042 | E75: Tue | F75: Downtown-4 | G75: L-4 | H75: Zone E Breakout Area | I75: Tech Event | J75: Tech & Innovation | K75: 20 | L75: Small Event | M75: 09:00 AM | N75: 10:00 AM | O75: Yes- Tea and Snacks from Pihu | Q75: Rupika Nagpal | S75: Confirmed (Done) | T75: Not Required | U75: 46021 | V75: Theater Style - Tea for 20 packs
A76: =IF(OR(D76<>"",H76<>"",I76<>"",Q76<>"",S76<>""), "EVT-" & TEXT(B76, "0000") & "-" & TEXT(COUNTIF(OFFSET($A$1, 1, 0, ROW()-2, 1), "EVT*") + 1, "0000"), "") -> EVT-2026-0074 | B76: 2026 | C76: Jan | D76: 46042 | E76: Tue | F76: Downtown-4 | G76: L-5 | H76: MR-405 | I76: AU | J76: Team Meeting & Workshop | K76: 1 | L76: Small Event | M76: 08:00 AM | N76: 05:00 PM | Q76: check in by 7:50 am , offline singage, Diet coke, sanitizer & tissue box | S76: Confirmed (Done) | T76: Not Required
A77: =IF(OR(D77<>"",H77<>"",I77<>"",Q77<>"",S77<>""), "EVT-" & TEXT(B77, "0000") & "-" & TEXT(COUNTIF(OFFSET($A$1, 1, 0, ROW()-2, 1), "EVT*") + 1, "0000"), "") -> EVT-2026-0075 | B77: 2026 | C77: Jan | D77: 46042 | E77: Tue | F77: Downtown-4 | G77: L-5 | H77: Hackable Area | I77: Markets India Technology - Full Team Meeting | J77: Tech & Innovation | K77: 75 | L77: Small Event | M77: 01:30 PM | N77: 02:30 PM | P77: Ekta Sharma | Q77: Theater style | S77: Confirmed (Done) | T77: Not Required
A78: =IF(OR(D78<>"",H78<>"",I78<>"",Q78<>"",S78<>""), "EVT-" & TEXT(B78, "0000") & "-" & TEXT(COUNTIF(OFFSET($A$1, 1, 0, ROW()-2, 1), "EVT*") + 1, "0000"), "") -> EVT-2026-0076 | B78: 2026 | C78: Jan | D78: 46042 | E78: Tue | F78: Downtown-4 | G78: L-5 | H78: Zone E Breakout Area | I78: Lunch | J78: Social & Team Connect | K78: 12 | L78: Small Event | M78: 12:00 PM | N78: 01:30 PM | Q78: Shikha Saxena | S78: Confirmed (Done) | T78: Not Required | U78: 46037 | V78: Board room type set up
A79: =IF(OR(D79<>"",H79<>"",I79<>"",Q79<>"",S79<>""), "EVT-" & TEXT(B79, "0000") & "-" & TEXT(COUNTIF(OFFSET($A$1, 1, 0, ROW()-2, 1), "EVT*") + 1, "0000"), "") -> EVT-2026-0077 | B79: 2026 | C79: Jan | D79: 46042 | E79: Tue | F79: Downtown-4 | G79: L-4 | H79: Zone E Breakout Area | I79: Tech Onboarding - | J79: Induction & Onboarding | K79: 30 | L79: Small Event | M79: 02:00 PM | N79: 05:00 PM | P79: No | Q79: Soamya | S79: Confirmed (Done) | T79: Not Required | U79: 46008 | V79: Theater style
A80: =IF(OR(D80<>"",H80<>"",I80<>"",Q80<>"",S80<>""), "EVT-" & TEXT(B80, "0000") & "-" & TEXT(COUNTIF(OFFSET($A$1, 1, 0, ROW()-2, 1), "EVT*") + 1, "0000"), "") -> EVT-2026-0078 | B80: 2026 | C80: Jan | D80: 46043 | E80: Wed | F80: Downtown-4 | G80: L-5 | H80: Cafeteria | I80: EO PB Townhall | J80: Townhall & All-Hands | K80: 500 | L80: Big Event | M80: 02:00 PM | N80: 05:00 PM | O80: Yes | Q80: Bhawna Kashyap | S80: Canceled | T80: Not Required | U80: 46015 | V80: Theater Style - two red chairs +one small table - tissue box with 4 water bottles | W80: Cancelled the event - email sent by Bhawna
A81: =IF(OR(D81<>"",H81<>"",I81<>"",Q81<>"",S81<>""), "EVT-" & TEXT(B81, "0000") & "-" & TEXT(COUNTIF(OFFSET($A$1, 1, 0, ROW()-2, 1), "EVT*") + 1, "0000"), "") -> EVT-2026-0079 | B81: 2026 | C81: Jan | D81: 46043 | E81: Wed | F81: Downtown-4 | G81: L-4 | H81: Hackable space / Zone E Brekout Area | I81: Meditation Sessioin | J81: Tech & Innovation | K81: 80 | L81: Small Event | M81: 02:30 PM | N81: 04:00 PM | P81: No | Q81: Nisarg | S81: Canceled | T81: Not Required
A82: =IF(OR(D82<>"",H82<>"",I82<>"",Q82<>"",S82<>""), "EVT-" & TEXT(B82, "0000") & "-" & TEXT(COUNTIF(OFFSET($A$1, 1, 0, ROW()-2, 1), "EVT*") + 1, "0000"), "") -> EVT-2026-0080 | B82: 2026 | C82: Jan | D82: 46044 | E82: Thu | F82: Downtown-4 | G82: L-5 | H82: Hackable space | I82: Customer Voices Awareness Session II - NAB India) | J82: Tech & Innovation | K82: 50 | L82: Small Event | M82: 01:00 PM | N82: 02:00 PM | Q82: Sneha Kulkarni | S82: Confirmed (Done) | T82: Not Required | U82: 46035 | V82: Theater style
A83: =IF(OR(D83<>"",H83<>"",I83<>"",Q83<>"",S83<>""), "EVT-" & TEXT(B83, "0000") & "-" & TEXT(COUNTIF(OFFSET($A$1, 1, 0, ROW()-2, 1), "EVT*") + 1, "0000"), "") -> EVT-2026-0081 | B83: 2026 | C83: Jan | D83: 46044 | E83: Thu | F83: Downtown-4 | G83: L-5 | H83: Hackable space | I83: NAB Assist Rewards and Recognition | J83: Tech & Innovation | K83: 80 | L83: Small Event | M83: 03:00 PM | N83: 04:00 PM | P83: No | Q83: Avinash Kumar | S83: Confirmed (Done) | T83: Not Required | U83: 46038
A84: =IF(OR(D84<>"",H84<>"",I84<>"",Q84<>"",S84<>""), "EVT-" & TEXT(B84, "0000") & "-" & TEXT(COUNTIF(OFFSET($A$1, 1, 0, ROW()-2, 1), "EVT*") + 1, "0000"), "") -> EVT-2026-0082 | B84: 2026 | C84: Jan | D84: 46044 | E84: Thu | F84: Downtown-4 | G84: L-5 | H84: Zone E Breakout Area | I84: Fin Crime ( Food Fest) | J84: Team Meeting & Workshop | K84: 180 | L84: Big Event | M84: 12:00 PM | N84: 02:00 PM | Q84: Ratri | S84: Confirmed (Done) | T84: Not Required | U84: 46041
A85: =IF(OR(D85<>"",H85<>"",I85<>"",Q85<>"",S85<>""), "EVT-" & TEXT(B85, "0000") & "-" & TEXT(COUNTIF(OFFSET($A$1, 1, 0, ROW()-2, 1), "EVT*") + 1, "0000"), "") -> EVT-2026-0083 | B85: 2026 | C85: Jan | D85: 46044 | E85: Thu | F85: Downtown-4 | G85: L-5 | H85: Hackable Area | I85: R&R event for BPLS | J85: Tech & Innovation | K85: 70 | L85: Small Event | M85: 09:30 AM | N85: 10:15 AM | Q85: Neha Pandy | S85: Confirmed (Done) | T85: Not Required | U85: 46037
A86: =IF(OR(D86<>"",H86<>"",I86<>"",Q86<>"",S86<>""), "EVT-" & TEXT(B86, "0000") & "-" & TEXT(COUNTIF(OFFSET($A$1, 1, 0, ROW()-2, 1), "EVT*") + 1, "0000"), "") -> EVT-2026-0084 | B86: 2026 | C86: Jan | D86: 46044 | E86: Thu | F86: Downtown-4 | G86: L-4 | H86: Zone E Brekout Area | I86: Meditation Sessioin | J86: Team Meeting & Workshop | K86: 80 | L86: Small Event | M86: 02:30 PM | N86: 04:00 PM | P86: No | Q86: Nisarg | S86: Canceled | T86: Not Required | V86: Theater style | W86: Moved on 29th Jan'26
A87: =IF(OR(D87<>"",H87<>"",I87<>"",Q87<>"",S87<>""), "EVT-" & TEXT(B87, "0000") & "-" & TEXT(COUNTIF(OFFSET($A$1, 1, 0, ROW()-2, 1), "EVT*") + 1, "0000"), "") -> EVT-2026-0085 | B87: 2026 | C87: Jan | D87: 46045 | E87: Fri | F87: Downtown-4 | G87: L-5 | H87: Hackable Area | I87: Ops - New Joiners Onboarding | J87: Induction & Onboarding | K87: 70 | L87: Small Event | M87: 09:00 AM | N87: 12:00 PM | Q87: Shikha Saxena | S87: Canceled | T87: Not Required | U87: 46031 | V87: Theater style
A88: =IF(OR(D88<>"",H88<>"",I88<>"",Q88<>"",S88<>""), "EVT-" & TEXT(B88, "0000") & "-" & TEXT(COUNTIF(OFFSET($A$1, 1, 0, ROW()-2, 1), "EVT*") + 1, "0000"), "") -> EVT-2026-0086 | B88: 2026 | C88: Jan | D88: 46045 | E88: Fri | F88: Downtown-4 | J88: Team Meeting & Workshop | K88: 0 | L88: Small Event | S88: Confirmed (Done) | T88: Not Required
A89: =IF(OR(D89<>"",H89<>"",I89<>"",Q89<>"",S89<>""), "EVT-" & TEXT(B89, "0000") & "-" & TEXT(COUNTIF(OFFSET($A$1, 1, 0, ROW()-2, 1), "EVT*") + 1, "0000"), "") -> EVT-2026-0087 | B89: 2026 | C89: Jan | D89: 46045 | E89: Fri | F89: Downtown-4 | G89: L-4 | H89: Zone E Breakout Area | I89: Tech Onboarding - | J89: Induction & Onboarding | K89: 30 | L89: Small Event | M89: 02:00 PM | N89: 05:00 PM | P89: No | Q89: Soamya | S89: Confirmed (Done) | T89: Not Required | U89: 46008 | V89: Theater style
A90: =IF(OR(D90<>"",H90<>"",I90<>"",Q90<>"",S90<>""), "EVT-" & TEXT(B90, "0000") & "-" & TEXT(COUNTIF(OFFSET($A$1, 1, 0, ROW()-2, 1), "EVT*") + 1, "0000"), "") -> EVT-2026-0088 | B90: 2026 | C90: Jan | D90: 46046 | E90: Sat | F90: Downtown-4 | J90: Team Meeting & Workshop | K90: 0 | L90: Small Event | S90: Confirmed (Done) | T90: Not Required
A91: =IF(OR(D91<>"",H91<>"",I91<>"",Q91<>"",S91<>""), "EVT-" & TEXT(B91, "0000") & "-" & TEXT(COUNTIF(OFFSET($A$1, 1, 0, ROW()-2, 1), "EVT*") + 1, "0000"), "") -> EVT-2026-0089 | B91: 2026 | C91: Jan | D91: 46047 | E91: Sun | F91: Downtown-4 | J91: Team Meeting & Workshop | K91: 0 | L91: Small Event | S91: Confirmed (Done) | T91: Not Required
A92: =IF(OR(D92<>"",H92<>"",I92<>"",Q92<>"",S92<>""), "EVT-" & TEXT(B92, "0000") & "-" & TEXT(COUNTIF(OFFSET($A$1, 1, 0, ROW()-2, 1), "EVT*") + 1, "0000"), "") -> EVT-2026-0090 | B92: 2026 | C92: Jan | D92: 46048 | E92: Mon | F92: Downtown-4 | J92: Team Meeting & Workshop | K92: 0 | L92: Small Event | S92: Confirmed (Done) | T92: Not Required
A93: =IF(OR(D93<>"",H93<>"",I93<>"",Q93<>"",S93<>""), "EVT-" & TEXT(B93, "0000") & "-" & TEXT(COUNTIF(OFFSET($A$1, 1, 0, ROW()-2, 1), "EVT*") + 1, "0000"), "") -> EVT-2026-0091 | B93: 2026 | C93: Jan | D93: 46049 | E93: Tue | F93: Downtown-4 | G93: L-5 | H93: DT4 – 5.D.405 | I93: AU visitor | J93: Leadership & VIP Visit | K93: 2 | L93: Small Event | M93: 08:00 AM | N93: 05:00 PM | S93: Confirmed (Done) | T93: Not Required | V93: check in, offline singage, water bottles Diet coke, sanitizer & tissue box
A94: =IF(OR(D94<>"",H94<>"",I94<>"",Q94<>"",S94<>""), "EVT-" & TEXT(B94, "0000") & "-" & TEXT(COUNTIF(OFFSET($A$1, 1, 0, ROW()-2, 1), "EVT*") + 1, "0000"), "") -> EVT-2026-0092 | B94: 2026 | C94: Jan | D94: 46049 | E94: Tue | F94: Downtown-4 | G94: L-5 | H94: Zone E Breakout Area | I94: Potluck Lunch | J94: Social & Team Connect | K94: 70 | L94: Small Event | M94: 12:00 PM | N94: 01:00 PM | Q94: Shikha Saxena | S94: Confirmed (Done) | T94: Not Required | U94: 46037 | V94: Place the tables for placing the lunch near to the Glasses side as 70 pax is arranging the lunch- arranage cutlery - (plates, tissues spooons)
A95: =IF(OR(D95<>"",H95<>"",I95<>"",Q95<>"",S95<>""), "EVT-" & TEXT(B95, "0000") & "-" & TEXT(COUNTIF(OFFSET($A$1, 1, 0, ROW()-2, 1), "EVT*") + 1, "0000"), "") -> EVT-2026-0093 | B95: 2026 | C95: Jan | D95: 46049 | E95: Tue | F95: Downtown-4 | G95: L-5 | H95: Hackable Area | I95: Markets India Technology - Full Team Meeting | J95: Tech & Innovation | K95: 75 | L95: Small Event | M95: 01:30 PM | N95: 02:30 PM | P95: Ekta Sharma | Q95: Theater style | S95: Canceled | T95: Not Required | V95: Checking with Prem | W95: Event cancelled
A96: =IF(OR(D96<>"",H96<>"",I96<>"",Q96<>"",S96<>""), "EVT-" & TEXT(B96, "0000") & "-" & TEXT(COUNTIF(OFFSET($A$1, 1, 0, ROW()-2, 1), "EVT*") + 1, "0000"), "") -> EVT-2026-0094 | B96: 2026 | C96: Jan | D96: 46049 | E96: Tue | F96: Downtown-4 | G96: L-5 | H96: Cafeteria | I96: Business update- Townhall | J96: Townhall & All-Hands | K96: 80 | L96: Small Event | M96: 03:30 PM | N96: 05:00 PM | Q96: Shikha Saxena | S96: Confirmed (Done) | T96: Not Required | U96: 46028 | V96: Theater style - and two red chairs along with round table - four water bottles and tissue box
A97: =IF(OR(D97<>"",H97<>"",I97<>"",Q97<>"",S97<>""), "EVT-" & TEXT(B97, "0000") & "-" & TEXT(COUNTIF(OFFSET($A$1, 1, 0, ROW()-2, 1), "EVT*") + 1, "0000"), "") -> EVT-2026-0095 | B97: 2026 | C97: Jan | D97: 46049 | E97: Tue | F97: Downtown-4 | G97: L-4 | H97: Zone E Breakout Area | I97: Codility | J97: Assessment & Hiring | K97: 50 | L97: Small Event | M97: 01:30 PM | N97: 04:00 PM | Q97: Parul Wadhera | S97: Confirmed (Done) | T97: Not Required | U97: 46008 | V97: Classroom set up
A98: =IF(OR(D98<>"",H98<>"",I98<>"",Q98<>"",S98<>""), "EVT-" & TEXT(B98, "0000") & "-" & TEXT(COUNTIF(OFFSET($A$1, 1, 0, ROW()-2, 1), "EVT*") + 1, "0000"), "") -> EVT-2026-0096 | B98: 2026 | C98: Jan | D98: 46050 | E98: Wed | F98: Downtown-4 | G98: L-5 | H98: Cafeteria | I98: All Hands- DEDA | J98: Townhall & All-Hands | K98: 180 | L98: Big Event | M98: 03:00 PM | N98: 04:15 PM | Q98: Ekta Sharma | S98: Canceled | T98: Not Required | U98: 46035 | W98: Moved on 2nd Feb'2026
A99: =IF(OR(D99<>"",H99<>"",I99<>"",Q99<>"",S99<>""), "EVT-" & TEXT(B99, "0000") & "-" & TEXT(COUNTIF(OFFSET($A$1, 1, 0, ROW()-2, 1), "EVT*") + 1, "0000"), "") -> EVT-2026-0097 | B99: 2026 | C99: Jan | D99: 46050 | E99: Wed | F99: Downtown-4 | G99: L-4 | H99: Zone E Breakout Area | I99: Smart Bites | J99: Team Meeting & Workshop | K99: 30 | L99: Small Event | M99: 02:00 PM | N99: 04:30 PM | Q99: Somya | S99: Confirmed (Done) | T99: Not Required | U99: 46042 | V99: Theater style- event name
A100: =IF(OR(D100<>"",H100<>"",I100<>"",Q100<>"",S100<>""), "EVT-" & TEXT(B100, "0000") & "-" & TEXT(COUNTIF(OFFSET($A$1, 1, 0, ROW()-2, 1), "EVT*") + 1, "0000"), "") -> EVT-2026-0098 | B100: 2026 | C100: Jan | D100: 46050 | E100: Wed | F100: Downtown-4 | G100: L-5 | H100: Hackable Area | I100: Group Security event | J100: Tech & Innovation | K100: 40 | L100: Small Event | M100: 02:30 PM | N100: 05:00 PM | Q100: Sadaf Athar | S100: Confirmed (Done) | T100: Not Required | U100: 46044
...

Sheet DT-3 Jan26
A1: 🏠 ⮌ RETURN TO DASHBOARD | D1: DOWNTOWN-3 EVENT OPERATIONS TRACKER • JAN26 | N1: 🟢 Green: Confirmed | 🟡 Yellow: Pending | 🔴 Red: Canceled
A2: Event ID | B2: Event Date | C2: Day | D2: Location | E2: Event Type / Title | F2: Capacity | G2: Event Scale | H2: Event Start Time | I2: Event End Time | J2: F& B | K2: Logistic Support | L2: Booked By | M2: Requester Email | N2: Booking Date | O2: Status | P2: Feedback Form | Q2: Remarks | R2: Booking Taken By
A3: =IF(OR(D3<>"", E3<>"", K3<>"", N3<>""), "EVT-2026-" & TEXT(COUNTIF(OFFSET($A$1, 1, 0, ROW()-2, 1), "EVT*") + 1, "0000"), "") | B3: 46023 | C3: Thu | G3: Small Event | O3: Confirmed (Done) | P3: Not Required
A4: =IF(OR(D4<>"", E4<>"", K4<>"", N4<>""), "EVT-2026-" & TEXT(COUNTIF(OFFSET($A$1, 1, 0, ROW()-2, 1), "EVT*") + 1, "0000"), "") | B4: 46024 | C4: Fri | G4: Small Event | O4: Confirmed (Done) | P4: Not Required
A5: =IF(OR(D5<>"", E5<>"", K5<>"", N5<>""), "EVT-2026-" & TEXT(COUNTIF(OFFSET($A$1, 1, 0, ROW()-2, 1), "EVT*") + 1, "0000"), "") | B5: 46025 | C5: Sat | G5: Small Event | O5: Confirmed (Done) | P5: Not Required
A6: =IF(OR(D6<>"", E6<>"", K6<>"", N6<>""), "EVT-2026-" & TEXT(COUNTIF(OFFSET($A$1, 1, 0, ROW()-2, 1), "EVT*") + 1, "0000"), "") | B6: 46026 | C6: Sun | G6: Small Event | O6: Confirmed (Done) | P6: Not Required
A7: =IF(OR(D7<>"", E7<>"", K7<>"", N7<>""), "EVT-2026-" & TEXT(COUNTIF(OFFSET($A$1, 1, 0, ROW()-2, 1), "EVT*") + 1, "0000"), "") -> EVT-2026-0001 | B7: 46027 | C7: Mon | D7: MR-305 & 306 | E7: Induction Session | F7: 35 | G7: Small Event | H7: 08:00 AM | I7: 05:00 PM | J7: Lunch | L7: Deshraj | N7: 46001 | O7: Confirmed (Done) | P7: Not Required | Q7: Classroom set up with power extension-
A8: =IF(OR(D8<>"", E8<>"", K8<>"", N8<>""), "EVT-2026-" & TEXT(COUNTIF(OFFSET($A$1, 1, 0, ROW()-2, 1), "EVT*") + 1, "0000"), "") -> EVT-2026-0002 | B8: 46027 | C8: Mon | D8: Breakout Area | E8: Induction Session | F8: 35 | G8: Small Event | H8: 08:00 AM | I8: 05:00 PM | J8: Lunch | L8: Deshraj | O8: Confirmed (Done) | P8: Not Required | Q8: Classroom set up with power extension-
A9: =IF(OR(D9<>"", E9<>"", K9<>"", N9<>""), "EVT-2026-" & TEXT(COUNTIF(OFFSET($A$1, 1, 0, ROW()-2, 1), "EVT*") + 1, "0000"), "") | B9: 46028 | C9: Tue | G9: Small Event | O9: Confirmed (Done) | P9: Not Required
A10: =IF(OR(D10<>"", E10<>"", K10<>"", N10<>""), "EVT-2026-" & TEXT(COUNTIF(OFFSET($A$1, 1, 0, ROW()-2, 1), "EVT*") + 1, "0000"), "") | B10: 46029 | C10: Wed | G10: Small Event | O10: Confirmed (Done) | P10: Not Required
A11: =IF(OR(D11<>"", E11<>"", K11<>"", N11<>""), "EVT-2026-" & TEXT(COUNTIF(OFFSET($A$1, 1, 0, ROW()-2, 1), "EVT*") + 1, "0000"), "") | B11: 46030 | C11: Thu | G11: Small Event | O11: Confirmed (Done) | P11: Not Required
A12: =IF(OR(D12<>"", E12<>"", K12<>"", N12<>""), "EVT-2026-" & TEXT(COUNTIF(OFFSET($A$1, 1, 0, ROW()-2, 1), "EVT*") + 1, "0000"), "") | B12: 46031 | C12: Fri | G12: Small Event | O12: Confirmed (Done) | P12: Not Required
A13: =IF(OR(D13<>"", E13<>"", K13<>"", N13<>""), "EVT-2026-" & TEXT(COUNTIF(OFFSET($A$1, 1, 0, ROW()-2, 1), "EVT*") + 1, "0000"), "") -> EVT-2026-0003 | B13: 46032 | C13: Sat | D13: MR-305 & 306 | E13: Driver's Training | F13: 20 | G13: Small Event | H13: 10:00 AM | I13: 01:00 PM | J13: Snacks | L13: Prem Chaudhary | O13: Confirmed (Done) | P13: Not Required | Q13: Arranged the snacks- Cup Cakes, Samosa and tea
A14: =IF(OR(D14<>"", E14<>"", K14<>"", N14<>""), "EVT-2026-" & TEXT(COUNTIF(OFFSET($A$1, 1, 0, ROW()-2, 1), "EVT*") + 1, "0000"), "") -> EVT-2026-0004 | B14: 46032 | C14: Sat | D14: Hiring drive | E14: ZONE C, D and E | G14: Small Event | H14: 08:30 AM | I14: 05:00 PM | L14: Manoj Thakral | O14: Confirmed (Done) | P14: Not Required | Q14: List will be shared shortly.
A15: =IF(OR(D15<>"", E15<>"", K15<>"", N15<>""), "EVT-2026-" & TEXT(COUNTIF(OFFSET($A$1, 1, 0, ROW()-2, 1), "EVT*") + 1, "0000"), "") | B15: 46033 | C15: Sun | G15: Small Event | O15: Confirmed (Done) | P15: Not Required
A16: =IF(OR(D16<>"", E16<>"", K16<>"", N16<>""), "EVT-2026-" & TEXT(COUNTIF(OFFSET($A$1, 1, 0, ROW()-2, 1), "EVT*") + 1, "0000"), "") -> EVT-2026-0005 | B16: 46034 | C16: Mon | D16: MR-305 & 306 | E16: Inductin Session | F16: 40 | G16: Small Event | H16: 08:00 AM | I16: 05:00 PM | J16: Lunch | L16: Deshraj | O16: Confirmed (Done) | P16: Not Required | Q16: Classroom set up with power extension
A17: =IF(OR(D17<>"", E17<>"", K17<>"", N17<>""), "EVT-2026-" & TEXT(COUNTIF(OFFSET($A$1, 1, 0, ROW()-2, 1), "EVT*") + 1, "0000"), "") -> EVT-2026-0006 | B17: 46034 | C17: Mon | D17: Breakout Area | E17: Inductin Session | F17: 20 | G17: Small Event | H17: 08:00 AM | I17: 05:00 PM | J17: Lunch | L17: Deshraj | O17: Confirmed (Done) | P17: Not Required | Q17: Classroom set up and require one table and one chair for the facilitator
A18: =IF(OR(D18<>"", E18<>"", K18<>"", N18<>""), "EVT-2026-" & TEXT(COUNTIF(OFFSET($A$1, 1, 0, ROW()-2, 1), "EVT*") + 1, "0000"), "") | B18: 46035 | C18: Tue | G18: Small Event | O18: Confirmed (Done) | P18: Not Required | Q18: TBC
A19: =IF(OR(D19<>"", E19<>"", K19<>"", N19<>""), "EVT-2026-" & TEXT(COUNTIF(OFFSET($A$1, 1, 0, ROW()-2, 1), "EVT*") + 1, "0000"), "") -> EVT-2026-0007 | B19: 46036 | C19: Wed | D19: MR-305 & 306 | E19: Inductin Session | F19: 25 | G19: Small Event | H19: 08:00 AM | I19: 05:00 PM | J19: Lunch | L19: Deshraj | O19: Confirmed (Done) | P19: Not Required
A20: =IF(OR(D20<>"", E20<>"", K20<>"", N20<>""), "EVT-2026-" & TEXT(COUNTIF(OFFSET($A$1, 1, 0, ROW()-2, 1), "EVT*") + 1, "0000"), "") -> EVT-2026-0008 | B20: 46036 | C20: Wed | D20: Breakout Area | G20: Small Event | O20: Confirmed (Done) | P20: Not Required
A21: =IF(OR(D21<>"", E21<>"", K21<>"", N21<>""), "EVT-2026-" & TEXT(COUNTIF(OFFSET($A$1, 1, 0, ROW()-2, 1), "EVT*") + 1, "0000"), "") -> EVT-2026-0009 | B21: 46037 | C21: Thu | D21: MR-305 & 306 | E21: Communicating with Impact (FCO + Nom) | F21: 25 | G21: Small Event | H21: 02:30 PM | I21: 04:30 PM | L21: Deshraj | O21: Confirmed (Done) | P21: Not Required | Q21: Cluster Set up- add onlyone chair and one chair+table for the facilitator
A22: =IF(OR(D22<>"", E22<>"", K22<>"", N22<>""), "EVT-2026-" & TEXT(COUNTIF(OFFSET($A$1, 1, 0, ROW()-2, 1), "EVT*") + 1, "0000"), "") -> EVT-2026-0010 | B22: 46037 | C22: Thu | D22: Cafeteria + Breakout Area | E22: Risk Awareness session for Enterprise Data team | F22: 200 | G22: Big Event | H22: 03:00 PM | I22: 04:00 PM | L22: Maanshu Chugh | N22: 6th Jan'26 | O22: Confirmed (Done) | P22: Not Required | Q22: Theater style
A23: =IF(OR(D23<>"", E23<>"", K23<>"", N23<>""), "EVT-2026-" & TEXT(COUNTIF(OFFSET($A$1, 1, 0, ROW()-2, 1), "EVT*") + 1, "0000"), "") -> EVT-2026-0011 | B23: 46038 | C23: Fri | D23: Cafeteria | E23: Culture Immersion NH + Nominations | F23: 50 | G23: Small Event | H23: 03:00 PM | I23: 04:30 PM | L23: Deshraj | O23: Confirmed (Done) | P23: Not Required | Q23: Theater style
A24: =IF(OR(D24<>"", E24<>"", K24<>"", N24<>""), "EVT-2026-" & TEXT(COUNTIF(OFFSET($A$1, 1, 0, ROW()-2, 1), "EVT*") + 1, "0000"), "") -> EVT-2026-0012 | B24: 46039 | C24: Sat | E24: Hiring Drive | G24: Small Event | H24: 08:00 AM | I24: 05:00 PM | L24: Mohit Mishra/ Monika Nigam | O24: Confirmed (Done) | P24: Not Required
A25: =IF(OR(D25<>"", E25<>"", K25<>"", N25<>""), "EVT-2026-" & TEXT(COUNTIF(OFFSET($A$1, 1, 0, ROW()-2, 1), "EVT*") + 1, "0000"), "") | B25: 46040 | C25: Sun | G25: Small Event | O25: Confirmed (Done) | P25: Not Required
A26: =IF(OR(D26<>"", E26<>"", K26<>"", N26<>""), "EVT-2026-" & TEXT(COUNTIF(OFFSET($A$1, 1, 0, ROW()-2, 1), "EVT*") + 1, "0000"), "") -> EVT-2026-0013 | B26: 46041 | C26: Mon | D26: MR-305 & 306 | E26: Induction Session (perm -305 and 306) contractors- (breakout area) | F26: 70 | G26: Small Event | H26: 08:00 AM | I26: 05:00 PM | J26: Lunch | L26: Deshraj | N26: 46001 | O26: Confirmed (Done) | P26: Not Required | Q26: Classroom set up
A27: =IF(OR(D27<>"", E27<>"", K27<>"", N27<>""), "EVT-2026-" & TEXT(COUNTIF(OFFSET($A$1, 1, 0, ROW()-2, 1), "EVT*") + 1, "0000"), "") -> EVT-2026-0014 | B27: 46041 | C27: Mon | D27: Breakout Area | G27: Small Event | L27: Deshraj | O27: Confirmed (Done) | P27: Not Required | Q27: Classroom set up
A28: =IF(OR(D28<>"", E28<>"", K28<>"", N28<>""), "EVT-2026-" & TEXT(COUNTIF(OFFSET($A$1, 1, 0, ROW()-2, 1), "EVT*") + 1, "0000"), "") -> EVT-2026-0015 | B28: 46042 | C28: Tue | D28: MR-305 & 306 | E28: ALT Workshop 2 | G28: Small Event | H28: 08:30 AM | I28: 04:30 PM | J28: Tea, cookies and Food Arrnagement | L28: Deshraj | N28: 46364 | O28: Confirmed (Done) | P28: Not Required | Q28: Cluster Set Up- Two white boards required
A29: =IF(OR(D29<>"", E29<>"", K29<>"", N29<>""), "EVT-2026-" & TEXT(COUNTIF(OFFSET($A$1, 1, 0, ROW()-2, 1), "EVT*") + 1, "0000"), "") | B29: 46042 | C29: Tue | G29: Small Event | O29: Confirmed (Done) | P29: Not Required | Q29: Cluster set up
A30: =IF(OR(D30<>"", E30<>"", K30<>"", N30<>""), "EVT-2026-" & TEXT(COUNTIF(OFFSET($A$1, 1, 0, ROW()-2, 1), "EVT*") + 1, "0000"), "") -> EVT-2026-0016 | B30: 46042 | C30: Tue | D30: Breakout Area | E30: Internal Sourcing Training | F30: 30 | G30: Small Event | H30: 02:00 PM | I30: 04:00 PM | L30: Tushar Mudgil | N30: 13th Jan'26 | O30: Confirmed (Done) | P30: Not Required | Q30: Theater set up
A31: =IF(OR(D31<>"", E31<>"", K31<>"", N31<>""), "EVT-2026-" & TEXT(COUNTIF(OFFSET($A$1, 1, 0, ROW()-2, 1), "EVT*") + 1, "0000"), "") -> EVT-2026-0017 | B31: 46043 | C31: Wed | D31: Breakout Area | E31: Internal Sourcing Training | F31: 30 | G31: Small Event | H31: 02:00 PM | I31: 04:00 PM | L31: Tushar Mudgil | N31: 13th Jan'26 | O31: Canceled | P31: Not Required | Q31: Theater set up
A32: =IF(OR(D32<>"", E32<>"", K32<>"", N32<>""), "EVT-2026-" & TEXT(COUNTIF(OFFSET($A$1, 1, 0, ROW()-2, 1), "EVT*") + 1, "0000"), "") -> EVT-2026-0018 | B32: 46044 | C32: Thu | D32: Breakou Area | E32: Q1 R&R Ceremony (Business Lending) | F32: 70 | G32: Small Event | H32: 09:30 AM | I32: 10:15 AM | L32: Jackie Jose | N32: 46035 | O32: Canceled | P32: Not Required | Q32: Theater style | R32: Moved to DT-4 Hackable space
A33: =IF(OR(D33<>"", E33<>"", K33<>"", N33<>""), "EVT-2026-" & TEXT(COUNTIF(OFFSET($A$1, 1, 0, ROW()-2, 1), "EVT*") + 1, "0000"), "") | B33: 46044 | C33: Thu | G33: Small Event | O33: Confirmed (Done) | P33: Not Required | Q33: Theater style
A34: =IF(OR(D34<>"", E34<>"", K34<>"", N34<>""), "EVT-2026-" & TEXT(COUNTIF(OFFSET($A$1, 1, 0, ROW()-2, 1), "EVT*") + 1, "0000"), "") -> EVT-2026-0019 | B34: 46044 | C34: Thu | D34: Breakou Area | E34: DCO Fun Crew – Republic Day Event” | F34: 60 | G34: Small Event | H34: 03:00 PM | I34: 04:30 PM | L34: Arpan Relan | N34: 5th Jan'26 | O34: Confirmed (Done) | P34: Not Required | Q34: Theater Style
A35: =IF(OR(D35<>"", E35<>"", K35<>"", N35<>""), "EVT-2026-" & TEXT(COUNTIF(OFFSET($A$1, 1, 0, ROW()-2, 1), "EVT*") + 1, "0000"), "") -> EVT-2026-0020 | B35: 46045 | C35: Fri | D35: Social Hub 2 | E35: Lunch | G35: Small Event | L35: Sameer Duttta | N35: 46044 | O35: Confirmed (Done) | P35: Not Required | Q35: Sameer will share the details /
A36: =IF(OR(D36<>"", E36<>"", K36<>"", N36<>""), "EVT-2026-" & TEXT(COUNTIF(OFFSET($A$1, 1, 0, ROW()-2, 1), "EVT*") + 1, "0000"), "") -> EVT-2026-0021 | B36: 46046 | C36: Sat | E36: Hiring Drive | G36: Small Event | H36: 08:00 AM | I36: 05:00 PM | L36: Eisha Mittal | N36: 46031 | O36: Confirmed (Done) | P36: Not Required
A37: =IF(OR(D37<>"", E37<>"", K37<>"", N37<>""), "EVT-2026-" & TEXT(COUNTIF(OFFSET($A$1, 1, 0, ROW()-2, 1), "EVT*") + 1, "0000"), "") | B37: 46047 | C37: Sun | G37: Small Event | O37: Confirmed (Done) | P37: Not Required
A38: =IF(OR(D38<>"", E38<>"", K38<>"", N38<>""), "EVT-2026-" & TEXT(COUNTIF(OFFSET($A$1, 1, 0, ROW()-2, 1), "EVT*") + 1, "0000"), "") -> EVT-2026-0022 | B38: 46049 | C38: Tue | D38: MR-305 and 306 | E38: Induction Session (perm -305 and 306) contractors- (breakout area) | G38: Small Event | H38: 08:00 AM | I38: 05:00 PM | J38: Lunch | L38: Deshraj | O38: Confirmed (Done) | P38: Not Required | Q38: Classroom set up
A39: =IF(OR(D39<>"", E39<>"", K39<>"", N39<>""), "EVT-2026-" & TEXT(COUNTIF(OFFSET($A$1, 1, 0, ROW()-2, 1), "EVT*") + 1, "0000"), "") -> EVT-2026-0023 | B39: 46049 | C39: Tue | D39: Breakout Area | E39: DL Workshop | G39: Small Event | H39: 08:00 AM | I39: 05:00 PM | J39: Snacks+Lunch | L39: Deshraj | O39: Confirmed (Done) | P39: Not Required | Q39: Classroom set up
A40: =IF(OR(D40<>"", E40<>"", K40<>"", N40<>""), "EVT-2026-" & TEXT(COUNTIF(OFFSET($A$1, 1, 0, ROW()-2, 1), "EVT*") + 1, "0000"), "") -> EVT-2026-0024 | B40: 46050 | C40: Wed | D40: MR-305 and 306 | E40: DL Workshop | G40: Small Event | H40: 08:00 AM | I40: 05:00 PM | J40: Snacks+Lunch | L40: Deshraj | O40: Confirmed (Done) | P40: Not Required | Q40: Classroom set up
A41: =IF(OR(D41<>"", E41<>"", K41<>"", N41<>""), "EVT-2026-" & TEXT(COUNTIF(OFFSET($A$1, 1, 0, ROW()-2, 1), "EVT*") + 1, "0000"), "") -> EVT-2026-0025 | B41: 46051 | C41: Thu | D41: Breakout Area | E41: All hands meeting for Enterprise Operations Tech | F41: 50 | G41: Small Event | H41: 11:00 AM | I41: 12:00 PM | L41: Ajay Sutrave | O41: Confirmed (Done) | P41: Not Required | Q41: Theater style
A42: =IF(OR(D42<>"", E42<>"", K42<>"", N42<>""), "EVT-2026-" & TEXT(COUNTIF(OFFSET($A$1, 1, 0, ROW()-2, 1), "EVT*") + 1, "0000"), "") -> EVT-2026-0026 | B42: 46051 | C42: Thu | D42: Cafeteria + Breakout Area | E42: Risk Awareness Session - Enterprise Technology Team | F42: 200 | G42: Big Event | H42: 03:00 PM | I42: 04:30 PM | L42: Maanshu Chugh | O42: Confirmed (Done) | P42: Not Required | Q42: Theater style
A43: =IF(OR(D43<>"", E43<>"", K43<>"", N43<>""), "EVT-2026-" & TEXT(COUNTIF(OFFSET($A$1, 1, 0, ROW()-2, 1), "EVT*") + 1, "0000"), "") -> EVT-2026-0027 | B43: 46051 | C43: Thu | D43: Breakout Area | E43: Finance Townhall | F43: 50 | G43: Small Event | H43: 02:00 PM | I43: 04:00 PM | L43: Anju Verma | O43: Canceled | P43: Not Required | Q43: Theater Style | R43: Moved the event on 3rd Feb'26
A44: =IF(OR(D44<>"", E44<>"", K44<>"", N44<>""), "EVT-2026-" & TEXT(COUNTIF(OFFSET($A$1, 1, 0, ROW()-2, 1), "EVT*") + 1, "0000"), "") -> EVT-2026-0028 | B44: 46052 | C44: Fri | D44: Cafeteria | E44: T&EO Global Town Halls 2026 | F44: walk in | G44: Small Event | H44: 09:00 AM | I44: 10:00 AM | L44: Prerena Malik | O44: Confirmed (Done) | P44: Not Required
A45: =IF(OR(D45<>"", E45<>"", K45<>"", N45<>""), "EVT-2026-" & TEXT(COUNTIF(OFFSET($A$1, 1, 0, ROW()-2, 1), "EVT*") + 1, "0000"), "") -> EVT-2026-0029 | B45: 46052 | C45: Fri | D45: Cafeteria | E45: CQiB Felicitation | F45: 180 | G45: Big Event | H45: 03:00 PM | I45: 04:00 PM | L45: Deshraj | N45: 10th Jan'26 | O45: Confirmed (Done) | P45: Not Required | Q45: theater style
A46: =IF(OR(D46<>"", E46<>"", K46<>"", N46<>""), "EVT-2026-" & TEXT(COUNTIF(OFFSET($A$1, 1, 0, ROW()-2, 1), "EVT*") + 1, "0000"), "") -> EVT-2026-0030 | B46: 46053 | C46: Sat | D46: No hiring drive on 31st due to the family day | G46: Small Event | O46: Confirmed (Done) | P46: Not Required
A47: =IF(OR(D47<>"", E47<>"", K47<>"", N47<>""), "EVT-2026-" & TEXT(COUNTIF(OFFSET($A$1, 1, 0, ROW()-2, 1), "EVT*") + 1, "0000"), "") | G47: Small Event | O47: Confirmed (Done) | P47: Not Required
A48: =IF(OR(D48<>"", E48<>"", K48<>"", N48<>""), "EVT-2026-" & TEXT(COUNTIF(OFFSET($A$1, 1, 0, ROW()-2, 1), "EVT*") + 1, "0000"), "") | G48: Small Event | O48: Confirmed (Done) | P48: Not Required
A49: =IF(OR(D49<>"", E49<>"", K49<>"", N49<>""), "EVT-2026-" & TEXT(COUNTIF(OFFSET($A$1, 1, 0, ROW()-2, 1), "EVT*") + 1, "0000"), "") | G49: Small Event | O49: Confirmed (Done) | P49: Not Required
A50: =IF(OR(D50<>"", E50<>"", K50<>"", N50<>""), "EVT-2026-" & TEXT(COUNTIF(OFFSET($A$1, 1, 0, ROW()-2, 1), "EVT*") + 1, "0000"), "") | G50: Small Event | O50: Confirmed (Done) | P50: Not Required

Sheet DT-4 Jan26
A1: 🏠 ⮌ RETURN TO DASHBOARD | D1: DOWNTOWN-4 EVENT OPERATIONS TRACKER • JAN26 | O1: 🟢 Green: Confirmed | 🟡 Yellow: Pending | 🔴 Red: Canceled
A2: Event ID | B2: Event Date | C2: Day | D2: Location | E2: Floor | F2: Event Type / Title | G2: Capacity | H2: Event Scale | I2: Event Start Time | J2: Event End Time | K2: F& B | L2: Logistic Support | M2: Booked By | N2: Requester Email | O2: Booking Date | P2: Status | Q2: Feedback Form | R2: Remarks | S2: Booking Taken By
A3: =IF(OR(D3<>"", F3<>"", L3<>"", O3<>""), "EVT-2026-" & TEXT(COUNTIF('DT-3 Jan26'!$A$3:$A$500, "EVT*") + COUNTIF(OFFSET($A$1, 1, 0, ROW()-2, 1), "EVT*") + 1, "0000"), "") -> EVT-2026-0031 | B3: 01/01/2026- 30th Jan'26 | C3: Thur | D3: Hackable Area | E3: 5th Floor | F3: Training | G3: 35 | H3: Small Event | I3: 08:00 AM | J3: 05:00 PM | L3: nO | M3: Binu | O3: 45992 | P3: Confirmed (Done) | Q3: Not Required | R3: Classroom set up and require the Power extension
A4: =IF(OR(D4<>"", F4<>"", L4<>"", O4<>""), "EVT-2026-" & TEXT(COUNTIF('DT-3 Jan26'!$A$3:$A$500, "EVT*") + COUNTIF(OFFSET($A$1, 1, 0, ROW()-2, 1), "EVT*") + 1, "0000"), "") -> EVT-2026-0032 | B4: 01/01/2026- 30th Jan'26 | C4: Thur | D4: Zone E Breakout Area | E4: 5th Floor | F4: Training | G4: 35 | H4: Small Event | I4: 08:00 AM | J4: 05:00 PM | L4: nO | M4: Binu | O4: 45992 | P4: Confirmed (Done) | Q4: Not Required | R4: Classroom set up and require the Power extension
A5: =IF(OR(D5<>"", F5<>"", L5<>"", O5<>""), "EVT-2026-" & TEXT(COUNTIF('DT-3 Jan26'!$A$3:$A$500, "EVT*") + COUNTIF(OFFSET($A$1, 1, 0, ROW()-2, 1), "EVT*") + 1, "0000"), "") | B5: 46024 | C5: Fri | H5: Small Event | P5: Confirmed (Done) | Q5: Not Required
A6: =IF(OR(D6<>"", F6<>"", L6<>"", O6<>""), "EVT-2026-" & TEXT(COUNTIF('DT-3 Jan26'!$A$3:$A$500, "EVT*") + COUNTIF(OFFSET($A$1, 1, 0, ROW()-2, 1), "EVT*") + 1, "0000"), "") | B6: 46025 | C6: Sat | H6: Small Event | P6: Confirmed (Done) | Q6: Not Required
A7: =IF(OR(D7<>"", F7<>"", L7<>"", O7<>""), "EVT-2026-" & TEXT(COUNTIF('DT-3 Jan26'!$A$3:$A$500, "EVT*") + COUNTIF(OFFSET($A$1, 1, 0, ROW()-2, 1), "EVT*") + 1, "0000"), "") | B7: 46026 | C7: Sun | H7: Small Event | P7: Confirmed (Done) | Q7: Not Required
A8: =IF(OR(D8<>"", F8<>"", L8<>"", O8<>""), "EVT-2026-" & TEXT(COUNTIF('DT-3 Jan26'!$A$3:$A$500, "EVT*") + COUNTIF(OFFSET($A$1, 1, 0, ROW()-2, 1), "EVT*") + 1, "0000"), "") | B8: 46027 | C8: Mon | H8: Small Event | P8: Confirmed (Done) | Q8: Not Required
A9: =IF(OR(D9<>"", F9<>"", L9<>"", O9<>""), "EVT-2026-" & TEXT(COUNTIF('DT-3 Jan26'!$A$3:$A$500, "EVT*") + COUNTIF(OFFSET($A$1, 1, 0, ROW()-2, 1), "EVT*") + 1, "0000"), "") -> EVT-2026-0033 | B9: 46028 | C9: Tue | D9: Zone E Breakout Area | E9: L-4 | F9: Codility | G9: 50 | H9: Small Event | I9: 01:30 PM | J9: 04:00 PM | M9: Parul Wadhera | O9: 46008 | P9: Confirmed (Done) | Q9: Not Required | R9: Classroom set up
A10: =IF(OR(D10<>"", F10<>"", L10<>"", O10<>""), "EVT-2026-" & TEXT(COUNTIF('DT-3 Jan26'!$A$3:$A$500, "EVT*") + COUNTIF(OFFSET($A$1, 1, 0, ROW()-2, 1), "EVT*") + 1, "0000"), "") | B10: 46029 | C10: Wed | H10: Small Event | P10: Confirmed (Done) | Q10: Not Required
A11: =IF(OR(D11<>"", F11<>"", L11<>"", O11<>""), "EVT-2026-" & TEXT(COUNTIF('DT-3 Jan26'!$A$3:$A$500, "EVT*") + COUNTIF(OFFSET($A$1, 1, 0, ROW()-2, 1), "EVT*") + 1, "0000"), "") | B11: 46030 | C11: Thu | H11: Small Event | P11: Confirmed (Done) | Q11: Not Required
A12: =IF(OR(D12<>"", F12<>"", L12<>"", O12<>""), "EVT-2026-" & TEXT(COUNTIF('DT-3 Jan26'!$A$3:$A$500, "EVT*") + COUNTIF(OFFSET($A$1, 1, 0, ROW()-2, 1), "EVT*") + 1, "0000"), "") | B12: 46031 | C12: Fri | H12: Small Event | P12: Confirmed (Done) | Q12: Not Required
A13: =IF(OR(D13<>"", F13<>"", L13<>"", O13<>""), "EVT-2026-" & TEXT(COUNTIF('DT-3 Jan26'!$A$3:$A$500, "EVT*") + COUNTIF(OFFSET($A$1, 1, 0, ROW()-2, 1), "EVT*") + 1, "0000"), "") | B13: 46032 | C13: Sat | H13: Small Event | P13: Confirmed (Done) | Q13: Not Required
A14: =IF(OR(D14<>"", F14<>"", L14<>"", O14<>""), "EVT-2026-" & TEXT(COUNTIF('DT-3 Jan26'!$A$3:$A$500, "EVT*") + COUNTIF(OFFSET($A$1, 1, 0, ROW()-2, 1), "EVT*") + 1, "0000"), "") | B14: 46033 | C14: Sun | H14: Small Event | P14: Confirmed (Done) | Q14: Not Required
A15: =IF(OR(D15<>"", F15<>"", L15<>"", O15<>""), "EVT-2026-" & TEXT(COUNTIF('DT-3 Jan26'!$A$3:$A$500, "EVT*") + COUNTIF(OFFSET($A$1, 1, 0, ROW()-2, 1), "EVT*") + 1, "0000"), "") | B15: 46034 | C15: Mon | H15: Small Event | P15: Confirmed (Done) | Q15: Not Required
A16: =IF(OR(D16<>"", F16<>"", L16<>"", O16<>""), "EVT-2026-" & TEXT(COUNTIF('DT-3 Jan26'!$A$3:$A$500, "EVT*") + COUNTIF(OFFSET($A$1, 1, 0, ROW()-2, 1), "EVT*") + 1, "0000"), "") -> EVT-2026-0034 | B16: 46035 | C16: Tue | D16: Zone E Breakout Area | E16: L-4 | F16: Codility | G16: 50 | H16: Small Event | I16: 01:30 PM | J16: 04:00 PM | M16: Parul Wadhera | O16: 46008 | P16: Confirmed (Done) | Q16: Not Required | R16: Classroom set up
A17: =IF(OR(D17<>"", F17<>"", L17<>"", O17<>""), "EVT-2026-" & TEXT(COUNTIF('DT-3 Jan26'!$A$3:$A$500, "EVT*") + COUNTIF(OFFSET($A$1, 1, 0, ROW()-2, 1), "EVT*") + 1, "0000"), "") -> EVT-2026-0035 | B17: 46037 | C17: Thu | D17: Zone E Breakout Area | E17: L-4 | F17: Codility | G17: 50 | H17: Small Event | I17: 01:30 PM | J17: 04:00 PM | M17: Parul Wadhera | P17: Confirmed (Done) | Q17: Not Required
A18: =IF(OR(D18<>"", F18<>"", L18<>"", O18<>""), "EVT-2026-" & TEXT(COUNTIF('DT-3 Jan26'!$A$3:$A$500, "EVT*") + COUNTIF(OFFSET($A$1, 1, 0, ROW()-2, 1), "EVT*") + 1, "0000"), "") -> EVT-2026-0036 | B18: 46037 | C18: Thu | D18: Innovation ARea | E18: L-1 | F18: Townhall | G18: 200 | H18: Big Event | I18: 11:00 AM | J18: 12:30 PM | M18: Kriti Kapoor | O18: 14th Jan'26 | P18: Confirmed (Done) | Q18: Not Required | R18: Theater Style
A19: =IF(OR(D19<>"", F19<>"", L19<>"", O19<>""), "EVT-2026-" & TEXT(COUNTIF('DT-3 Jan26'!$A$3:$A$500, "EVT*") + COUNTIF(OFFSET($A$1, 1, 0, ROW()-2, 1), "EVT*") + 1, "0000"), "") -> EVT-2026-0037 | B19: 46037 | C19: Thu | D19: Zone E Breakout Area | E19: L-4 | F19: Codility | G19: 50 | H19: Small Event | I19: 02:00 PM | J19: 04:00 PM | M19: Parul Wadhera | P19: Confirmed (Done) | Q19: Not Required
A20: =IF(OR(D20<>"", F20<>"", L20<>"", O20<>""), "EVT-2026-" & TEXT(COUNTIF('DT-3 Jan26'!$A$3:$A$500, "EVT*") + COUNTIF(OFFSET($A$1, 1, 0, ROW()-2, 1), "EVT*") + 1, "0000"), "") -> EVT-2026-0038 | B20: 46038 | C20: Fri | D20: Cafeteria | E20: L-5 | F20: Department Townhall | G20: 60 | H20: Small Event | I20: 04:00 PM | J20: 05:00 PM | M20: Prateek Gupta | O20: 7th Jan'26 | P20: Confirmed (Done) | Q20: Not Required | R20: Theater style
A21: =IF(OR(D21<>"", F21<>"", L21<>"", O21<>""), "EVT-2026-" & TEXT(COUNTIF('DT-3 Jan26'!$A$3:$A$500, "EVT*") + COUNTIF(OFFSET($A$1, 1, 0, ROW()-2, 1), "EVT*") + 1, "0000"), "") -> EVT-2026-0039 | B21: 46038 | C21: Fri | D21: Zone E Breakout Area | E21: L-4 | F21: Smart Bytes | G21: 30 | H21: Small Event | I21: 03:00 PM | J21: 03:30 PM | M21: Somaya | O21: 7th Jan'26 | P21: Confirmed (Done) | Q21: Not Required | R21: Theater Style
A22: =IF(OR(D22<>"", F22<>"", L22<>"", O22<>""), "EVT-2026-" & TEXT(COUNTIF('DT-3 Jan26'!$A$3:$A$500, "EVT*") + COUNTIF(OFFSET($A$1, 1, 0, ROW()-2, 1), "EVT*") + 1, "0000"), "") -> EVT-2026-0040 | B22: 46039 | C22: Sat | E22: Hiring Drive | G22: 0.33333333 | H22: Small Event | I22: 05:00 PM | L22: Eisha Mittal- | M22: 2026-01-09 00:00:00 | O22: waiting for the final number of the candidates from Mohit, if numbers are increased then we can keep Eisha hiring drive in Dt-4 | P22: Confirmed (Done) | Q22: Not Required
A23: =IF(OR(D23<>"", F23<>"", L23<>"", O23<>""), "EVT-2026-" & TEXT(COUNTIF('DT-3 Jan26'!$A$3:$A$500, "EVT*") + COUNTIF(OFFSET($A$1, 1, 0, ROW()-2, 1), "EVT*") + 1, "0000"), "") | B23: 46040 | C23: Sun | H23: Small Event | P23: Confirmed (Done) | Q23: Not Required
A24: =IF(OR(D24<>"", F24<>"", L24<>"", O24<>""), "EVT-2026-" & TEXT(COUNTIF('DT-3 Jan26'!$A$3:$A$500, "EVT*") + COUNTIF(OFFSET($A$1, 1, 0, ROW()-2, 1), "EVT*") + 1, "0000"), "") -> EVT-2026-0041 | B24: 46041 | C24: Mon | D24: Hackable Area | E24: L-5 | F24: Fraud Operations- Internal Meeting | G24: 16 | H24: Small Event | I24: 11:00 AM | J24: 12:00 PM | M24: Manu Singh | P24: Confirmed (Done) | Q24: Not Required | R24: Theater style
A25: =IF(OR(D25<>"", F25<>"", L25<>"", O25<>""), "EVT-2026-" & TEXT(COUNTIF('DT-3 Jan26'!$A$3:$A$500, "EVT*") + COUNTIF(OFFSET($A$1, 1, 0, ROW()-2, 1), "EVT*") + 1, "0000"), "") -> EVT-2026-0042 | B25: 46041 | C25: Mon | D25: Hackable Area | E25: L-5 | F25: Introduction sesion Paul cookie- Tech | G25: 70 | H25: Small Event | I25: 02:30 PM | J25: 03:30 PM | M25: Rupika Nagpal | P25: Confirmed (Done) | Q25: Not Required | R25: Theater Style
A26: =IF(OR(D26<>"", F26<>"", L26<>"", O26<>""), "EVT-2026-" & TEXT(COUNTIF('DT-3 Jan26'!$A$3:$A$500, "EVT*") + COUNTIF(OFFSET($A$1, 1, 0, ROW()-2, 1), "EVT*") + 1, "0000"), "") -> EVT-2026-0043 | B26: 46041 | C26: Mon | D26: Zone E Breakout Area | E26: L-4 | F26: Tech Onboarding - | G26: 30 | H26: Small Event | I26: 02:00 PM | J26: 05:00 PM | L26: No | M26: Soamya | O26: 46008 | P26: Confirmed (Done) | Q26: Not Required | R26: Theater style
A27: =IF(OR(D27<>"", F27<>"", L27<>"", O27<>""), "EVT-2026-" & TEXT(COUNTIF('DT-3 Jan26'!$A$3:$A$500, "EVT*") + COUNTIF(OFFSET($A$1, 1, 0, ROW()-2, 1), "EVT*") + 1, "0000"), "") -> EVT-2026-0044 | B27: 46042 | C27: Tue | D27: Zone E Breakout Area | E27: L-4 | F27: Tech Event | G27: 20 | H27: Small Event | I27: 09:00 AM | J27: 10:00 AM | K27: Yes- Tea and Snacks from Pihu | M27: Rupika Nagpal | O27: 46021 | P27: Confirmed (Done) | Q27: Not Required | R27: Theater Style - Tea for 20 packs
A28: =IF(OR(D28<>"", F28<>"", L28<>"", O28<>""), "EVT-2026-" & TEXT(COUNTIF('DT-3 Jan26'!$A$3:$A$500, "EVT*") + COUNTIF(OFFSET($A$1, 1, 0, ROW()-2, 1), "EVT*") + 1, "0000"), "") -> EVT-2026-0045 | B28: 20/01/2026 to 22nd jan'26 | C28: Tue | D28: MR-405 | E28: L-5 | F28: AU | G28: 1 | H28: Small Event | I28: 08:00 AM | J28: 05:00 PM | M28: check in by 7:50 am , offline singage, Diet coke, sanitizer & tissue box | P28: Confirmed (Done) | Q28: Not Required
A29: =IF(OR(D29<>"", F29<>"", L29<>"", O29<>""), "EVT-2026-" & TEXT(COUNTIF('DT-3 Jan26'!$A$3:$A$500, "EVT*") + COUNTIF(OFFSET($A$1, 1, 0, ROW()-2, 1), "EVT*") + 1, "0000"), "") -> EVT-2026-0046 | B29: 46042 | C29: Tue | D29: Hackable Area | E29: L-5 | F29: Markets India Technology - Full Team Meeting | G29: 75 | H29: Small Event | I29: 01:30 PM | J29: 02:30 PM | L29: Ekta Sharma | M29: Theater style | P29: Confirmed (Done) | Q29: Not Required
A30: =IF(OR(D30<>"", F30<>"", L30<>"", O30<>""), "EVT-2026-" & TEXT(COUNTIF('DT-3 Jan26'!$A$3:$A$500, "EVT*") + COUNTIF(OFFSET($A$1, 1, 0, ROW()-2, 1), "EVT*") + 1, "0000"), "") -> EVT-2026-0047 | B30: 46042 | C30: Tue | D30: Zone E Breakout Area | E30: L-5 | F30: Lunch | G30: 12 | H30: Small Event | I30: 12:00 PM | J30: 01:30 PM | M30: Shikha Saxena | O30: 15th Jan'26 | P30: Confirmed (Done) | Q30: Not Required | R30: Board room type set up
A31: =IF(OR(D31<>"", F31<>"", L31<>"", O31<>""), "EVT-2026-" & TEXT(COUNTIF('DT-3 Jan26'!$A$3:$A$500, "EVT*") + COUNTIF(OFFSET($A$1, 1, 0, ROW()-2, 1), "EVT*") + 1, "0000"), "") -> EVT-2026-0048 | B31: 46042 | C31: Tue | D31: Zone E Breakout Area | E31: L-4 | F31: Tech Onboarding - | G31: 30 | H31: Small Event | I31: 02:00 PM | J31: 05:00 PM | L31: No | M31: Soamya | O31: 46008 | P31: Confirmed (Done) | Q31: Not Required | R31: Theater style
A32: =IF(OR(D32<>"", F32<>"", L32<>"", O32<>""), "EVT-2026-" & TEXT(COUNTIF('DT-3 Jan26'!$A$3:$A$500, "EVT*") + COUNTIF(OFFSET($A$1, 1, 0, ROW()-2, 1), "EVT*") + 1, "0000"), "") -> EVT-2026-0049 | B32: 46043 | C32: Wed | D32: Cafeteria | E32: L-5 | F32: EO PB Townhall | G32: 500 | H32: Big Event | I32: 02:00 PM | J32: 05:00 PM | K32: Yes | M32: Bhawna Kashyap | O32: 46015 | P32: Canceled | Q32: Not Required | R32: Theater Style - two red chairs +one small table - tissue box with 4 water bottles | S32: Cancelled the event - email sent by Bhawna
A33: =IF(OR(D33<>"", F33<>"", L33<>"", O33<>""), "EVT-2026-" & TEXT(COUNTIF('DT-3 Jan26'!$A$3:$A$500, "EVT*") + COUNTIF(OFFSET($A$1, 1, 0, ROW()-2, 1), "EVT*") + 1, "0000"), "") -> EVT-2026-0050 | B33: 46043 | C33: Wed | D33: Hackable space / Zone E Brekout Area | E33: L-4 | F33: Meditation Sessioin | G33: 80 | H33: Small Event | I33: 02:30 PM | J33: 04:00 PM | L33: No | M33: Nisarg | P33: Canceled | Q33: Not Required
A34: =IF(OR(D34<>"", F34<>"", L34<>"", O34<>""), "EVT-2026-" & TEXT(COUNTIF('DT-3 Jan26'!$A$3:$A$500, "EVT*") + COUNTIF(OFFSET($A$1, 1, 0, ROW()-2, 1), "EVT*") + 1, "0000"), "") -> EVT-2026-0051 | B34: 46044 | C34: Thu | D34: Hackable space | E34: L-5 | F34: Customer Voices Awareness Session II - NAB India) | G34: 50 | H34: Small Event | I34: 01:00 PM | J34: 02:00 PM | M34: Sneha Kulkarni | O34: 13th Jan'26 | P34: Confirmed (Done) | Q34: Not Required | R34: Theater style
A35: =IF(OR(D35<>"", F35<>"", L35<>"", O35<>""), "EVT-2026-" & TEXT(COUNTIF('DT-3 Jan26'!$A$3:$A$500, "EVT*") + COUNTIF(OFFSET($A$1, 1, 0, ROW()-2, 1), "EVT*") + 1, "0000"), "") -> EVT-2026-0052 | B35: 46044 | C35: Thu | D35: Hackable space | E35: L-5 | F35: NAB Assist Rewards and Recognition | G35: 80 | H35: Small Event | I35: 03:00 PM | J35: 04:00 PM | L35: No | M35: Avinash Kumar | O35: 16th Jan'26 | P35: Confirmed (Done) | Q35: Not Required
A36: =IF(OR(D36<>"", F36<>"", L36<>"", O36<>""), "EVT-2026-" & TEXT(COUNTIF('DT-3 Jan26'!$A$3:$A$500, "EVT*") + COUNTIF(OFFSET($A$1, 1, 0, ROW()-2, 1), "EVT*") + 1, "0000"), "") -> EVT-2026-0053 | B36: 46044 | C36: Thu | D36: Zone E Breakout Area | E36: L-5 | F36: Fin Crime ( Food Fest) | G36: 180 | H36: Big Event | I36: 12:00 PM | J36: 02:00 PM | M36: Ratri | O36: 19th Jan'26 | P36: Confirmed (Done) | Q36: Not Required
A37: =IF(OR(D37<>"", F37<>"", L37<>"", O37<>""), "EVT-2026-" & TEXT(COUNTIF('DT-3 Jan26'!$A$3:$A$500, "EVT*") + COUNTIF(OFFSET($A$1, 1, 0, ROW()-2, 1), "EVT*") + 1, "0000"), "") -> EVT-2026-0054 | B37: 46044 | C37: Thu | D37: Hackable Area | E37: L-5 | F37: R&R event for BPLS | G37: 70 | H37: Small Event | I37: 09:30 AM | J37: 10:15 AM | M37: Neha Pandy | O37: 15th JAN'26 | P37: Confirmed (Done) | Q37: Not Required
A38: =IF(OR(D38<>"", F38<>"", L38<>"", O38<>""), "EVT-2026-" & TEXT(COUNTIF('DT-3 Jan26'!$A$3:$A$500, "EVT*") + COUNTIF(OFFSET($A$1, 1, 0, ROW()-2, 1), "EVT*") + 1, "0000"), "") -> EVT-2026-0055 | B38: 46044 | C38: Thu | D38: Zone E Brekout Area | E38: L-4 | F38: Meditation Sessioin | G38: 80 | H38: Small Event | I38: 02:30 PM | J38: 04:00 PM | L38: No | M38: Nisarg | P38: Canceled | Q38: Not Required | R38: Theater style | S38: Moved on 29th Jan'26
A39: =IF(OR(D39<>"", F39<>"", L39<>"", O39<>""), "EVT-2026-" & TEXT(COUNTIF('DT-3 Jan26'!$A$3:$A$500, "EVT*") + COUNTIF(OFFSET($A$1, 1, 0, ROW()-2, 1), "EVT*") + 1, "0000"), "") -> EVT-2026-0056 | B39: 46045 | C39: Fri | D39: Hackable Area | E39: L-5 | F39: Ops - New Joiners Onboarding | G39: 70 | H39: Small Event | I39: 09:00 AM | J39: 12:00 PM | M39: Shikha Saxena | O39: 9th Jan'26 | P39: Canceled | Q39: Not Required | R39: Theater style
A40: =IF(OR(D40<>"", F40<>"", L40<>"", O40<>""), "EVT-2026-" & TEXT(COUNTIF('DT-3 Jan26'!$A$3:$A$500, "EVT*") + COUNTIF(OFFSET($A$1, 1, 0, ROW()-2, 1), "EVT*") + 1, "0000"), "") | B40: 46045 | C40: Fri | H40: Small Event | P40: Confirmed (Done) | Q40: Not Required
A41: =IF(OR(D41<>"", F41<>"", L41<>"", O41<>""), "EVT-2026-" & TEXT(COUNTIF('DT-3 Jan26'!$A$3:$A$500, "EVT*") + COUNTIF(OFFSET($A$1, 1, 0, ROW()-2, 1), "EVT*") + 1, "0000"), "") -> EVT-2026-0057 | B41: 46045 | C41: Fri | D41: Zone E Breakout Area | E41: L-4 | F41: Tech Onboarding - | G41: 30 | H41: Small Event | I41: 02:00 PM | J41: 05:00 PM | L41: No | M41: Soamya | O41: 46008 | P41: Confirmed (Done) | Q41: Not Required | R41: Theater style
A42: =IF(OR(D42<>"", F42<>"", L42<>"", O42<>""), "EVT-2026-" & TEXT(COUNTIF('DT-3 Jan26'!$A$3:$A$500, "EVT*") + COUNTIF(OFFSET($A$1, 1, 0, ROW()-2, 1), "EVT*") + 1, "0000"), "") | B42: 46046 | C42: Sat | H42: Small Event | P42: Confirmed (Done) | Q42: Not Required
A43: =IF(OR(D43<>"", F43<>"", L43<>"", O43<>""), "EVT-2026-" & TEXT(COUNTIF('DT-3 Jan26'!$A$3:$A$500, "EVT*") + COUNTIF(OFFSET($A$1, 1, 0, ROW()-2, 1), "EVT*") + 1, "0000"), "") | B43: 46047 | C43: Sun | H43: Small Event | P43: Confirmed (Done) | Q43: Not Required
A44: =IF(OR(D44<>"", F44<>"", L44<>"", O44<>""), "EVT-2026-" & TEXT(COUNTIF('DT-3 Jan26'!$A$3:$A$500, "EVT*") + COUNTIF(OFFSET($A$1, 1, 0, ROW()-2, 1), "EVT*") + 1, "0000"), "") | B44: 46048 | C44: Mon | H44: Small Event | P44: Confirmed (Done) | Q44: Not Required
A45: =IF(OR(D45<>"", F45<>"", L45<>"", O45<>""), "EVT-2026-" & TEXT(COUNTIF('DT-3 Jan26'!$A$3:$A$500, "EVT*") + COUNTIF(OFFSET($A$1, 1, 0, ROW()-2, 1), "EVT*") + 1, "0000"), "") -> EVT-2026-0058 | B45: 27/01/2026 to 29/012026 | C45: Tue | D45: DT4 – 5.D.405 | E45: L-5 | F45: AU visitor | G45: 2 | H45: Small Event | I45: 08:00 AM | J45: 05:00 PM | P45: Confirmed (Done) | Q45: Not Required | R45: check in, offline singage, water bottles Diet coke, sanitizer & tissue box
A46: =IF(OR(D46<>"", F46<>"", L46<>"", O46<>""), "EVT-2026-" & TEXT(COUNTIF('DT-3 Jan26'!$A$3:$A$500, "EVT*") + COUNTIF(OFFSET($A$1, 1, 0, ROW()-2, 1), "EVT*") + 1, "0000"), "") -> EVT-2026-0059 | B46: 46049 | C46: Tue | D46: Zone E Breakout Area | E46: L-5 | F46: Potluck Lunch | G46: 70 | H46: Small Event | I46: 12:00 PM | J46: 01:00 PM | M46: Shikha Saxena | O46: 15th Jan'26 | P46: Confirmed (Done) | Q46: Not Required | R46: Place the tables for placing the lunch near to the Glasses side as 70 pax is arranging the lunch- arranage cutlery - (plates, tissues spooons)
A47: =IF(OR(D47<>"", F47<>"", L47<>"", O47<>""), "EVT-2026-" & TEXT(COUNTIF('DT-3 Jan26'!$A$3:$A$500, "EVT*") + COUNTIF(OFFSET($A$1, 1, 0, ROW()-2, 1), "EVT*") + 1, "0000"), "") -> EVT-2026-0060 | B47: 46049 | C47: Tue | D47: Hackable Area | E47: L-5 | F47: Markets India Technology - Full Team Meeting | G47: 75 | H47: Small Event | I47: 01:30 PM | J47: 02:30 PM | L47: Ekta Sharma | M47: Theater style | P47: Canceled | Q47: Not Required | R47: Checking with Prem | S47: Event cancelled
A48: =IF(OR(D48<>"", F48<>"", L48<>"", O48<>""), "EVT-2026-" & TEXT(COUNTIF('DT-3 Jan26'!$A$3:$A$500, "EVT*") + COUNTIF(OFFSET($A$1, 1, 0, ROW()-2, 1), "EVT*") + 1, "0000"), "") -> EVT-2026-0061 | B48: 46049 | C48: Tue | D48: Cafeteria | E48: L-5 | F48: Business update- Townhall | G48: 80 | H48: Small Event | I48: 03:30 PM | J48: 05:00 PM | M48: Shikha Saxena | O48: 46028 | P48: Confirmed (Done) | Q48: Not Required | R48: Theater style - and two red chairs along with round table - four water bottles and tissue box
A49: =IF(OR(D49<>"", F49<>"", L49<>"", O49<>""), "EVT-2026-" & TEXT(COUNTIF('DT-3 Jan26'!$A$3:$A$500, "EVT*") + COUNTIF(OFFSET($A$1, 1, 0, ROW()-2, 1), "EVT*") + 1, "0000"), "") -> EVT-2026-0062 | B49: 46049 | C49: Tue | D49: Zone E Breakout Area | E49: L-4 | F49: Codility | G49: 50 | H49: Small Event | I49: 01:30 PM | J49: 04:00 PM | M49: Parul Wadhera | O49: 46008 | P49: Confirmed (Done) | Q49: Not Required | R49: Classroom set up
A50: =IF(OR(D50<>"", F50<>"", L50<>"", O50<>""), "EVT-2026-" & TEXT(COUNTIF('DT-3 Jan26'!$A$3:$A$500, "EVT*") + COUNTIF(OFFSET($A$1, 1, 0, ROW()-2, 1), "EVT*") + 1, "0000"), "") -> EVT-2026-0063 | B50: 46050 | C50: Wed | D50: Cafeteria | E50: L-5 | F50: All Hands- DEDA | G50: 180 | H50: Big Event | I50: 03:00 PM | J50: 04:15 PM | M50: Ekta Sharma | O50: 13th Jan'26 | P50: Canceled | Q50: Not Required | S50: Moved on 2nd Feb'2026
A51: =IF(OR(D51<>"", F51<>"", L51<>"", O51<>""), "EVT-2026-" & TEXT(COUNTIF('DT-3 Jan26'!$A$3:$A$500, "EVT*") + COUNTIF(OFFSET($A$1, 1, 0, ROW()-2, 1), "EVT*") + 1, "0000"), "") -> EVT-2026-0064 | B51: 46050 | C51: Wed | D51: Zone E Breakout Area | E51: L-4 | F51: Smart Bites | G51: 30 | H51: Small Event | I51: 02:00 PM | J51: 04:30 PM | M51: Somya | O51: 20th Jan'26 | P51: Confirmed (Done) | Q51: Not Required | R51: Theater style- event name
A52: =IF(OR(D52<>"", F52<>"", L52<>"", O52<>""), "EVT-2026-" & TEXT(COUNTIF('DT-3 Jan26'!$A$3:$A$500, "EVT*") + COUNTIF(OFFSET($A$1, 1, 0, ROW()-2, 1), "EVT*") + 1, "0000"), "") -> EVT-2026-0065 | B52: 46050 | C52: Wed | D52: Hackable Area | E52: L-5 | F52: Group Security event | G52: 40 | H52: Small Event | I52: 02:30 PM | J52: 05:00 PM | M52: Sadaf Athar | O52: 22nd Jan'26 | P52: Confirmed (Done) | Q52: Not Required
A53: =IF(OR(D53<>"", F53<>"", L53<>"", O53<>""), "EVT-2026-" & TEXT(COUNTIF('DT-3 Jan26'!$A$3:$A$500, "EVT*") + COUNTIF(OFFSET($A$1, 1, 0, ROW()-2, 1), "EVT*") + 1, "0000"), "") -> EVT-2026-0066 | B53: 46050 | C53: Wed | D53: Cafeteria | E53: L-5 | F53: Business update- Townhall | G53: 80 | H53: Small Event | I53: 03:00 PM | J53: 04:00 PM | M53: Shikha Saxena | O53: 46028 | P53: Canceled | Q53: Not Required | R53: Theater style - and two red chairs along with round table - four water bottles and tissue box | S53: Moved on 27th Jan'26
A54: =IF(OR(D54<>"", F54<>"", L54<>"", O54<>""), "EVT-2026-" & TEXT(COUNTIF('DT-3 Jan26'!$A$3:$A$500, "EVT*") + COUNTIF(OFFSET($A$1, 1, 0, ROW()-2, 1), "EVT*") + 1, "0000"), "") -> EVT-2026-0067 | B54: 46051 | C54: Thu | D54: Cafeteria | E54: L-5 | G54: 40 | H54: Small Event | I54: 03:30 PM | J54: 04:30 PM | M54: Rajesh Motwani | P54: Confirmed (Done) | Q54: Not Required | R54: Theater style
A55: =IF(OR(D55<>"", F55<>"", L55<>"", O55<>""), "EVT-2026-" & TEXT(COUNTIF('DT-3 Jan26'!$A$3:$A$500, "EVT*") + COUNTIF(OFFSET($A$1, 1, 0, ROW()-2, 1), "EVT*") + 1, "0000"), "") -> EVT-2026-0068 | B55: 46051 | C55: Thu | D55: Zone E Breakout Area | E55: L-4 | F55: Meditation Sessioin | G55: 80 | H55: Small Event | I55: 02:30 PM | J55: 04:00 PM | L55: No | M55: Nisarg | P55: Confirmed (Done) | Q55: Not Required
A56: =IF(OR(D56<>"", F56<>"", L56<>"", O56<>""), "EVT-2026-" & TEXT(COUNTIF('DT-3 Jan26'!$A$3:$A$500, "EVT*") + COUNTIF(OFFSET($A$1, 1, 0, ROW()-2, 1), "EVT*") + 1, "0000"), "") -> EVT-2026-0069 | B56: 46051 | C56: Thu | D56: Zone E Breakout Area | E56: L5 | F56: Markets India Technology - Full Team Meeting | G56: 80 | H56: Small Event | I56: 01:30 PM | J56: 02:30 PM | M56: Ekta Sharma | O56: 46043 | P56: Confirmed (Done) | Q56: Not Required
A57: =IF(OR(D57<>"", F57<>"", L57<>"", O57<>""), "EVT-2026-" & TEXT(COUNTIF('DT-3 Jan26'!$A$3:$A$500, "EVT*") + COUNTIF(OFFSET($A$1, 1, 0, ROW()-2, 1), "EVT*") + 1, "0000"), "") -> EVT-2026-0070 | B57: 46051 | C57: Thu | D57: Hackable Area | E57: L5 | F57: V- Townhall | G57: 40 | H57: Small Event | I57: 12:00 PM | J57: 04:00 PM | M57: Shikha Saxena | P57: Confirmed (Done) | Q57: Not Required
A58: =IF(OR(D58<>"", F58<>"", L58<>"", O58<>""), "EVT-2026-" & TEXT(COUNTIF('DT-3 Jan26'!$A$3:$A$500, "EVT*") + COUNTIF(OFFSET($A$1, 1, 0, ROW()-2, 1), "EVT*") + 1, "0000"), "") -> EVT-2026-0071 | B58: 46051 | C58: Thu | D58: Zone E Breakout Area | E58: L-5 | F58: Codility | G58: 50 | H58: Small Event | I58: 01:30 PM | J58: 04:00 PM | M58: Parul Wadhera | O58: 28th Jan'26 | P58: Confirmed (Done) | Q58: Not Required | R58: Classroom set up
A59: =IF(OR(D59<>"", F59<>"", L59<>"", O59<>""), "EVT-2026-" & TEXT(COUNTIF('DT-3 Jan26'!$A$3:$A$500, "EVT*") + COUNTIF(OFFSET($A$1, 1, 0, ROW()-2, 1), "EVT*") + 1, "0000"), "") -> EVT-2026-0072 | B59: 46052 | C59: Fri | D59: hackable space | E59: L-1 | F59: T&EO Global Town Halls 2026 | H59: Small Event | I59: 09:00 AM | J59: 10:00 AM | M59: Prerena Malik | O59: Checking with Neeraj | P59: Confirmed (Done) | Q59: Not Required
A60: =IF(OR(D60<>"", F60<>"", L60<>"", O60<>""), "EVT-2026-" & TEXT(COUNTIF('DT-3 Jan26'!$A$3:$A$500, "EVT*") + COUNTIF(OFFSET($A$1, 1, 0, ROW()-2, 1), "EVT*") + 1, "0000"), "") -> EVT-2026-0073 | B60: 46052 | C60: Fri | D60: Cafeteria | E60: L-5 | F60: T&EO Global Town Halls 2026 | G60: walk in | H60: Small Event | I60: 09:00 AM | J60: 10:00 AM | M60: Prerena Malik | P60: Confirmed (Done) | Q60: Not Required | R60: Hi Tea- Theater style
A61: =IF(OR(D61<>"", F61<>"", L61<>"", O61<>""), "EVT-2026-" & TEXT(COUNTIF('DT-3 Jan26'!$A$3:$A$500, "EVT*") + COUNTIF(OFFSET($A$1, 1, 0, ROW()-2, 1), "EVT*") + 1, "0000"), "") -> EVT-2026-0074 | B61: 46052 | C61: Fri | D61: Cafeteria | E61: L-5 | H61: Small Event | I61: 03:00 PM | J61: 04:00 PM | M61: Anurag Shah | P61: Confirmed (Done) | Q61: Not Required
A62: =IF(OR(D62<>"", F62<>"", L62<>"", O62<>""), "EVT-2026-" & TEXT(COUNTIF('DT-3 Jan26'!$A$3:$A$500, "EVT*") + COUNTIF(OFFSET($A$1, 1, 0, ROW()-2, 1), "EVT*") + 1, "0000"), "") -> EVT-2026-0075 | B62: 46053 | C62: Sat | D62: No hiring drive on 31st due to the family day | H62: Small Event | P62: Confirmed (Done) | Q62: Not Required
A63: =IF(OR(D63<>"", F63<>"", L63<>"", O63<>""), "EVT-2026-" & TEXT(COUNTIF('DT-3 Jan26'!$A$3:$A$500, "EVT*") + COUNTIF(OFFSET($A$1, 1, 0, ROW()-2, 1), "EVT*") + 1, "0000"), "") | C63: Hackable space and Zone E breakout area is not available due to the ongoing trainings | H63: Small Event | P63: Confirmed (Done) | Q63: Not Required

Sheet DT-3 Feb26
A1: 🏠 ⮌ RETURN TO DASHBOARD | D1: DOWNTOWN-3 EVENT OPERATIONS TRACKER • FEB26 | N1: 🟢 Green: Confirmed | 🟡 Yellow: Pending | 🔴 Red: Canceled
A2: Event ID | B2: Event Date | C2: Day | D2: Location | E2: Event Type / Title | F2: Capacity | G2: Event Scale | H2: Event Start Time | I2: Event End Time | J2: F& B | K2: Logistic Support | L2: Booked By | M2: Requester Email | N2: Booking Date | O2: Status | P2: Feedback Form | Q2: Remarks | R2: Booking Taken By
A3: =IF(OR(D3<>"", E3<>"", K3<>"", N3<>""), "EVT-2026-" & TEXT(COUNTIF('DT-3 Jan26'!$A$3:$A$500, "EVT*") + COUNTIF('DT-4 Jan26'!$A$3:$A$500, "EVT*") + COUNTIF(OFFSET($A$1, 1, 0, ROW()-2, 1), "EVT*") + 1, "0000"), "") | B3: 46054 | C3: Sun | G3: Small Event | O3: Confirmed (Done) | P3: Not Required
A4: =IF(OR(D4<>"", E4<>"", K4<>"", N4<>""), "EVT-2026-" & TEXT(COUNTIF('DT-3 Jan26'!$A$3:$A$500, "EVT*") + COUNTIF('DT-4 Jan26'!$A$3:$A$500, "EVT*") + COUNTIF(OFFSET($A$1, 1, 0, ROW()-2, 1), "EVT*") + 1, "0000"), "") -> EVT-2026-0076 | B4: 46055 | C4: Mon | D4: MR-305 and 306 | E4: New Joiners Induction | F4: 28 | G4: Small Event | H4: 08:00 AM | I4: 05:00 PM | L4: Deshraj | O4: Confirmed (Done) | P4: Not Required | Q4: original set up of 24 pax- in cluster and add 4 notepad chairs
A5: =IF(OR(D5<>"", E5<>"", K5<>"", N5<>""), "EVT-2026-" & TEXT(COUNTIF('DT-3 Jan26'!$A$3:$A$500, "EVT*") + COUNTIF('DT-4 Jan26'!$A$3:$A$500, "EVT*") + COUNTIF(OFFSET($A$1, 1, 0, ROW()-2, 1), "EVT*") + 1, "0000"), "") -> EVT-2026-0077 | B5: 46056 | C5: Tue | D5: Breakout Area | E5: – Teams CVT and M&D | F5: 50 | G5: Small Event | H5: 11:30 AM | I5: 12:30 PM | L5: Vicky Khosla | O5: Confirmed (Done) | P5: Not Required | Q5: Theater style
A6: =IF(OR(D6<>"", E6<>"", K6<>"", N6<>""), "EVT-2026-" & TEXT(COUNTIF('DT-3 Jan26'!$A$3:$A$500, "EVT*") + COUNTIF('DT-4 Jan26'!$A$3:$A$500, "EVT*") + COUNTIF(OFFSET($A$1, 1, 0, ROW()-2, 1), "EVT*") + 1, "0000"), "") -> EVT-2026-0078 | B6: 46057 | C6: Wed | D6: Breakout Area | E6: Support Hub | F6: 35 | G6: Small Event | H6: 11:30 AM | I6: 12:30 PM | L6: Vicky Khosla | O6: Confirmed (Done) | P6: Not Required | Q6: Theater style
A7: =IF(OR(D7<>"", E7<>"", K7<>"", N7<>""), "EVT-2026-" & TEXT(COUNTIF('DT-3 Jan26'!$A$3:$A$500, "EVT*") + COUNTIF('DT-4 Jan26'!$A$3:$A$500, "EVT*") + COUNTIF(OFFSET($A$1, 1, 0, ROW()-2, 1), "EVT*") + 1, "0000"), "") -> EVT-2026-0079 | B7: 46057 | C7: Wed | D7: Breakout Area | G7: Small Event | H7: 02:00 PM | I7: 05:00 PM | L7: Deshraj | O7: Confirmed (Done) | P7: Not Required | Q7: Tentatively
A8: =IF(OR(D8<>"", E8<>"", K8<>"", N8<>""), "EVT-2026-" & TEXT(COUNTIF('DT-3 Jan26'!$A$3:$A$500, "EVT*") + COUNTIF('DT-4 Jan26'!$A$3:$A$500, "EVT*") + COUNTIF(OFFSET($A$1, 1, 0, ROW()-2, 1), "EVT*") + 1, "0000"), "") -> EVT-2026-0080 | B8: 46058 | C8: Thu | D8: Breakout Area | E8: Finance Townhall | F8: 60 | G8: Small Event | H8: 02:30 PM | I8: 04:00 PM | L8: Anju | O8: Confirmed (Done) | P8: Not Required | Q8: Details will be shared by her later
A9: =IF(OR(D9<>"", E9<>"", K9<>"", N9<>""), "EVT-2026-" & TEXT(COUNTIF('DT-3 Jan26'!$A$3:$A$500, "EVT*") + COUNTIF('DT-4 Jan26'!$A$3:$A$500, "EVT*") + COUNTIF(OFFSET($A$1, 1, 0, ROW()-2, 1), "EVT*") + 1, "0000"), "") -> EVT-2026-0081 | B9: 46058 | C9: Thu | D9: MR-305 and 306 | E9: Writing Effective Goals & IDPs | F9: 25 | G9: Small Event | H9: 02:30 PM | I9: 04:30 PM | L9: Deshraj | O9: Confirmed (Done) | P9: Not Required | Q9: Cluster set up (add one notepad chair)
A10: =IF(OR(D10<>"", E10<>"", K10<>"", N10<>""), "EVT-2026-" & TEXT(COUNTIF('DT-3 Jan26'!$A$3:$A$500, "EVT*") + COUNTIF('DT-4 Jan26'!$A$3:$A$500, "EVT*") + COUNTIF(OFFSET($A$1, 1, 0, ROW()-2, 1), "EVT*") + 1, "0000"), "") | B10: 46059 | C10: Fri | G10: Small Event | O10: Confirmed (Done) | P10: Not Required
A11: =IF(OR(D11<>"", E11<>"", K11<>"", N11<>""), "EVT-2026-" & TEXT(COUNTIF('DT-3 Jan26'!$A$3:$A$500, "EVT*") + COUNTIF('DT-4 Jan26'!$A$3:$A$500, "EVT*") + COUNTIF(OFFSET($A$1, 1, 0, ROW()-2, 1), "EVT*") + 1, "0000"), "") -> EVT-2026-0082 | B11: 46060 | C11: Sat | D11: No hiring drive due to the family day | G11: Small Event | O11: Confirmed (Done) | P11: Not Required
A12: =IF(OR(D12<>"", E12<>"", K12<>"", N12<>""), "EVT-2026-" & TEXT(COUNTIF('DT-3 Jan26'!$A$3:$A$500, "EVT*") + COUNTIF('DT-4 Jan26'!$A$3:$A$500, "EVT*") + COUNTIF(OFFSET($A$1, 1, 0, ROW()-2, 1), "EVT*") + 1, "0000"), "") | B12: 46061 | C12: Sun | G12: Small Event | O12: Confirmed (Done) | P12: Not Required
A13: =IF(OR(D13<>"", E13<>"", K13<>"", N13<>""), "EVT-2026-" & TEXT(COUNTIF('DT-3 Jan26'!$A$3:$A$500, "EVT*") + COUNTIF('DT-4 Jan26'!$A$3:$A$500, "EVT*") + COUNTIF(OFFSET($A$1, 1, 0, ROW()-2, 1), "EVT*") + 1, "0000"), "") -> EVT-2026-0083 | B13: 46062 | C13: Mon | D13: MR-305 and 306 | E13: New Joiners Induction | F13: 40 | G13: Small Event | H13: 08:00 AM | I13: 05:00 PM | L13: Deshraj | O13: Confirmed (Done) | P13: Not Required | Q13: Theate style with Notepad chairs
A14: =IF(OR(D14<>"", E14<>"", K14<>"", N14<>""), "EVT-2026-" & TEXT(COUNTIF('DT-3 Jan26'!$A$3:$A$500, "EVT*") + COUNTIF('DT-4 Jan26'!$A$3:$A$500, "EVT*") + COUNTIF(OFFSET($A$1, 1, 0, ROW()-2, 1), "EVT*") + 1, "0000"), "") -> EVT-2026-0084 | B14: 46063 | C14: Tue | D14: - DT3-GGN-3.E.505-4P-TC | E14: AU Visitors | F14: 1 | G14: Small Event | H14: 08:00 AM | I14: 05:00 PM | L14: Shikha Saxena | O14: Confirmed (Done) | P14: Not Required | Q14: Check in MR, tissue box and water bottles
A15: =IF(OR(D15<>"", E15<>"", K15<>"", N15<>""), "EVT-2026-" & TEXT(COUNTIF('DT-3 Jan26'!$A$3:$A$500, "EVT*") + COUNTIF('DT-4 Jan26'!$A$3:$A$500, "EVT*") + COUNTIF(OFFSET($A$1, 1, 0, ROW()-2, 1), "EVT*") + 1, "0000"), "") -> EVT-2026-0085 | B15: 46063 | C15: Tue | D15: MR-305 and 306 | E15: DL Workshop | F15: 25 | G15: Small Event | H15: 08:00 AM | I15: 05:00 PM | J15: Tea, cookies and Food Arrangements | L15: Deshraj | O15: Canceled | P15: Not Required | Q15: Two white boards- Cluster set up of 24 pax and one notepad chair
A16: =IF(OR(D16<>"", E16<>"", K16<>"", N16<>""), "EVT-2026-" & TEXT(COUNTIF('DT-3 Jan26'!$A$3:$A$500, "EVT*") + COUNTIF('DT-4 Jan26'!$A$3:$A$500, "EVT*") + COUNTIF(OFFSET($A$1, 1, 0, ROW()-2, 1), "EVT*") + 1, "0000"), "") -> EVT-2026-0086 | B16: 46064 | C16: Wed | D16: MR-305 and 306 | E16: DL Workshop | F16: 25 | G16: Small Event | H16: 08:00 AM | I16: 05:00 PM | J16: Tea, cookies and Food Arrangements | L16: Deshraj | O16: Canceled | P16: Not Required
A17: =IF(OR(D17<>"", E17<>"", K17<>"", N17<>""), "EVT-2026-" & TEXT(COUNTIF('DT-3 Jan26'!$A$3:$A$500, "EVT*") + COUNTIF('DT-4 Jan26'!$A$3:$A$500, "EVT*") + COUNTIF(OFFSET($A$1, 1, 0, ROW()-2, 1), "EVT*") + 1, "0000"), "") -> EVT-2026-0087 | B17: 46064 | C17: Wed | D17: - DT3-GGN-3.E.505-4P-TC | E17: AU Visitors | F17: 1 | G17: Small Event | H17: 08:00 AM | I17: 05:00 PM | L17: Shikha Saxena | O17: Confirmed (Done) | P17: Not Required | Q17: Check in MR, tissue box and water bottles
A18: =IF(OR(D18<>"", E18<>"", K18<>"", N18<>""), "EVT-2026-" & TEXT(COUNTIF('DT-3 Jan26'!$A$3:$A$500, "EVT*") + COUNTIF('DT-4 Jan26'!$A$3:$A$500, "EVT*") + COUNTIF(OFFSET($A$1, 1, 0, ROW()-2, 1), "EVT*") + 1, "0000"), "") -> EVT-2026-0088 | B18: 46064 | C18: Wed | D18: Breakout Area | E18: Meet the Grads | F18: 25 | G18: Small Event | H18: 11:30 AM | I18: 12:30 PM | L18: Roohi Saxena | N18: 6th Feb'26 | O18: Confirmed (Done) | P18: Not Required | Q18: Theater style
A19: =IF(OR(D19<>"", E19<>"", K19<>"", N19<>""), "EVT-2026-" & TEXT(COUNTIF('DT-3 Jan26'!$A$3:$A$500, "EVT*") + COUNTIF('DT-4 Jan26'!$A$3:$A$500, "EVT*") + COUNTIF(OFFSET($A$1, 1, 0, ROW()-2, 1), "EVT*") + 1, "0000"), "") -> EVT-2026-0089 | B19: 46064 | C19: Wed | D19: Breakout Area | E19: CF and OCE team for our AU visitors | F19: 35 | G19: Small Event | H19: 02:15 AM | I19: 03:15 PM | L19: Roohi Saxena | N19: 9th Feb'2026 | O19: Confirmed (Done) | P19: Not Required | Q19: Theater style
A20: =IF(OR(D20<>"", E20<>"", K20<>"", N20<>""), "EVT-2026-" & TEXT(COUNTIF('DT-3 Jan26'!$A$3:$A$500, "EVT*") + COUNTIF('DT-4 Jan26'!$A$3:$A$500, "EVT*") + COUNTIF(OFFSET($A$1, 1, 0, ROW()-2, 1), "EVT*") + 1, "0000"), "") -> EVT-2026-0090 | B20: 46064 | C20: Wed | D20: Cafeteria | E20: Risk Awareness session | F20: 60 | G20: Small Event | H20: 03:00 PM | I20: 04:00 PM | L20: Maanshu | O20: Confirmed (Done) | P20: Not Required | Q20: Theater style
A21: =IF(OR(D21<>"", E21<>"", K21<>"", N21<>""), "EVT-2026-" & TEXT(COUNTIF('DT-3 Jan26'!$A$3:$A$500, "EVT*") + COUNTIF('DT-4 Jan26'!$A$3:$A$500, "EVT*") + COUNTIF(OFFSET($A$1, 1, 0, ROW()-2, 1), "EVT*") + 1, "0000"), "") -> EVT-2026-0091 | B21: 46064 | C21: Wed | D21: MR-305 and 306 | E21: CIB leadership visit | F21: 30 | G21: Small Event | H21: 07:30 PM | I21: 08:00 PM | L21: Praveen Singhal | O21: Confirmed (Done) | P21: Not Required | Q21: Cluster set up of 24 pax and add 6 more chairs
A22: =IF(OR(D22<>"", E22<>"", K22<>"", N22<>""), "EVT-2026-" & TEXT(COUNTIF('DT-3 Jan26'!$A$3:$A$500, "EVT*") + COUNTIF('DT-4 Jan26'!$A$3:$A$500, "EVT*") + COUNTIF(OFFSET($A$1, 1, 0, ROW()-2, 1), "EVT*") + 1, "0000"), "") -> EVT-2026-0092 | B22: 46065 | C22: Thu | D22: DT3-GGN-3.E.503-Focus | E22: AU Visitors | F22: 1 | G22: Small Event | H22: 08:00 AM | I22: 05:00 PM | L22: Shikha Saxena | O22: Confirmed (Done) | P22: Not Required | Q22: Check in MR, tissue box and water bottles
A23: =IF(OR(D23<>"", E23<>"", K23<>"", N23<>""), "EVT-2026-" & TEXT(COUNTIF('DT-3 Jan26'!$A$3:$A$500, "EVT*") + COUNTIF('DT-4 Jan26'!$A$3:$A$500, "EVT*") + COUNTIF(OFFSET($A$1, 1, 0, ROW()-2, 1), "EVT*") + 1, "0000"), "") -> EVT-2026-0093 | B23: 46065 | C23: Thu | D23: Breakout Area | E23: P and C Pot Luck Lunch | F23: 100 | G23: Big Event | H23: 11:00 AM | I23: 01:00 PM | L23: Roohi Saxena | O23: Confirmed (Done) | P23: Not Required | Q23: Place 2 tables at the glass side and 2 in the partition side, free space side keep the chairs at the glass and partition side and no chairs in the center space- will discuss on this
A24: =IF(OR(D24<>"", E24<>"", K24<>"", N24<>""), "EVT-2026-" & TEXT(COUNTIF('DT-3 Jan26'!$A$3:$A$500, "EVT*") + COUNTIF('DT-4 Jan26'!$A$3:$A$500, "EVT*") + COUNTIF(OFFSET($A$1, 1, 0, ROW()-2, 1), "EVT*") + 1, "0000"), "") -> EVT-2026-0094 | B24: 46065 | C24: Thu | D24: Breakout Area | E24: Ask me Anything- DCO | F24: 100 | G24: Big Event | H24: 03:00 PM | I24: 04:30 AM | L24: Shagun | O24: Canceled | P24: Not Required | Q24: Theater style
A25: =IF(OR(D25<>"", E25<>"", K25<>"", N25<>""), "EVT-2026-" & TEXT(COUNTIF('DT-3 Jan26'!$A$3:$A$500, "EVT*") + COUNTIF('DT-4 Jan26'!$A$3:$A$500, "EVT*") + COUNTIF(OFFSET($A$1, 1, 0, ROW()-2, 1), "EVT*") + 1, "0000"), "") -> EVT-2026-0095 | B25: 46065 | C25: Thu | D25: Mr-305 and 306 | E25: Presentation Skills (G3) | F25: 25 | G25: Small Event | H25: 02:00 PM | I25: 05:00 PM | L25: Deshraj | O25: Confirmed (Done) | P25: Not Required | Q25: Cluster setup and add one extra notepad chairs
A26: =IF(OR(D26<>"", E26<>"", K26<>"", N26<>""), "EVT-2026-" & TEXT(COUNTIF('DT-3 Jan26'!$A$3:$A$500, "EVT*") + COUNTIF('DT-4 Jan26'!$A$3:$A$500, "EVT*") + COUNTIF(OFFSET($A$1, 1, 0, ROW()-2, 1), "EVT*") + 1, "0000"), "") -> EVT-2026-0096 | B26: 46066 | C26: Fri | D26: DT3-GGN-3.E.504-4P-TC | E26: AU Visitors | F26: 1 | G26: Small Event | H26: 08:00 AM | I26: 05:00 PM | L26: Shikha Saxena | O26: Confirmed (Done) | P26: Not Required | Q26: Check in MR, tissue box and water bottles
A27: =IF(OR(D27<>"", E27<>"", K27<>"", N27<>""), "EVT-2026-" & TEXT(COUNTIF('DT-3 Jan26'!$A$3:$A$500, "EVT*") + COUNTIF('DT-4 Jan26'!$A$3:$A$500, "EVT*") + COUNTIF(OFFSET($A$1, 1, 0, ROW()-2, 1), "EVT*") + 1, "0000"), "") -> EVT-2026-0097 | B27: 46066 | C27: Fri | D27: Breakout Area | E27: Ask me Anything- DCO | F27: 70 | G27: Small Event | H27: 03:00 PM | I27: 04:30 PM | L27: Shagun | O27: Confirmed (Done) | P27: Not Required | Q27: Theater style
A28: =IF(OR(D28<>"", E28<>"", K28<>"", N28<>""), "EVT-2026-" & TEXT(COUNTIF('DT-3 Jan26'!$A$3:$A$500, "EVT*") + COUNTIF('DT-4 Jan26'!$A$3:$A$500, "EVT*") + COUNTIF(OFFSET($A$1, 1, 0, ROW()-2, 1), "EVT*") + 1, "0000"), "") -> EVT-2026-0098 | B28: 46067 | C28: Sat | D28: Hiring drive | E28: All Zones | G28: Small Event | H28: 08:00 AM | I28: 05:00 PM | L28: Eisha Mittal | O28: Confirmed (Done) | P28: Not Required | Q28: Details will be shared shortly
A29: =IF(OR(D29<>"", E29<>"", K29<>"", N29<>""), "EVT-2026-" & TEXT(COUNTIF('DT-3 Jan26'!$A$3:$A$500, "EVT*") + COUNTIF('DT-4 Jan26'!$A$3:$A$500, "EVT*") + COUNTIF(OFFSET($A$1, 1, 0, ROW()-2, 1), "EVT*") + 1, "0000"), "") | B29: 46068 | C29: Sun | G29: Small Event | O29: Confirmed (Done) | P29: Not Required
A30: =IF(OR(D30<>"", E30<>"", K30<>"", N30<>""), "EVT-2026-" & TEXT(COUNTIF('DT-3 Jan26'!$A$3:$A$500, "EVT*") + COUNTIF('DT-4 Jan26'!$A$3:$A$500, "EVT*") + COUNTIF(OFFSET($A$1, 1, 0, ROW()-2, 1), "EVT*") + 1, "0000"), "") -> EVT-2026-0099 | B30: 46069 | C30: Mon | D30: MR-305 and 306 | E30: New Joiners Induction | F30: 40 | G30: Small Event | H30: 08:00 AM | I30: 05:00 PM | L30: Deshraj | O30: Confirmed (Done) | P30: Not Required | Q30: Theater style and require writing pad chairs
A31: =IF(OR(D31<>"", E31<>"", K31<>"", N31<>""), "EVT-2026-" & TEXT(COUNTIF('DT-3 Jan26'!$A$3:$A$500, "EVT*") + COUNTIF('DT-4 Jan26'!$A$3:$A$500, "EVT*") + COUNTIF(OFFSET($A$1, 1, 0, ROW()-2, 1), "EVT*") + 1, "0000"), "") -> EVT-2026-0100 | B31: 46070 | C31: Tue | D31: Mr-305 and 306 | E31: DL Workshop | F31: 25 | G31: Small Event | H31: 08:00 AM | I31: 05:00 PM | J31: Cookies +Brownies from Pihu Foods and Lunch will be arranged by Cook House | L31: Deshraj | O31: Confirmed (Done) | P31: Not Required | Q31: Cluster set up, Markers (2-3) , White boards
A32: =IF(OR(D32<>"", E32<>"", K32<>"", N32<>""), "EVT-2026-" & TEXT(COUNTIF('DT-3 Jan26'!$A$3:$A$500, "EVT*") + COUNTIF('DT-4 Jan26'!$A$3:$A$500, "EVT*") + COUNTIF(OFFSET($A$1, 1, 0, ROW()-2, 1), "EVT*") + 1, "0000"), "") -> EVT-2026-0101 | B32: 46071 | C32: Wed | D32: Mr-305 and 306 | E32: DL Workshop | F32: 25 | G32: Small Event | H32: 08:00 AM | I32: 05:00 PM | J32: Cookies +Brownies from Pihu Foods and Lunch will be arranged by Cook House | L32: Deshraj | O32: Confirmed (Done) | P32: Not Required | Q32: Cluster set up, Markers (2-3)
A33: =IF(OR(D33<>"", E33<>"", K33<>"", N33<>""), "EVT-2026-" & TEXT(COUNTIF('DT-3 Jan26'!$A$3:$A$500, "EVT*") + COUNTIF('DT-4 Jan26'!$A$3:$A$500, "EVT*") + COUNTIF(OFFSET($A$1, 1, 0, ROW()-2, 1), "EVT*") + 1, "0000"), "") -> EVT-2026-0102 | B33: 46073 | C33: Fri | D33: Breakout Area/MR-305 and 306 | E33: Culture Immersion NH + Nominations | F33: 35 | G33: Small Event | H33: 02:30 PM | I33: 04:30 PM | L33: Deshraj | O33: Confirmed (Done) | P33: Not Required | Q33: Cluster set up
A34: =IF(OR(D34<>"", E34<>"", K34<>"", N34<>""), "EVT-2026-" & TEXT(COUNTIF('DT-3 Jan26'!$A$3:$A$500, "EVT*") + COUNTIF('DT-4 Jan26'!$A$3:$A$500, "EVT*") + COUNTIF(OFFSET($A$1, 1, 0, ROW()-2, 1), "EVT*") + 1, "0000"), "") -> EVT-2026-0103 | B34: 46073 | C34: Fri | D34: Cafeteria +breakout Area | E34: AI Risk and Governance Session by KPMG | F34: 120 | G34: Big Event | H34: 03:00 PM | I34: 04:00 PM | L34: Maanshu | O34: Confirmed (Done) | P34: Not Required | Q34: Theater style
A35: =IF(OR(D35<>"", E35<>"", K35<>"", N35<>""), "EVT-2026-" & TEXT(COUNTIF('DT-3 Jan26'!$A$3:$A$500, "EVT*") + COUNTIF('DT-4 Jan26'!$A$3:$A$500, "EVT*") + COUNTIF(OFFSET($A$1, 1, 0, ROW()-2, 1), "EVT*") + 1, "0000"), "") -> EVT-2026-0104 | B35: 46074 | C35: Sat | D35: Hiring drive | G35: Small Event | H35: 08:00 AM | I35: 05:00 PM | L35: Mohit Mishra | N35: 8th Jan'26 | O35: Confirmed (Done) | P35: Not Required
A36: =IF(OR(D36<>"", E36<>"", K36<>"", N36<>""), "EVT-2026-" & TEXT(COUNTIF('DT-3 Jan26'!$A$3:$A$500, "EVT*") + COUNTIF('DT-4 Jan26'!$A$3:$A$500, "EVT*") + COUNTIF(OFFSET($A$1, 1, 0, ROW()-2, 1), "EVT*") + 1, "0000"), "") | B36: 46075 | C36: Sun | G36: Small Event | O36: Confirmed (Done) | P36: Not Required
A37: =IF(OR(D37<>"", E37<>"", K37<>"", N37<>""), "EVT-2026-" & TEXT(COUNTIF('DT-3 Jan26'!$A$3:$A$500, "EVT*") + COUNTIF('DT-4 Jan26'!$A$3:$A$500, "EVT*") + COUNTIF(OFFSET($A$1, 1, 0, ROW()-2, 1), "EVT*") + 1, "0000"), "") -> EVT-2026-0105 | B37: 46076 | C37: Mon | D37: MR-305 and 306 | E37: New Joiners Induction | F37: 35 | G37: Small Event | H37: 08:00 AM | I37: 05:00 PM | J37: Lunch | L37: Deshraj | O37: Confirmed (Done) | P37: Not Required | Q37: Classroomset up
A38: =IF(OR(D38<>"", E38<>"", K38<>"", N38<>""), "EVT-2026-" & TEXT(COUNTIF('DT-3 Jan26'!$A$3:$A$500, "EVT*") + COUNTIF('DT-4 Jan26'!$A$3:$A$500, "EVT*") + COUNTIF(OFFSET($A$1, 1, 0, ROW()-2, 1), "EVT*") + 1, "0000"), "") -> EVT-2026-0106 | B38: 46077 | C38: Tue | D38: Breakout Area+Cafteria | E38: Screen Testing | F38: 0 | G38: Small Event | H38: 08:00 AM | I38: 05:00 PM | L38: Sahil Kumar | O38: Confirmed (Done) | P38: Not Required | Q38: No setup- The vendor will come and do the testing of the TV Screens , no bookings on that day
A39: =IF(OR(D39<>"", E39<>"", K39<>"", N39<>""), "EVT-2026-" & TEXT(COUNTIF('DT-3 Jan26'!$A$3:$A$500, "EVT*") + COUNTIF('DT-4 Jan26'!$A$3:$A$500, "EVT*") + COUNTIF(OFFSET($A$1, 1, 0, ROW()-2, 1), "EVT*") + 1, "0000"), "") -> EVT-2026-0107 | B39: 46078 | C39: Wed | D39: MR-305 and 306 | E39: PLE | F39: 25 | G39: Small Event | H39: 02:00 PM | I39: 05:00 PM | L39: Deshraj | O39: Confirmed (Done) | P39: Not Required | Q39: Cluster set up (add one notepad chair)
A40: =IF(OR(D40<>"", E40<>"", K40<>"", N40<>""), "EVT-2026-" & TEXT(COUNTIF('DT-3 Jan26'!$A$3:$A$500, "EVT*") + COUNTIF('DT-4 Jan26'!$A$3:$A$500, "EVT*") + COUNTIF(OFFSET($A$1, 1, 0, ROW()-2, 1), "EVT*") + 1, "0000"), "") -> EVT-2026-0108 | B40: 46078 | C40: Wed | D40: Breakout Area+Cafteria | E40: P& C Montly Session | F40: 60 | G40: Small Event | H40: 03:00 AM | I40: 05:00 PM | L40: Kaushik | O40: Confirmed (Done) | P40: Not Required | Q40: Cluster set u
A41: =IF(OR(D41<>"", E41<>"", K41<>"", N41<>""), "EVT-2026-" & TEXT(COUNTIF('DT-3 Jan26'!$A$3:$A$500, "EVT*") + COUNTIF('DT-4 Jan26'!$A$3:$A$500, "EVT*") + COUNTIF(OFFSET($A$1, 1, 0, ROW()-2, 1), "EVT*") + 1, "0000"), "") -> EVT-2026-0109 | B41: 46078 | C41: Wed | D41: Breakout Area +Cafeteria | E41: DCO & CF Townhall | F41: 150 | G41: Big Event | H41: 03:00 PM | I41: 04:30 PM | L41: Shagun | O41: Canceled | P41: Not Required | Q41: Details are awaited
A42: =IF(OR(D42<>"", E42<>"", K42<>"", N42<>""), "EVT-2026-" & TEXT(COUNTIF('DT-3 Jan26'!$A$3:$A$500, "EVT*") + COUNTIF('DT-4 Jan26'!$A$3:$A$500, "EVT*") + COUNTIF(OFFSET($A$1, 1, 0, ROW()-2, 1), "EVT*") + 1, "0000"), "") -> EVT-2026-0110 | B42: 46079 | C42: Thu | D42: MR-305 and 306 | E42: PLE | F42: 25 | G42: Small Event | H42: 02:00 PM | I42: 05:00 PM | L42: Deshraj | O42: Confirmed (Done) | P42: Not Required | Q42: Cluster set up (add one notepad chair)
A43: =IF(OR(D43<>"", E43<>"", K43<>"", N43<>""), "EVT-2026-" & TEXT(COUNTIF('DT-3 Jan26'!$A$3:$A$500, "EVT*") + COUNTIF('DT-4 Jan26'!$A$3:$A$500, "EVT*") + COUNTIF(OFFSET($A$1, 1, 0, ROW()-2, 1), "EVT*") + 1, "0000"), "") -> EVT-2026-0111 | B43: 46079 | C43: Thu | D43: Cafeteria +Breakout area | E43: CIO BP&D Town Hall for Q2 | F43: 100 | G43: Big Event | H43: 10:00 AM | I43: 11:30 AM | L43: Ekta | O43: Confirmed (Done) | P43: Not Required | Q43: Theater style
A44: =IF(OR(D44<>"", E44<>"", K44<>"", N44<>""), "EVT-2026-" & TEXT(COUNTIF('DT-3 Jan26'!$A$3:$A$500, "EVT*") + COUNTIF('DT-4 Jan26'!$A$3:$A$500, "EVT*") + COUNTIF(OFFSET($A$1, 1, 0, ROW()-2, 1), "EVT*") + 1, "0000"), "") -> EVT-2026-0112 | B44: 46080 | C44: Fri | D44: Breakout Area +Cafeteria | E44: Personal Banking | F44: 120 | G44: Big Event | H44: 03:00 PM | I44: 04:00 PM | L44: Maanshu | O44: Confirmed (Done) | P44: Not Required | Q44: Theater style - Tentativley booking
A45: =IF(OR(D45<>"", E45<>"", K45<>"", N45<>""), "EVT-2026-" & TEXT(COUNTIF('DT-3 Jan26'!$A$3:$A$500, "EVT*") + COUNTIF('DT-4 Jan26'!$A$3:$A$500, "EVT*") + COUNTIF(OFFSET($A$1, 1, 0, ROW()-2, 1), "EVT*") + 1, "0000"), "") -> EVT-2026-0113 | B45: 46081 | C45: Sat | E45: Hiring Drive | G45: Small Event | H45: 08:30 AM | I45: 05:00 PM | L45: Tarun Bajaj | N45: 20th Feb'2026 | O45: Confirmed (Done) | P45: Not Required | Q45: Awaiting for the details
A46: =IF(OR(D46<>"", E46<>"", K46<>"", N46<>""), "EVT-2026-" & TEXT(COUNTIF('DT-3 Jan26'!$A$3:$A$500, "EVT*") + COUNTIF('DT-4 Jan26'!$A$3:$A$500, "EVT*") + COUNTIF(OFFSET($A$1, 1, 0, ROW()-2, 1), "EVT*") + 1, "0000"), "") | G46: Small Event | O46: Confirmed (Done) | P46: Not Required
A47: =IF(OR(D47<>"", E47<>"", K47<>"", N47<>""), "EVT-2026-" & TEXT(COUNTIF('DT-3 Jan26'!$A$3:$A$500, "EVT*") + COUNTIF('DT-4 Jan26'!$A$3:$A$500, "EVT*") + COUNTIF(OFFSET($A$1, 1, 0, ROW()-2, 1), "EVT*") + 1, "0000"), "") | G47: Small Event | O47: Confirmed (Done) | P47: Not Required
A48: =IF(OR(D48<>"", E48<>"", K48<>"", N48<>""), "EVT-2026-" & TEXT(COUNTIF('DT-3 Jan26'!$A$3:$A$500, "EVT*") + COUNTIF('DT-4 Jan26'!$A$3:$A$500, "EVT*") + COUNTIF(OFFSET($A$1, 1, 0, ROW()-2, 1), "EVT*") + 1, "0000"), "") | G48: Small Event | O48: Confirmed (Done) | P48: Not Required
A49: =IF(OR(D49<>"", E49<>"", K49<>"", N49<>""), "EVT-2026-" & TEXT(COUNTIF('DT-3 Jan26'!$A$3:$A$500, "EVT*") + COUNTIF('DT-4 Jan26'!$A$3:$A$500, "EVT*") + COUNTIF(OFFSET($A$1, 1, 0, ROW()-2, 1), "EVT*") + 1, "0000"), "") | G49: Small Event | O49: Confirmed (Done) | P49: Not Required
A50: =IF(OR(D50<>"", E50<>"", K50<>"", N50<>""), "EVT-2026-" & TEXT(COUNTIF('DT-3 Jan26'!$A$3:$A$500, "EVT*") + COUNTIF('DT-4 Jan26'!$A$3:$A$500, "EVT*") + COUNTIF(OFFSET($A$1, 1, 0, ROW()-2, 1), "EVT*") + 1, "0000"), "") | G50: Small Event | O50: Confirmed (Done) | P50: Not Required

Sheet DT-4 Feb26
A1: 🏠 ⮌ RETURN TO DASHBOARD | D1: DOWNTOWN-4 EVENT OPERATIONS TRACKER • FEB26 | O1: 🟢 Green: Confirmed | 🟡 Yellow: Pending | 🔴 Red: Canceled
A2: Event ID | B2: Event Date | C2: Day | D2: Location | E2: Floor | F2: Event Type / Title | G2: Capacity | H2: Event Scale | I2: Event Start Time | J2: Event End Time | K2: F& B | L2: Logistic Support | M2: Booked By | N2: Requester Email | O2: Booking Date | P2: Status | Q2: Feedback Form | R2: Remarks | S2: Booking Taken By
A3: =IF(OR(D3<>"", F3<>"", L3<>"", O3<>""), "EVT-2026-" & TEXT(COUNTIF('DT-3 Jan26'!$A$3:$A$500, "EVT*") + COUNTIF('DT-4 Jan26'!$A$3:$A$500, "EVT*") + COUNTIF('DT-3 Feb26'!$A$3:$A$500, "EVT*") + COUNTIF(OFFSET($A$1, 1, 0, ROW()-2, 1), "EVT*") + 1, "0000"), "") | B3: 46054 | C3: Sun | H3: Small Event | P3: Confirmed (Done) | Q3: Not Required
A4: =IF(OR(D4<>"", F4<>"", L4<>"", O4<>""), "EVT-2026-" & TEXT(COUNTIF('DT-3 Jan26'!$A$3:$A$500, "EVT*") + COUNTIF('DT-4 Jan26'!$A$3:$A$500, "EVT*") + COUNTIF('DT-3 Feb26'!$A$3:$A$500, "EVT*") + COUNTIF(OFFSET($A$1, 1, 0, ROW()-2, 1), "EVT*") + 1, "0000"), "") -> EVT-2026-0114 | B4: 46055 | C4: Mon | D4: MR-506 | H4: Small Event | P4: Confirmed (Done) | Q4: Not Required
A5: =IF(OR(D5<>"", F5<>"", L5<>"", O5<>""), "EVT-2026-" & TEXT(COUNTIF('DT-3 Jan26'!$A$3:$A$500, "EVT*") + COUNTIF('DT-4 Jan26'!$A$3:$A$500, "EVT*") + COUNTIF('DT-3 Feb26'!$A$3:$A$500, "EVT*") + COUNTIF(OFFSET($A$1, 1, 0, ROW()-2, 1), "EVT*") + 1, "0000"), "") -> EVT-2026-0115 | B5: 46055 | C5: Mon | D5: Cafeteria | E5: L-5 | F5: All Hands- DEDA | G5: 180 | H5: Big Event | I5: 03:00 PM | J5: 04:15 PM | L5: 150 Samosa and Brownies - PIHU Foods | M5: Ekta Sharma - Ruchi Bubber | O5: 13th Jan'26 | P5: Confirmed (Done) | Q5: Not Required | R5: Theater style
A6: =IF(OR(D6<>"", F6<>"", L6<>"", O6<>""), "EVT-2026-" & TEXT(COUNTIF('DT-3 Jan26'!$A$3:$A$500, "EVT*") + COUNTIF('DT-4 Jan26'!$A$3:$A$500, "EVT*") + COUNTIF('DT-3 Feb26'!$A$3:$A$500, "EVT*") + COUNTIF(OFFSET($A$1, 1, 0, ROW()-2, 1), "EVT*") + 1, "0000"), "") -> EVT-2026-0116 | B6: 46055 | C6: Mon | D6: Zone E Breakout Area | E6: L-4 | F6: Tech Onboarding - | G6: 30 | H6: Small Event | I6: 02:00 PM | J6: 05:00 PM | K6: No | L6: Nil | M6: Soamya | O6: 46008 | P6: Confirmed (Done) | Q6: Not Required | R6: Theate style
A7: =IF(OR(D7<>"", F7<>"", L7<>"", O7<>""), "EVT-2026-" & TEXT(COUNTIF('DT-3 Jan26'!$A$3:$A$500, "EVT*") + COUNTIF('DT-4 Jan26'!$A$3:$A$500, "EVT*") + COUNTIF('DT-3 Feb26'!$A$3:$A$500, "EVT*") + COUNTIF(OFFSET($A$1, 1, 0, ROW()-2, 1), "EVT*") + 1, "0000"), "") -> EVT-2026-0117 | B7: 46055 | C7: Mon | D7: Hackable Area | E7: L-5 | H7: Small Event | P7: Confirmed (Done) | Q7: Not Required
A8: =IF(OR(D8<>"", F8<>"", L8<>"", O8<>""), "EVT-2026-" & TEXT(COUNTIF('DT-3 Jan26'!$A$3:$A$500, "EVT*") + COUNTIF('DT-4 Jan26'!$A$3:$A$500, "EVT*") + COUNTIF('DT-3 Feb26'!$A$3:$A$500, "EVT*") + COUNTIF(OFFSET($A$1, 1, 0, ROW()-2, 1), "EVT*") + 1, "0000"), "") -> EVT-2026-0118 | B8: 46056 | C8: Tue | D8: Cafteria | E8: L-5 | F8: Rewards and Recognition team event for all of ES & CIM area. | G8: 100 | H8: Big Event | I8: 03:00 PM | J8: 03:45 PM | M8: Saurbh Dutta | O8: 28th Jan'26 | P8: Confirmed (Done) | Q8: Not Required | R8: Theater style
A9: =IF(OR(D9<>"", F9<>"", L9<>"", O9<>""), "EVT-2026-" & TEXT(COUNTIF('DT-3 Jan26'!$A$3:$A$500, "EVT*") + COUNTIF('DT-4 Jan26'!$A$3:$A$500, "EVT*") + COUNTIF('DT-3 Feb26'!$A$3:$A$500, "EVT*") + COUNTIF(OFFSET($A$1, 1, 0, ROW()-2, 1), "EVT*") + 1, "0000"), "") -> EVT-2026-0119 | B9: 46056 | C9: Tue | D9: Zone E Breakout Area | E9: L-4 | F9: FCO OCDD Townhall | G9: 70 | H9: Small Event | I9: 09:30 AM | J9: 10:30 AM | K9: No | M9: Neelu Rana | O9: 20th Jan'26 | P9: Confirmed (Done) | Q9: Not Required | R9: Theate style
A10: =IF(OR(D10<>"", F10<>"", L10<>"", O10<>""), "EVT-2026-" & TEXT(COUNTIF('DT-3 Jan26'!$A$3:$A$500, "EVT*") + COUNTIF('DT-4 Jan26'!$A$3:$A$500, "EVT*") + COUNTIF('DT-3 Feb26'!$A$3:$A$500, "EVT*") + COUNTIF(OFFSET($A$1, 1, 0, ROW()-2, 1), "EVT*") + 1, "0000"), "") -> EVT-2026-0120 | B10: 46056 | C10: Tue | D10: Zone E Breakout Area | E10: L-4 | F10: Codility | G10: 50 | H10: Small Event | I10: 01:30 PM | J10: 04:00 PM | M10: Parul Wadhera | O10: 46008 | P10: Confirmed (Done) | Q10: Not Required | R10: Classroom set up
A11: =IF(OR(D11<>"", F11<>"", L11<>"", O11<>""), "EVT-2026-" & TEXT(COUNTIF('DT-3 Jan26'!$A$3:$A$500, "EVT*") + COUNTIF('DT-4 Jan26'!$A$3:$A$500, "EVT*") + COUNTIF('DT-3 Feb26'!$A$3:$A$500, "EVT*") + COUNTIF(OFFSET($A$1, 1, 0, ROW()-2, 1), "EVT*") + 1, "0000"), "") -> EVT-2026-0121 | B11: 46056 | C11: Tue | D11: Innovation Hub | E11: L_4 | F11: Steve’s Townhall | G11: 90 | H11: Small Event | I11: 09:00 AM | J11: 10:00 AM | M11: Ekta Sharma | P11: Confirmed (Done) | Q11: Not Required
A12: =IF(OR(D12<>"", F12<>"", L12<>"", O12<>""), "EVT-2026-" & TEXT(COUNTIF('DT-3 Jan26'!$A$3:$A$500, "EVT*") + COUNTIF('DT-4 Jan26'!$A$3:$A$500, "EVT*") + COUNTIF('DT-3 Feb26'!$A$3:$A$500, "EVT*") + COUNTIF(OFFSET($A$1, 1, 0, ROW()-2, 1), "EVT*") + 1, "0000"), "") -> EVT-2026-0122 | B12: 46056 | C12: Tue | D12: Innovation Hub | E12: L-5 | F12: Townhall for Workplace- Greg’s Townhall | G12: 90 | H12: Small Event | I12: 12:00 PM | J12: 01:30 PM | M12: Kriti Kapoor | O12: 28th Jan'26 | P12: Confirmed (Done) | Q12: Not Required | R12: theater style, fork, spoons, tissue paper , tea and water bottles (4) for the speaker and place round table for the water
A13: =IF(OR(D13<>"", F13<>"", L13<>"", O13<>""), "EVT-2026-" & TEXT(COUNTIF('DT-3 Jan26'!$A$3:$A$500, "EVT*") + COUNTIF('DT-4 Jan26'!$A$3:$A$500, "EVT*") + COUNTIF('DT-3 Feb26'!$A$3:$A$500, "EVT*") + COUNTIF(OFFSET($A$1, 1, 0, ROW()-2, 1), "EVT*") + 1, "0000"), "") -> EVT-2026-0123 | B13: 46056 | C13: Tue | D13: Hackable Area | E13: L-5 | F13: Haydn's All hand Meet | G13: 80 | H13: Small Event | I13: 12:00 PM | J13: 01:00 PM | M13: Tripti Anis | O13: 46044 | P13: Confirmed (Done) | Q13: Not Required | R13: Theate style
A14: =IF(OR(D14<>"", F14<>"", L14<>"", O14<>""), "EVT-2026-" & TEXT(COUNTIF('DT-3 Jan26'!$A$3:$A$500, "EVT*") + COUNTIF('DT-4 Jan26'!$A$3:$A$500, "EVT*") + COUNTIF('DT-3 Feb26'!$A$3:$A$500, "EVT*") + COUNTIF(OFFSET($A$1, 1, 0, ROW()-2, 1), "EVT*") + 1, "0000"), "") -> EVT-2026-0124 | B14: 46056 | C14: Tue | D14: Hackable Area | E14: L-5 | F14: Dry Run - PEDB Tech Global Townhall | H14: Small Event | I14: 10:30 AM | J14: 11:00 AM | M14: Ekta Sharma/ Rashmi Chugh | O14: 46055 | P14: Confirmed (Done) | Q14: Not Required | R14: no set up required
A15: =IF(OR(D15<>"", F15<>"", L15<>"", O15<>""), "EVT-2026-" & TEXT(COUNTIF('DT-3 Jan26'!$A$3:$A$500, "EVT*") + COUNTIF('DT-4 Jan26'!$A$3:$A$500, "EVT*") + COUNTIF('DT-3 Feb26'!$A$3:$A$500, "EVT*") + COUNTIF(OFFSET($A$1, 1, 0, ROW()-2, 1), "EVT*") + 1, "0000"), "") -> EVT-2026-0125 | B15: 46057 | C15: Wed | D15: Innovation Hub | E15: L-5 | F15: Wellness | G15: 150 | H15: Big Event | I15: 03:00 PM | J15: 04:00 PM | M15: Ruhi Malhotra | O15: 46049 | P15: Confirmed (Done) | Q15: Not Required | R15: Theater style- she will share more details
A16: =IF(OR(D16<>"", F16<>"", L16<>"", O16<>""), "EVT-2026-" & TEXT(COUNTIF('DT-3 Jan26'!$A$3:$A$500, "EVT*") + COUNTIF('DT-4 Jan26'!$A$3:$A$500, "EVT*") + COUNTIF('DT-3 Feb26'!$A$3:$A$500, "EVT*") + COUNTIF(OFFSET($A$1, 1, 0, ROW()-2, 1), "EVT*") + 1, "0000"), "") -> EVT-2026-0126 | B16: 46057 | C16: Wed | D16: Hackable Area | E16: L-5 | F16: PEB Tech Global townhall | G16: 60 | H16: Small Event | I16: 10:30 AM | J16: 12:00 PM | L16: Refreshments Pihu Foods - cookies and tea | M16: Ekta Sharma | O16: 46051 | P16: Confirmed (Done) | Q16: Not Required | R16: Theater style
A17: =IF(OR(D17<>"", F17<>"", L17<>"", O17<>""), "EVT-2026-" & TEXT(COUNTIF('DT-3 Jan26'!$A$3:$A$500, "EVT*") + COUNTIF('DT-4 Jan26'!$A$3:$A$500, "EVT*") + COUNTIF('DT-3 Feb26'!$A$3:$A$500, "EVT*") + COUNTIF(OFFSET($A$1, 1, 0, ROW()-2, 1), "EVT*") + 1, "0000"), "") -> EVT-2026-0127 | B17: 46057 | C17: Wed | D17: Hackable Area | E17: L-5 | F17: Tech Session | G17: 80 | H17: Small Event | I17: 03:00 PM | J17: 04:00 PM | M17: Rupika | O17: 46056 | P17: Confirmed (Done) | Q17: Not Required
A18: =IF(OR(D18<>"", F18<>"", L18<>"", O18<>""), "EVT-2026-" & TEXT(COUNTIF('DT-3 Jan26'!$A$3:$A$500, "EVT*") + COUNTIF('DT-4 Jan26'!$A$3:$A$500, "EVT*") + COUNTIF('DT-3 Feb26'!$A$3:$A$500, "EVT*") + COUNTIF(OFFSET($A$1, 1, 0, ROW()-2, 1), "EVT*") + 1, "0000"), "") -> EVT-2026-0128 | B18: 46058 | C18: Thu | D18: Innovation Hub | E18: L-1 | F18: Cloud Risks and Controls | G18: 100 | H18: Big Event | I18: 11:00 AM | J18: 12:30 PM | M18: Maanshu Chugh | O18: 46043 | P18: Confirmed (Done) | Q18: Not Required | R18: Theater style
A19: =IF(OR(D19<>"", F19<>"", L19<>"", O19<>""), "EVT-2026-" & TEXT(COUNTIF('DT-3 Jan26'!$A$3:$A$500, "EVT*") + COUNTIF('DT-4 Jan26'!$A$3:$A$500, "EVT*") + COUNTIF('DT-3 Feb26'!$A$3:$A$500, "EVT*") + COUNTIF(OFFSET($A$1, 1, 0, ROW()-2, 1), "EVT*") + 1, "0000"), "") -> EVT-2026-0129 | B19: 46058 | C19: Thu | D19: Hackable space | E19: L-5 | F19: Enterprise Data & Analytics | G19: 25 | H19: Small Event | I19: 02:00 PM | J19: 03:00 PM | M19: Shashank Shekhar | O19: 4th Feb'26 | P19: Confirmed (Done) | Q19: Not Required | R19: Theater style
A20: =IF(OR(D20<>"", F20<>"", L20<>"", O20<>""), "EVT-2026-" & TEXT(COUNTIF('DT-3 Jan26'!$A$3:$A$500, "EVT*") + COUNTIF('DT-4 Jan26'!$A$3:$A$500, "EVT*") + COUNTIF('DT-3 Feb26'!$A$3:$A$500, "EVT*") + COUNTIF(OFFSET($A$1, 1, 0, ROW()-2, 1), "EVT*") + 1, "0000"), "") -> EVT-2026-0130 | B20: 46058 | C20: Thu | D20: Hackable space | E20: L-5 | G20: 50 | H20: Small Event | I20: 04:00 PM | J20: 05:00 PM | M20: Laxmi Prasad | O20: 5th Feb'2026 | P20: Confirmed (Done) | Q20: Not Required | R20: Theater style
A21: =IF(OR(D21<>"", F21<>"", L21<>"", O21<>""), "EVT-2026-" & TEXT(COUNTIF('DT-3 Jan26'!$A$3:$A$500, "EVT*") + COUNTIF('DT-4 Jan26'!$A$3:$A$500, "EVT*") + COUNTIF('DT-3 Feb26'!$A$3:$A$500, "EVT*") + COUNTIF(OFFSET($A$1, 1, 0, ROW()-2, 1), "EVT*") + 1, "0000"), "") -> EVT-2026-0131 | B21: 46058 | C21: Thu | D21: Innovation Hub | E21: L-5 | F21: Wellness | G21: 150 | H21: Big Event | I21: 03:00 PM | J21: 04:30 PM | L21: Snacks arrangements for the female colleauge+Tea- awaiting the response | M21: Ruhi Malhotra | O21: 46049 | P21: Confirmed (Done) | Q21: Not Required | R21: Theater style- tea and coffee from Vending machines , arrange the mugs in the advance.
A22: =IF(OR(D22<>"", F22<>"", L22<>"", O22<>""), "EVT-2026-" & TEXT(COUNTIF('DT-3 Jan26'!$A$3:$A$500, "EVT*") + COUNTIF('DT-4 Jan26'!$A$3:$A$500, "EVT*") + COUNTIF('DT-3 Feb26'!$A$3:$A$500, "EVT*") + COUNTIF(OFFSET($A$1, 1, 0, ROW()-2, 1), "EVT*") + 1, "0000"), "") -> EVT-2026-0132 | B22: 46058 | C22: Thu | D22: Zone E Breakout Area | E22: L-4 | F22: Customer Master team connect. | G22: 40 | H22: Small Event | I22: 02:30 PM | J22: 04:00 PM | K22: No | L22: NIL | M22: Vikas K | O22: 46006 | P22: Confirmed (Done) | Q22: Not Required | R22: Theater style
A23: =IF(OR(D23<>"", F23<>"", L23<>"", O23<>""), "EVT-2026-" & TEXT(COUNTIF('DT-3 Jan26'!$A$3:$A$500, "EVT*") + COUNTIF('DT-4 Jan26'!$A$3:$A$500, "EVT*") + COUNTIF('DT-3 Feb26'!$A$3:$A$500, "EVT*") + COUNTIF(OFFSET($A$1, 1, 0, ROW()-2, 1), "EVT*") + 1, "0000"), "") -> EVT-2026-0133 | B23: 46058 | C23: Thu | D23: Zone E Breakout Area | E23: L-5 | F23: Codility | G23: 50 | H23: Small Event | I23: 01:30 PM | J23: 04:00 PM | M23: Parul Wadhera | O23: 46008 | P23: Confirmed (Done) | Q23: Not Required | R23: Classroom set up
A24: =IF(OR(D24<>"", F24<>"", L24<>"", O24<>""), "EVT-2026-" & TEXT(COUNTIF('DT-3 Jan26'!$A$3:$A$500, "EVT*") + COUNTIF('DT-4 Jan26'!$A$3:$A$500, "EVT*") + COUNTIF('DT-3 Feb26'!$A$3:$A$500, "EVT*") + COUNTIF(OFFSET($A$1, 1, 0, ROW()-2, 1), "EVT*") + 1, "0000"), "") -> EVT-2026-0134 | B24: 46059 | C24: Fri | D24: Hackable space | E24: L-5 | F24: OPS New Joiners | H24: Small Event | I24: 10:30 AM | J24: 12:00 PM | M24: Shikha Saxena | O24: 4th Feb'26 | P24: Confirmed (Done) | Q24: Not Required | R24: Theater style
A25: =IF(OR(D25<>"", F25<>"", L25<>"", O25<>""), "EVT-2026-" & TEXT(COUNTIF('DT-3 Jan26'!$A$3:$A$500, "EVT*") + COUNTIF('DT-4 Jan26'!$A$3:$A$500, "EVT*") + COUNTIF('DT-3 Feb26'!$A$3:$A$500, "EVT*") + COUNTIF(OFFSET($A$1, 1, 0, ROW()-2, 1), "EVT*") + 1, "0000"), "") | B25: 46059 | C25: Fri | H25: Small Event | P25: Confirmed (Done) | Q25: Not Required
A26: =IF(OR(D26<>"", F26<>"", L26<>"", O26<>""), "EVT-2026-" & TEXT(COUNTIF('DT-3 Jan26'!$A$3:$A$500, "EVT*") + COUNTIF('DT-4 Jan26'!$A$3:$A$500, "EVT*") + COUNTIF('DT-3 Feb26'!$A$3:$A$500, "EVT*") + COUNTIF(OFFSET($A$1, 1, 0, ROW()-2, 1), "EVT*") + 1, "0000"), "") -> EVT-2026-0135 | B26: 46060 | C26: Sat | D26: No hiring drive due to the family day | H26: Small Event | P26: Confirmed (Done) | Q26: Not Required
A27: =IF(OR(D27<>"", F27<>"", L27<>"", O27<>""), "EVT-2026-" & TEXT(COUNTIF('DT-3 Jan26'!$A$3:$A$500, "EVT*") + COUNTIF('DT-4 Jan26'!$A$3:$A$500, "EVT*") + COUNTIF('DT-3 Feb26'!$A$3:$A$500, "EVT*") + COUNTIF(OFFSET($A$1, 1, 0, ROW()-2, 1), "EVT*") + 1, "0000"), "") | B27: 46061 | C27: Sun | H27: Small Event | P27: Confirmed (Done) | Q27: Not Required
A28: =IF(OR(D28<>"", F28<>"", L28<>"", O28<>""), "EVT-2026-" & TEXT(COUNTIF('DT-3 Jan26'!$A$3:$A$500, "EVT*") + COUNTIF('DT-4 Jan26'!$A$3:$A$500, "EVT*") + COUNTIF('DT-3 Feb26'!$A$3:$A$500, "EVT*") + COUNTIF(OFFSET($A$1, 1, 0, ROW()-2, 1), "EVT*") + 1, "0000"), "") -> EVT-2026-0136 | B28: 9 to 13 Feb | C28: Mon | D28: Desk no W.5.F.765 | E28: L-5 | F28: Gratitude Week | H28: Small Event | I28: 08:00 AM | J28: 05:00 PM | M28: Vaibhav Anand | O28: 3rd Feb'26 | P28: Confirmed (Done) | Q28: Not Required | R28: Place the white board near to Desk no F-765
A29: =IF(OR(D29<>"", F29<>"", L29<>"", O29<>""), "EVT-2026-" & TEXT(COUNTIF('DT-3 Jan26'!$A$3:$A$500, "EVT*") + COUNTIF('DT-4 Jan26'!$A$3:$A$500, "EVT*") + COUNTIF('DT-3 Feb26'!$A$3:$A$500, "EVT*") + COUNTIF(OFFSET($A$1, 1, 0, ROW()-2, 1), "EVT*") + 1, "0000"), "") -> EVT-2026-0137 | B29: 46062 | C29: Mon | D29: Zone E Breakout Area | E29: L-4 | F29: Enterprise Data & Analytics | G29: 25 | H29: Small Event | I29: 02:00 PM | J29: 03:00 PM | M29: Shashank Shekhar | O29: 4th Feb'26 | P29: Confirmed (Done) | Q29: Not Required | S29: Theater style
A30: =IF(OR(D30<>"", F30<>"", L30<>"", O30<>""), "EVT-2026-" & TEXT(COUNTIF('DT-3 Jan26'!$A$3:$A$500, "EVT*") + COUNTIF('DT-4 Jan26'!$A$3:$A$500, "EVT*") + COUNTIF('DT-3 Feb26'!$A$3:$A$500, "EVT*") + COUNTIF(OFFSET($A$1, 1, 0, ROW()-2, 1), "EVT*") + 1, "0000"), "") -> EVT-2026-0138 | B30: 46063 | C30: Tue | D30: Zone E Breakout Area | E30: L-5 | H30: Small Event | I30: 10:00 AM | J30: 11:00 AM | M30: Atul Kumar | P30: Confirmed (Done) | Q30: Not Required | R30: Weighing Machine
A31: =IF(OR(D31<>"", F31<>"", L31<>"", O31<>""), "EVT-2026-" & TEXT(COUNTIF('DT-3 Jan26'!$A$3:$A$500, "EVT*") + COUNTIF('DT-4 Jan26'!$A$3:$A$500, "EVT*") + COUNTIF('DT-3 Feb26'!$A$3:$A$500, "EVT*") + COUNTIF(OFFSET($A$1, 1, 0, ROW()-2, 1), "EVT*") + 1, "0000"), "") -> EVT-2026-0139 | B31: 46063 | C31: Tue | D31: Zone E Breakout Area | E31: L-5 | H31: Small Event | I31: 03:30 PM | J31: 04:30 PM | M31: Atul Kumar | P31: Confirmed (Done) | Q31: Not Required | R31: Weighing Machine
A32: =IF(OR(D32<>"", F32<>"", L32<>"", O32<>""), "EVT-2026-" & TEXT(COUNTIF('DT-3 Jan26'!$A$3:$A$500, "EVT*") + COUNTIF('DT-4 Jan26'!$A$3:$A$500, "EVT*") + COUNTIF('DT-3 Feb26'!$A$3:$A$500, "EVT*") + COUNTIF(OFFSET($A$1, 1, 0, ROW()-2, 1), "EVT*") + 1, "0000"), "") -> EVT-2026-0140 | B32: 46063 | C32: Tue | D32: Zone E Breakout Area | E32: L-5 | F32: CIB Transformation domain meet and greet with our AU visitors | G32: 25 | H32: Small Event | I32: 01:30 PM | J32: 02:30 PM | M32: Prateek Sharma | O32: 3rd Feb'26 | P32: Confirmed (Done) | Q32: Not Required | R32: Theater style
A33: =IF(OR(D33<>"", F33<>"", L33<>"", O33<>""), "EVT-2026-" & TEXT(COUNTIF('DT-3 Jan26'!$A$3:$A$500, "EVT*") + COUNTIF('DT-4 Jan26'!$A$3:$A$500, "EVT*") + COUNTIF('DT-3 Feb26'!$A$3:$A$500, "EVT*") + COUNTIF(OFFSET($A$1, 1, 0, ROW()-2, 1), "EVT*") + 1, "0000"), "") -> EVT-2026-0141 | B33: 46063 | C33: Tue | D33: Zone E Breakout Area | E33: L-4 | F33: Codility | G33: 50 | H33: Small Event | I33: 01:30 PM | J33: 04:00 PM | M33: Parul Wadhera | O33: 46008 | P33: Confirmed (Done) | Q33: Not Required | R33: Classroom set up
A34: =IF(OR(D34<>"", F34<>"", L34<>"", O34<>""), "EVT-2026-" & TEXT(COUNTIF('DT-3 Jan26'!$A$3:$A$500, "EVT*") + COUNTIF('DT-4 Jan26'!$A$3:$A$500, "EVT*") + COUNTIF('DT-3 Feb26'!$A$3:$A$500, "EVT*") + COUNTIF(OFFSET($A$1, 1, 0, ROW()-2, 1), "EVT*") + 1, "0000"), "") -> EVT-2026-0142 | B34: 46063 | C34: Tue | D34: Innovation Hub | E34: L-1 | F34: Meeting | H34: Small Event | I34: 08:00 AM | J34: 05:00 AM | M34: Prem | P34: Confirmed (Done) | Q34: Not Required | R34: no set up required
A35: =IF(OR(D35<>"", F35<>"", L35<>"", O35<>""), "EVT-2026-" & TEXT(COUNTIF('DT-3 Jan26'!$A$3:$A$500, "EVT*") + COUNTIF('DT-4 Jan26'!$A$3:$A$500, "EVT*") + COUNTIF('DT-3 Feb26'!$A$3:$A$500, "EVT*") + COUNTIF(OFFSET($A$1, 1, 0, ROW()-2, 1), "EVT*") + 1, "0000"), "") -> EVT-2026-0143 | B35: 46064 | C35: Wed | D35: Innovation Hub | E35: L-1 | F35: LT Connect with Frank | G35: 15 | H35: Small Event | I35: 10:30 AM | J35: 11:00 AM | M35: Ekta Sharma | O35: 6th FEb'26 | P35: Confirmed (Done) | Q35: Not Required | R35: Theater style
A36: =IF(OR(D36<>"", F36<>"", L36<>"", O36<>""), "EVT-2026-" & TEXT(COUNTIF('DT-3 Jan26'!$A$3:$A$500, "EVT*") + COUNTIF('DT-4 Jan26'!$A$3:$A$500, "EVT*") + COUNTIF('DT-3 Feb26'!$A$3:$A$500, "EVT*") + COUNTIF(OFFSET($A$1, 1, 0, ROW()-2, 1), "EVT*") + 1, "0000"), "") -> EVT-2026-0144 | B36: 46064 | C36: Wed | D36: Innovation Hub | E36: L-1 | F36: Self Love Self Care Program | G36: 40 | H36: Small Event | I36: 01:00 PM | J36: 02:00 PM | M36: Sakshi Singh | O36: 6th feb'2026 | P36: Confirmed (Done) | Q36: Not Required
A37: =IF(OR(D37<>"", F37<>"", L37<>"", O37<>""), "EVT-2026-" & TEXT(COUNTIF('DT-3 Jan26'!$A$3:$A$500, "EVT*") + COUNTIF('DT-4 Jan26'!$A$3:$A$500, "EVT*") + COUNTIF('DT-3 Feb26'!$A$3:$A$500, "EVT*") + COUNTIF(OFFSET($A$1, 1, 0, ROW()-2, 1), "EVT*") + 1, "0000"), "") -> EVT-2026-0145 | B37: 46064 | C37: Wed | D37: Cafeteria | E37: L-5 | F37: R & R - Personal Banking | G37: 100 | H37: Big Event | I37: 10:15 AM | J37: 10:45 AM | M37: Ratinder Soni | O37: 4th Feb'26 | P37: Confirmed (Done) | Q37: Not Required | R37: Theater style
A38: =IF(OR(D38<>"", F38<>"", L38<>"", O38<>""), "EVT-2026-" & TEXT(COUNTIF('DT-3 Jan26'!$A$3:$A$500, "EVT*") + COUNTIF('DT-4 Jan26'!$A$3:$A$500, "EVT*") + COUNTIF('DT-3 Feb26'!$A$3:$A$500, "EVT*") + COUNTIF(OFFSET($A$1, 1, 0, ROW()-2, 1), "EVT*") + 1, "0000"), "") -> EVT-2026-0146 | B38: 46064 | C38: Wed | D38: Cafeteria | E38: L-5 | F38: Enterprise Data & Analytics | G38: 180 | H38: Big Event | I38: 03:00 PM | J38: 04:30 PM | M38: Ekta Sharma | O38: 6th Feb'26 | P38: Confirmed (Done) | Q38: Not Required | R38: Theater style
A39: =IF(OR(D39<>"", F39<>"", L39<>"", O39<>""), "EVT-2026-" & TEXT(COUNTIF('DT-3 Jan26'!$A$3:$A$500, "EVT*") + COUNTIF('DT-4 Jan26'!$A$3:$A$500, "EVT*") + COUNTIF('DT-3 Feb26'!$A$3:$A$500, "EVT*") + COUNTIF(OFFSET($A$1, 1, 0, ROW()-2, 1), "EVT*") + 1, "0000"), "") -> EVT-2026-0147 | B39: 46064 | C39: Wed | D39: Hackable Area | E39: L-5 | F39: Market Tech Q1 Townhall | G39: 90 | H39: Small Event | I39: 10:00 AM | J39: 11:45 AM | M39: Ekta Sharma /Taru | O39: 27th Jan'26 | P39: Confirmed (Done) | Q39: Not Required | R39: Theater style
A40: =IF(OR(D40<>"", F40<>"", L40<>"", O40<>""), "EVT-2026-" & TEXT(COUNTIF('DT-3 Jan26'!$A$3:$A$500, "EVT*") + COUNTIF('DT-4 Jan26'!$A$3:$A$500, "EVT*") + COUNTIF('DT-3 Feb26'!$A$3:$A$500, "EVT*") + COUNTIF(OFFSET($A$1, 1, 0, ROW()-2, 1), "EVT*") + 1, "0000"), "") -> EVT-2026-0148 | B40: 46064 | C40: Wed | D40: Hackable Area | E40: L-5 | F40: Ops Academy Training session part 2 - Ops Excellence (Strong return Pillar) | G40: 20 | H40: Small Event | I40: 02:00 PM | J40: 03:00 PM | M40: Martin | O40: 5th Feb'2026 | P40: Canceled | Q40: Not Required | R40: Thearter style- White board, with three different color Markers
A41: =IF(OR(D41<>"", F41<>"", L41<>"", O41<>""), "EVT-2026-" & TEXT(COUNTIF('DT-3 Jan26'!$A$3:$A$500, "EVT*") + COUNTIF('DT-4 Jan26'!$A$3:$A$500, "EVT*") + COUNTIF('DT-3 Feb26'!$A$3:$A$500, "EVT*") + COUNTIF(OFFSET($A$1, 1, 0, ROW()-2, 1), "EVT*") + 1, "0000"), "") -> EVT-2026-0149 | B41: 46065 | C41: Thu | D41: Hackable Area | E41: L-5 | F41: Innovation Hackathon | G41: 20 | H41: Small Event | I41: 01:30 PM | J41: 03:00 PM | M41: Ekta Sharma | O41: 6th Feb'2026 | P41: Confirmed (Done) | Q41: Not Required | R41: Theate style
A42: =IF(OR(D42<>"", F42<>"", L42<>"", O42<>""), "EVT-2026-" & TEXT(COUNTIF('DT-3 Jan26'!$A$3:$A$500, "EVT*") + COUNTIF('DT-4 Jan26'!$A$3:$A$500, "EVT*") + COUNTIF('DT-3 Feb26'!$A$3:$A$500, "EVT*") + COUNTIF(OFFSET($A$1, 1, 0, ROW()-2, 1), "EVT*") + 1, "0000"), "") -> EVT-2026-0150 | B42: 46065 | C42: Thu | D42: Zone E Breakout Area | E42: L-4 | F42: Codility | G42: 50 | H42: Small Event | I42: 01:30 PM | J42: 04:00 PM | M42: Parul Wadhera | O42: 46008 | P42: Confirmed (Done) | Q42: Not Required | R42: Classroom set up
A43: =IF(OR(D43<>"", F43<>"", L43<>"", O43<>""), "EVT-2026-" & TEXT(COUNTIF('DT-3 Jan26'!$A$3:$A$500, "EVT*") + COUNTIF('DT-4 Jan26'!$A$3:$A$500, "EVT*") + COUNTIF('DT-3 Feb26'!$A$3:$A$500, "EVT*") + COUNTIF(OFFSET($A$1, 1, 0, ROW()-2, 1), "EVT*") + 1, "0000"), "") -> EVT-2026-0151 | B43: 46065 | C43: Thu | D43: Innovation Hub | E43: L-1 | F43: Rewards and Recognition session- Identity Fraud Services | H43: Small Event | I43: 10:30 AM | J43: 12:30 PM | M43: Pooja Kumari | O43: 46063 | P43: Canceled | Q43: Not Required | R43: Theater style
A44: =IF(OR(D44<>"", F44<>"", L44<>"", O44<>""), "EVT-2026-" & TEXT(COUNTIF('DT-3 Jan26'!$A$3:$A$500, "EVT*") + COUNTIF('DT-4 Jan26'!$A$3:$A$500, "EVT*") + COUNTIF('DT-3 Feb26'!$A$3:$A$500, "EVT*") + COUNTIF(OFFSET($A$1, 1, 0, ROW()-2, 1), "EVT*") + 1, "0000"), "") -> EVT-2026-0152 | B44: 46065 | C44: Thu | D44: Innovation Hub | E44: L-1 | F44: Toast Master | G44: 25 | H44: Small Event | I44: 02:30 PM | J44: 04:30 PM | M44: prateek Sharma | P44: Confirmed (Done) | Q44: Not Required | R44: Theater style
A45: =IF(OR(D45<>"", F45<>"", L45<>"", O45<>""), "EVT-2026-" & TEXT(COUNTIF('DT-3 Jan26'!$A$3:$A$500, "EVT*") + COUNTIF('DT-4 Jan26'!$A$3:$A$500, "EVT*") + COUNTIF('DT-3 Feb26'!$A$3:$A$500, "EVT*") + COUNTIF(OFFSET($A$1, 1, 0, ROW()-2, 1), "EVT*") + 1, "0000"), "") -> EVT-2026-0153 | B45: 46065 | C45: Thu | D45: Hackable Sapce | E45: L-5 | F45: Sales and Marketing Global Townhall | G45: 50 | H45: Small Event | I45: 10:00 AM | J45: 11:30 AM | M45: Ekta Sharma /Vikas A | P45: Confirmed (Done) | Q45: Not Required | R45: Theater style
A46: =IF(OR(D46<>"", F46<>"", L46<>"", O46<>""), "EVT-2026-" & TEXT(COUNTIF('DT-3 Jan26'!$A$3:$A$500, "EVT*") + COUNTIF('DT-4 Jan26'!$A$3:$A$500, "EVT*") + COUNTIF('DT-3 Feb26'!$A$3:$A$500, "EVT*") + COUNTIF(OFFSET($A$1, 1, 0, ROW()-2, 1), "EVT*") + 1, "0000"), "") -> EVT-2026-0154 | B46: 46065 | C46: Thu | D46: Zone E Breakout Area | E46: L-5 | F46: DEDA Onboarding Session – | G46: 20 | H46: Small Event | I46: 03:00 PM | J46: 04:00 PM | M46: Piyush Dhayni | O46: 5th Feb'2026 | P46: Confirmed (Done) | Q46: Not Required | R46: Theater style
A47: =IF(OR(D47<>"", F47<>"", L47<>"", O47<>""), "EVT-2026-" & TEXT(COUNTIF('DT-3 Jan26'!$A$3:$A$500, "EVT*") + COUNTIF('DT-4 Jan26'!$A$3:$A$500, "EVT*") + COUNTIF('DT-3 Feb26'!$A$3:$A$500, "EVT*") + COUNTIF(OFFSET($A$1, 1, 0, ROW()-2, 1), "EVT*") + 1, "0000"), "") -> EVT-2026-0155 | B47: 46066 | C47: Fri | D47: Innovation Hub | E47: L-1 | F47: Rewards and Recognition session- Identity Fraud Services | G47: 40 | H47: Small Event | I47: 10:30 AM | J47: 12:30 PM | M47: Pooja Kumari | O47: 10th Feb'2026 | P47: Confirmed (Done) | Q47: Not Required | R47: Theater style
A48: =IF(OR(D48<>"", F48<>"", L48<>"", O48<>""), "EVT-2026-" & TEXT(COUNTIF('DT-3 Jan26'!$A$3:$A$500, "EVT*") + COUNTIF('DT-4 Jan26'!$A$3:$A$500, "EVT*") + COUNTIF('DT-3 Feb26'!$A$3:$A$500, "EVT*") + COUNTIF(OFFSET($A$1, 1, 0, ROW()-2, 1), "EVT*") + 1, "0000"), "") -> EVT-2026-0156 | B48: 46066 | C48: Fri | D48: Hackable Sapce | E48: L-5 | F48: NPL | G48: 15 | H48: Small Event | I48: 01:00 PM | J48: 01:30 PM | M48: Anurah=g Shah | P48: Confirmed (Done) | Q48: Not Required | R48: Theater Style
A49: =IF(OR(D49<>"", F49<>"", L49<>"", O49<>""), "EVT-2026-" & TEXT(COUNTIF('DT-3 Jan26'!$A$3:$A$500, "EVT*") + COUNTIF('DT-4 Jan26'!$A$3:$A$500, "EVT*") + COUNTIF('DT-3 Feb26'!$A$3:$A$500, "EVT*") + COUNTIF(OFFSET($A$1, 1, 0, ROW()-2, 1), "EVT*") + 1, "0000"), "") -> EVT-2026-0157 | B49: 46067 | C49: Sat | D49: Hiring Drive | E49: L5 | H49: Small Event | M49: Anshika | P49: Canceled | Q49: Not Required
A50: =IF(OR(D50<>"", F50<>"", L50<>"", O50<>""), "EVT-2026-" & TEXT(COUNTIF('DT-3 Jan26'!$A$3:$A$500, "EVT*") + COUNTIF('DT-4 Jan26'!$A$3:$A$500, "EVT*") + COUNTIF('DT-3 Feb26'!$A$3:$A$500, "EVT*") + COUNTIF(OFFSET($A$1, 1, 0, ROW()-2, 1), "EVT*") + 1, "0000"), "") | B50: 46068 | C50: Sun | H50: Small Event | P50: Confirmed (Done) | Q50: Not Required
A51: =IF(OR(D51<>"", F51<>"", L51<>"", O51<>""), "EVT-2026-" & TEXT(COUNTIF('DT-3 Jan26'!$A$3:$A$500, "EVT*") + COUNTIF('DT-4 Jan26'!$A$3:$A$500, "EVT*") + COUNTIF('DT-3 Feb26'!$A$3:$A$500, "EVT*") + COUNTIF(OFFSET($A$1, 1, 0, ROW()-2, 1), "EVT*") + 1, "0000"), "") -> EVT-2026-0158 | B51: 16th Feb to 17th April | C51: Mon | D51: Zone E Breakout Area | E51: L-5 | F51: Personal Banking Training | H51: Small Event | I51: 08:00 AM | J51: 05:00 PM | P51: Canceled | Q51: Not Required
A52: =IF(OR(D52<>"", F52<>"", L52<>"", O52<>""), "EVT-2026-" & TEXT(COUNTIF('DT-3 Jan26'!$A$3:$A$500, "EVT*") + COUNTIF('DT-4 Jan26'!$A$3:$A$500, "EVT*") + COUNTIF('DT-3 Feb26'!$A$3:$A$500, "EVT*") + COUNTIF(OFFSET($A$1, 1, 0, ROW()-2, 1), "EVT*") + 1, "0000"), "") -> EVT-2026-0159 | B52: 46069 | C52: Mon | D52: Innovation Hub | E52: L-1 | F52: CIBO townhall | G52: 80 | H52: Small Event | I52: 08:30 AM | J52: 10:00 AM | M52: Shikha Saxena | O52: 6th Feb'26 | P52: Confirmed (Done) | Q52: Not Required | R52: Theater style
A53: =IF(OR(D53<>"", F53<>"", L53<>"", O53<>""), "EVT-2026-" & TEXT(COUNTIF('DT-3 Jan26'!$A$3:$A$500, "EVT*") + COUNTIF('DT-4 Jan26'!$A$3:$A$500, "EVT*") + COUNTIF('DT-3 Feb26'!$A$3:$A$500, "EVT*") + COUNTIF(OFFSET($A$1, 1, 0, ROW()-2, 1), "EVT*") + 1, "0000"), "") -> EVT-2026-0160 | B53: 46069 | C53: Mon | D53: Innovation Hub | E53: L-1 | F53: TBEP get together | G53: 60 | H53: Small Event | I53: 02:30 PM | J53: 03:30 PM | M53: Abhay Dod | O53: 13th Feb'2026 | P53: Confirmed (Done) | Q53: Not Required | R53: Theate style
A54: =IF(OR(D54<>"", F54<>"", L54<>"", O54<>""), "EVT-2026-" & TEXT(COUNTIF('DT-3 Jan26'!$A$3:$A$500, "EVT*") + COUNTIF('DT-4 Jan26'!$A$3:$A$500, "EVT*") + COUNTIF('DT-3 Feb26'!$A$3:$A$500, "EVT*") + COUNTIF(OFFSET($A$1, 1, 0, ROW()-2, 1), "EVT*") + 1, "0000"), "") -> EVT-2026-0161 | B54: 46069 | C54: Mon | D54: Hacakable Space | E54: L-5 | F54: Enterprise Data & Analytics | G54: 25 | H54: Small Event | I54: 02:00 PM | J54: 03:00 PM | M54: Shashank Shekhar | P54: Confirmed (Done) | Q54: Not Required | R54: Theater style
A55: =IF(OR(D55<>"", F55<>"", L55<>"", O55<>""), "EVT-2026-" & TEXT(COUNTIF('DT-3 Jan26'!$A$3:$A$500, "EVT*") + COUNTIF('DT-4 Jan26'!$A$3:$A$500, "EVT*") + COUNTIF('DT-3 Feb26'!$A$3:$A$500, "EVT*") + COUNTIF(OFFSET($A$1, 1, 0, ROW()-2, 1), "EVT*") + 1, "0000"), "") -> EVT-2026-0162 | B55: 46070 | C55: Tue | D55: Cafeteria | E55: L-5 | F55: Testing | H55: Small Event | I55: 10:00 AM | J55: 11:00 AM | M55: Anoop Sir/Abhay Joshi | O55: 12th FEb'2026 | P55: Confirmed (Done) | Q55: Not Required | R55: no set up required
A56: =IF(OR(D56<>"", F56<>"", L56<>"", O56<>""), "EVT-2026-" & TEXT(COUNTIF('DT-3 Jan26'!$A$3:$A$500, "EVT*") + COUNTIF('DT-4 Jan26'!$A$3:$A$500, "EVT*") + COUNTIF('DT-3 Feb26'!$A$3:$A$500, "EVT*") + COUNTIF(OFFSET($A$1, 1, 0, ROW()-2, 1), "EVT*") + 1, "0000"), "") -> EVT-2026-0163 | B56: 46070 | C56: Tue | D56: Zone E Breakout Area | E56: L-4 | F56: Codility | G56: 50 | H56: Small Event | I56: 01:30 PM | J56: 04:00 PM | M56: Parul Wadhera | O56: 46008 | P56: Confirmed (Done) | Q56: Not Required | R56: Classroom set up
A57: =IF(OR(D57<>"", F57<>"", L57<>"", O57<>""), "EVT-2026-" & TEXT(COUNTIF('DT-3 Jan26'!$A$3:$A$500, "EVT*") + COUNTIF('DT-4 Jan26'!$A$3:$A$500, "EVT*") + COUNTIF('DT-3 Feb26'!$A$3:$A$500, "EVT*") + COUNTIF(OFFSET($A$1, 1, 0, ROW()-2, 1), "EVT*") + 1, "0000"), "") -> EVT-2026-0164 | B57: 46070 | C57: Tue | D57: Hacakable Space | F57: Ops Academy Training session part 2 - Ops Excellence (Strong return Pillar) | G57: 20 | H57: Small Event | I57: 03:00 PM | J57: 04:00 PM | M57: Martin | O57: 9th Feb'2026 | P57: Canceled | Q57: Not Required | R57: Theater style
A58: =IF(OR(D58<>"", F58<>"", L58<>"", O58<>""), "EVT-2026-" & TEXT(COUNTIF('DT-3 Jan26'!$A$3:$A$500, "EVT*") + COUNTIF('DT-4 Jan26'!$A$3:$A$500, "EVT*") + COUNTIF('DT-3 Feb26'!$A$3:$A$500, "EVT*") + COUNTIF(OFFSET($A$1, 1, 0, ROW()-2, 1), "EVT*") + 1, "0000"), "") -> EVT-2026-0165 | B58: 46070 | C58: Tue | D58: Innovation Hub | E58: L-1 | F58: Tech Training | G58: 35 | H58: Small Event | I58: 02:30 PM | J58: 04:00 PM | M58: Parul Wadhera | O58: 6th Feb26 | P58: Confirmed (Done) | Q58: Not Required | R58: Classroom set up
A59: =IF(OR(D59<>"", F59<>"", L59<>"", O59<>""), "EVT-2026-" & TEXT(COUNTIF('DT-3 Jan26'!$A$3:$A$500, "EVT*") + COUNTIF('DT-4 Jan26'!$A$3:$A$500, "EVT*") + COUNTIF('DT-3 Feb26'!$A$3:$A$500, "EVT*") + COUNTIF(OFFSET($A$1, 1, 0, ROW()-2, 1), "EVT*") + 1, "0000"), "") -> EVT-2026-0166 | B59: 18-feb to 20th Feb'2026 | C59: Wed | D59: MR-601 | E59: L-4 | F59: AU Visitors | G59: 1 | H59: Small Event | I59: 08:00 AM | J59: 05:00 PM | M59: Ekta Sharma | O59: 10th Feb'2026 | P59: Confirmed (Done) | Q59: Not Required | R59: Check in by 7:50 am, Water Bottles, Diet Coke & Tissue box
A60: =IF(OR(D60<>"", F60<>"", L60<>"", O60<>""), "EVT-2026-" & TEXT(COUNTIF('DT-3 Jan26'!$A$3:$A$500, "EVT*") + COUNTIF('DT-4 Jan26'!$A$3:$A$500, "EVT*") + COUNTIF('DT-3 Feb26'!$A$3:$A$500, "EVT*") + COUNTIF(OFFSET($A$1, 1, 0, ROW()-2, 1), "EVT*") + 1, "0000"), "") -> EVT-2026-0167 | B60: 46071 | C60: Wed | D60: hackable Space | E60: L-5 | F60: Group Seurity Townhall | G60: 100 | H60: Big Event | I60: 09:30 AM | J60: 11:00 AM | M60: Shikha Mittal | O60: 16th Feb '2026 | P60: Confirmed (Done) | Q60: Not Required | R60: Theater style
A61: =IF(OR(D61<>"", F61<>"", L61<>"", O61<>""), "EVT-2026-" & TEXT(COUNTIF('DT-3 Jan26'!$A$3:$A$500, "EVT*") + COUNTIF('DT-4 Jan26'!$A$3:$A$500, "EVT*") + COUNTIF('DT-3 Feb26'!$A$3:$A$500, "EVT*") + COUNTIF(OFFSET($A$1, 1, 0, ROW()-2, 1), "EVT*") + 1, "0000"), "") -> EVT-2026-0168 | B61: 46071 | C61: Wed | D61: Innovation Hub | E61: L-5 | F61: Fin Crime and Fraud Operations Townhall | G61: 100 | H61: Big Event | I61: 09:00 AM | J61: 10:00 AM | M61: Khushboo Kaur | O61: 10th Feb'2026 | P61: Confirmed (Done) | Q61: Not Required | R61: Theater set up
A62: =IF(OR(D62<>"", F62<>"", L62<>"", O62<>""), "EVT-2026-" & TEXT(COUNTIF('DT-3 Jan26'!$A$3:$A$500, "EVT*") + COUNTIF('DT-4 Jan26'!$A$3:$A$500, "EVT*") + COUNTIF('DT-3 Feb26'!$A$3:$A$500, "EVT*") + COUNTIF(OFFSET($A$1, 1, 0, ROW()-2, 1), "EVT*") + 1, "0000"), "") -> EVT-2026-0169 | B62: 46071 | C62: Wed | D62: Zone E Breakout Area | E62: L-5 | F62: Nab Assist Townhall - Q2 | G62: 60 | H62: Small Event | I62: 09:30 AM | J62: 10:30 AM | M62: Sangeeta Malik | O62: 17th Feb'2026 | P62: Confirmed (Done) | Q62: Not Required
A63: =IF(OR(D63<>"", F63<>"", L63<>"", O63<>""), "EVT-2026-" & TEXT(COUNTIF('DT-3 Jan26'!$A$3:$A$500, "EVT*") + COUNTIF('DT-4 Jan26'!$A$3:$A$500, "EVT*") + COUNTIF('DT-3 Feb26'!$A$3:$A$500, "EVT*") + COUNTIF(OFFSET($A$1, 1, 0, ROW()-2, 1), "EVT*") + 1, "0000"), "") -> EVT-2026-0170 | B63: 46071 | C63: Wed | D63: Innovation Hub | E63: L-1 | F63: All Hands Staff-Customer Function Operations | G63: 80 | H63: Small Event | I63: 10:00 AM | J63: 11:30 AM | M63: Shikha Saxena | O63: 20th Jan'26 | P63: Confirmed (Done) | Q63: Not Required | R63: Theater set up
A64: =IF(OR(D64<>"", F64<>"", L64<>"", O64<>""), "EVT-2026-" & TEXT(COUNTIF('DT-3 Jan26'!$A$3:$A$500, "EVT*") + COUNTIF('DT-4 Jan26'!$A$3:$A$500, "EVT*") + COUNTIF('DT-3 Feb26'!$A$3:$A$500, "EVT*") + COUNTIF(OFFSET($A$1, 1, 0, ROW()-2, 1), "EVT*") + 1, "0000"), "") -> EVT-2026-0171 | B64: 46071 | C64: Wed | D64: Innovation Hub | E64: L-1 | F64: Testing of India townhall | H64: Small Event | I64: 12:00 PM | J64: 02:00 PM | M64: Prena Malik | P64: Confirmed (Done) | Q64: Not Required | R64: Keep 15 extra chairs
A65: =IF(OR(D65<>"", F65<>"", L65<>"", O65<>""), "EVT-2026-" & TEXT(COUNTIF('DT-3 Jan26'!$A$3:$A$500, "EVT*") + COUNTIF('DT-4 Jan26'!$A$3:$A$500, "EVT*") + COUNTIF('DT-3 Feb26'!$A$3:$A$500, "EVT*") + COUNTIF(OFFSET($A$1, 1, 0, ROW()-2, 1), "EVT*") + 1, "0000"), "") -> EVT-2026-0172 | B65: 46072 | C65: Thu | D65: Innovation Hub | E65: L-1 | F65: all-hands meeting- Customer Function Operations | G65: 150 | H65: Big Event | I65: 10:00 AM | J65: 11:30 AM | L65: Lunch boxes placed at the big table | M65: Chetan Kumar | O65: 9th Feb'2026 | P65: Confirmed (Done) | Q65: Not Required | R65: Theater style
A66: =IF(OR(D66<>"", F66<>"", L66<>"", O66<>""), "EVT-2026-" & TEXT(COUNTIF('DT-3 Jan26'!$A$3:$A$500, "EVT*") + COUNTIF('DT-4 Jan26'!$A$3:$A$500, "EVT*") + COUNTIF('DT-3 Feb26'!$A$3:$A$500, "EVT*") + COUNTIF(OFFSET($A$1, 1, 0, ROW()-2, 1), "EVT*") + 1, "0000"), "") -> EVT-2026-0173 | B66: 46072 | C66: Thu | D66: Innovation Hub | E66: L-1 | F66: India townhall | G66: 180 | H66: Big Event | I66: 12:00 PM | J66: 04:00 PM | M66: Prerna malik | O66: 6th Jan'2026 | P66: Confirmed (Done) | Q66: Not Required | R66: Theater style
A67: =IF(OR(D67<>"", F67<>"", L67<>"", O67<>""), "EVT-2026-" & TEXT(COUNTIF('DT-3 Jan26'!$A$3:$A$500, "EVT*") + COUNTIF('DT-4 Jan26'!$A$3:$A$500, "EVT*") + COUNTIF('DT-3 Feb26'!$A$3:$A$500, "EVT*") + COUNTIF(OFFSET($A$1, 1, 0, ROW()-2, 1), "EVT*") + 1, "0000"), "") -> EVT-2026-0174 | B67: 46072 | C67: Thu | D67: Hackable space | E67: L-5 | F67: Training | G67: 30 | H67: Small Event | I67: 02:00 PM | J67: 03:00 PM | M67: Shashank Shekhar | P67: Confirmed (Done) | Q67: Not Required | R67: Theater style
A68: =IF(OR(D68<>"", F68<>"", L68<>"", O68<>""), "EVT-2026-" & TEXT(COUNTIF('DT-3 Jan26'!$A$3:$A$500, "EVT*") + COUNTIF('DT-4 Jan26'!$A$3:$A$500, "EVT*") + COUNTIF('DT-3 Feb26'!$A$3:$A$500, "EVT*") + COUNTIF(OFFSET($A$1, 1, 0, ROW()-2, 1), "EVT*") + 1, "0000"), "") -> EVT-2026-0175 | B68: 46072 | C68: Thu | D68: Zone E Breakout Area | E68: L-4 | H68: Small Event | P68: Confirmed (Done) | Q68: Not Required
A69: =IF(OR(D69<>"", F69<>"", L69<>"", O69<>""), "EVT-2026-" & TEXT(COUNTIF('DT-3 Jan26'!$A$3:$A$500, "EVT*") + COUNTIF('DT-4 Jan26'!$A$3:$A$500, "EVT*") + COUNTIF('DT-3 Feb26'!$A$3:$A$500, "EVT*") + COUNTIF(OFFSET($A$1, 1, 0, ROW()-2, 1), "EVT*") + 1, "0000"), "") -> EVT-2026-0176 | B69: 46072 | C69: Thu | D69: Zone E Breakout Area | E69: L-4 | F69: Codility | G69: 50 | H69: Small Event | I69: 01:30 PM | J69: 04:00 PM | M69: Parul Wadhera | O69: 46008 | P69: Confirmed (Done) | Q69: Not Required | R69: Classroom set up
A70: =IF(OR(D70<>"", F70<>"", L70<>"", O70<>""), "EVT-2026-" & TEXT(COUNTIF('DT-3 Jan26'!$A$3:$A$500, "EVT*") + COUNTIF('DT-4 Jan26'!$A$3:$A$500, "EVT*") + COUNTIF('DT-3 Feb26'!$A$3:$A$500, "EVT*") + COUNTIF(OFFSET($A$1, 1, 0, ROW()-2, 1), "EVT*") + 1, "0000"), "") -> EVT-2026-0177 | B70: 46072 | C70: Thu | D70: Hacakable Space | E70: L-5 | F70: Ops Onboarding | G70: 60 | H70: Small Event | I70: 11:00 AM | J70: 12:00 PM | M70: Shikha Saxena | O70: 18th Feb | P70: Confirmed (Done) | Q70: Not Required | R70: Semi Circle
A71: =IF(OR(D71<>"", F71<>"", L71<>"", O71<>""), "EVT-2026-" & TEXT(COUNTIF('DT-3 Jan26'!$A$3:$A$500, "EVT*") + COUNTIF('DT-4 Jan26'!$A$3:$A$500, "EVT*") + COUNTIF('DT-3 Feb26'!$A$3:$A$500, "EVT*") + COUNTIF(OFFSET($A$1, 1, 0, ROW()-2, 1), "EVT*") + 1, "0000"), "") -> EVT-2026-0178 | B71: 46073 | C71: Fri | D71: Cafeteria | E71: L-5 | F71: Baithak, Samvaad Aur Badlav | G71: 100 | H71: Big Event | I71: 03:00 PM | J71: 05:00 PM | M71: Pratul Singh | O71: 6th FEb'26 | P71: Canceled | Q71: Not Required | R71: Theater style
A72: =IF(OR(D72<>"", F72<>"", L72<>"", O72<>""), "EVT-2026-" & TEXT(COUNTIF('DT-3 Jan26'!$A$3:$A$500, "EVT*") + COUNTIF('DT-4 Jan26'!$A$3:$A$500, "EVT*") + COUNTIF('DT-3 Feb26'!$A$3:$A$500, "EVT*") + COUNTIF(OFFSET($A$1, 1, 0, ROW()-2, 1), "EVT*") + 1, "0000"), "") -> EVT-2026-0179 | B72: 46073 | C72: Fri | D72: Innovation Hub | E72: L-1 | F72: Group Seurity | G72: 110 | H72: Big Event | I72: 10:00 AM | J72: 11:30 AM | M72: Shikha Mittal | O72: 11th Feb'2026 | P72: Canceled | Q72: Not Required | R72: Theater style
A73: =IF(OR(D73<>"", F73<>"", L73<>"", O73<>""), "EVT-2026-" & TEXT(COUNTIF('DT-3 Jan26'!$A$3:$A$500, "EVT*") + COUNTIF('DT-4 Jan26'!$A$3:$A$500, "EVT*") + COUNTIF('DT-3 Feb26'!$A$3:$A$500, "EVT*") + COUNTIF(OFFSET($A$1, 1, 0, ROW()-2, 1), "EVT*") + 1, "0000"), "") -> EVT-2026-0180 | B73: 46073 | C73: Fri | D73: Innovation Hub | E73: L-1 | F73: Tech Training | G73: 35 | H73: Small Event | I73: 02:30 PM | J73: 04:00 PM | M73: Parul Wadhera | O73: 6th Feb26 | P73: Confirmed (Done) | Q73: Not Required | R73: Theater style
A74: =IF(OR(D74<>"", F74<>"", L74<>"", O74<>""), "EVT-2026-" & TEXT(COUNTIF('DT-3 Jan26'!$A$3:$A$500, "EVT*") + COUNTIF('DT-4 Jan26'!$A$3:$A$500, "EVT*") + COUNTIF('DT-3 Feb26'!$A$3:$A$500, "EVT*") + COUNTIF(OFFSET($A$1, 1, 0, ROW()-2, 1), "EVT*") + 1, "0000"), "") -> EVT-2026-0181 | B74: 46074 | C74: Sat | D74: Hiring Drive | E74: L-5 | H74: Small Event | M74: Anshika Singh | P74: Confirmed (Done) | Q74: Not Required | R74: Details will be shared shortly
A75: =IF(OR(D75<>"", F75<>"", L75<>"", O75<>""), "EVT-2026-" & TEXT(COUNTIF('DT-3 Jan26'!$A$3:$A$500, "EVT*") + COUNTIF('DT-4 Jan26'!$A$3:$A$500, "EVT*") + COUNTIF('DT-3 Feb26'!$A$3:$A$500, "EVT*") + COUNTIF(OFFSET($A$1, 1, 0, ROW()-2, 1), "EVT*") + 1, "0000"), "") | B75: 46075 | C75: Sun | H75: Small Event | P75: Confirmed (Done) | Q75: Not Required
A76: =IF(OR(D76<>"", F76<>"", L76<>"", O76<>""), "EVT-2026-" & TEXT(COUNTIF('DT-3 Jan26'!$A$3:$A$500, "EVT*") + COUNTIF('DT-4 Jan26'!$A$3:$A$500, "EVT*") + COUNTIF('DT-3 Feb26'!$A$3:$A$500, "EVT*") + COUNTIF(OFFSET($A$1, 1, 0, ROW()-2, 1), "EVT*") + 1, "0000"), "") -> EVT-2026-0182 | B76: 23/02/2026 to 26th Feb | C76: Mon | D76: 1.F603 (10P) | E76: L-1 | F76: AU Visitors | G76: 1 | H76: Small Event | I76: 07:00 AM | J76: 05:00 PM | M76: Kriti Kapoor | O76: 9th Feb'2026 | P76: Confirmed (Done) | Q76: Not Required | R76: Check in by 7:20 am - Water bottles, coke Sanitizer white board markers and tissue box - make a folder of pentonic pen, conferenne pad, higlighter, pencil, eraser and sharpner with sticky noted, Mentos Candies and keep this folder on monday and rest check the markers in the meeting room and also check the temperature
A77: =IF(OR(D77<>"", F77<>"", L77<>"", O77<>""), "EVT-2026-" & TEXT(COUNTIF('DT-3 Jan26'!$A$3:$A$500, "EVT*") + COUNTIF('DT-4 Jan26'!$A$3:$A$500, "EVT*") + COUNTIF('DT-3 Feb26'!$A$3:$A$500, "EVT*") + COUNTIF(OFFSET($A$1, 1, 0, ROW()-2, 1), "EVT*") + 1, "0000"), "") -> EVT-2026-0183 | B77: 46076 | C77: Mon | D77: Innovation Hub | E77: L-1 | F77: Tech Onboarding - | G77: 30 | H77: Small Event | I77: 02:00 PM | J77: 05:00 PM | L77: No | M77: Soamya | O77: 46008 | P77: Confirmed (Done) | Q77: Not Required | R77: Theater style
A78: =IF(OR(D78<>"", F78<>"", L78<>"", O78<>""), "EVT-2026-" & TEXT(COUNTIF('DT-3 Jan26'!$A$3:$A$500, "EVT*") + COUNTIF('DT-4 Jan26'!$A$3:$A$500, "EVT*") + COUNTIF('DT-3 Feb26'!$A$3:$A$500, "EVT*") + COUNTIF(OFFSET($A$1, 1, 0, ROW()-2, 1), "EVT*") + 1, "0000"), "") -> EVT-2026-0184 | B78: 46076 | C78: Mon | D78: Zone C Breakout area | E78: L-5 | F78: Pot Luck Lunch | G78: 35 | H78: Small Event | I78: 12:00 PM | J78: 01:00 PM | L78: No | M78: Ratri Bhattacharya | O78: 20th feb 2026 | P78: Confirmed (Done) | Q78: Not Required | R78: place the tables, cutlery and few cluster set up
A79: =IF(OR(D79<>"", F79<>"", L79<>"", O79<>""), "EVT-2026-" & TEXT(COUNTIF('DT-3 Jan26'!$A$3:$A$500, "EVT*") + COUNTIF('DT-4 Jan26'!$A$3:$A$500, "EVT*") + COUNTIF('DT-3 Feb26'!$A$3:$A$500, "EVT*") + COUNTIF(OFFSET($A$1, 1, 0, ROW()-2, 1), "EVT*") + 1, "0000"), "") -> EVT-2026-0185 | B79: 46076 | C79: Mon | D79: Zone E Breakout Area | E79: L-5 | F79: Training | G79: 25 | H79: Small Event | I79: 02:00 PM | J79: 03:00 PM | L79: NO | M79: Shashank Shekhar | P79: Confirmed (Done) | Q79: Not Required | R79: Theater style
A80: =IF(OR(D80<>"", F80<>"", L80<>"", O80<>""), "EVT-2026-" & TEXT(COUNTIF('DT-3 Jan26'!$A$3:$A$500, "EVT*") + COUNTIF('DT-4 Jan26'!$A$3:$A$500, "EVT*") + COUNTIF('DT-3 Feb26'!$A$3:$A$500, "EVT*") + COUNTIF(OFFSET($A$1, 1, 0, ROW()-2, 1), "EVT*") + 1, "0000"), "") -> EVT-2026-0186 | B80: 46076 | C80: Mon | D80: Receration Area | E80: L-5 | F80: Fin Crime & Fraud Operations. | G80: 35 | H80: Small Event | I80: 03:30 PM | J80: 04:30 PM | M80: Ratri Bhattacharya | O80: 9th Feb'2026 | P80: Confirmed (Done) | Q80: Not Required | R80: no set up requried- they will use the space for the games
A81: =IF(OR(D81<>"", F81<>"", L81<>"", O81<>""), "EVT-2026-" & TEXT(COUNTIF('DT-3 Jan26'!$A$3:$A$500, "EVT*") + COUNTIF('DT-4 Jan26'!$A$3:$A$500, "EVT*") + COUNTIF('DT-3 Feb26'!$A$3:$A$500, "EVT*") + COUNTIF(OFFSET($A$1, 1, 0, ROW()-2, 1), "EVT*") + 1, "0000"), "") -> EVT-2026-0187 | B81: 46076 | C81: Mon | D81: Zone E Breakout Area | E81: L-5 | F81: Payment Operations - Engagement Activity | G81: 65 | H81: Small Event | I81: 12:00 PM | J81: 01:00 PM | M81: Ritika Singhal | O81: 20th Feb'2026 | P81: Confirmed (Done) | Q81: Not Required | R81: Theater style
A82: =IF(OR(D82<>"", F82<>"", L82<>"", O82<>""), "EVT-2026-" & TEXT(COUNTIF('DT-3 Jan26'!$A$3:$A$500, "EVT*") + COUNTIF('DT-4 Jan26'!$A$3:$A$500, "EVT*") + COUNTIF('DT-3 Feb26'!$A$3:$A$500, "EVT*") + COUNTIF(OFFSET($A$1, 1, 0, ROW()-2, 1), "EVT*") + 1, "0000"), "") -> EVT-2026-0188 | B82: 46076 | C82: Mon | D82: Hacable Area | E82: L-5 | F82: Executive Meeting- DATA Technology | G82: 30 | H82: Small Event | I82: 11:00 AM | J82: 12:00 PM | M82: Nidhi Garg | O82: 20th Feb'2026 | P82: Confirmed (Done) | Q82: Not Required | R82: Theater style
A83: =IF(OR(D83<>"", F83<>"", L83<>"", O83<>""), "EVT-2026-" & TEXT(COUNTIF('DT-3 Jan26'!$A$3:$A$500, "EVT*") + COUNTIF('DT-4 Jan26'!$A$3:$A$500, "EVT*") + COUNTIF('DT-3 Feb26'!$A$3:$A$500, "EVT*") + COUNTIF(OFFSET($A$1, 1, 0, ROW()-2, 1), "EVT*") + 1, "0000"), "") -> EVT-2026-0189 | B83: 46076 | C83: Mon | D83: Hackabale Space | E83: L-5 | F83: Ada Ingestion RTE, Enterprise Data & Analytics | G83: 100 | H83: Big Event | I83: 02:30 PM | J83: 03:30 PM | M83: Shashank Shekhar | O83: 18th Feb | P83: Confirmed (Done) | Q83: Not Required | R83: Theater style
A84: =IF(OR(D84<>"", F84<>"", L84<>"", O84<>""), "EVT-2026-" & TEXT(COUNTIF('DT-3 Jan26'!$A$3:$A$500, "EVT*") + COUNTIF('DT-4 Jan26'!$A$3:$A$500, "EVT*") + COUNTIF('DT-3 Feb26'!$A$3:$A$500, "EVT*") + COUNTIF(OFFSET($A$1, 1, 0, ROW()-2, 1), "EVT*") + 1, "0000"), "") -> EVT-2026-0190 | B84: 23rd feb to 3rd March'2026 (except 27th Feb) | C84: Mon | D84: MR-506 | E84: L-1 | F84: Training | G84: 20 pax | H84: Small Event | I84: 01:30 PM | J84: 05:00 PM | M84: Adeetee Jain | O84: 10th Feb'2026 | P84: Confirmed (Done) | Q84: Not Required | R84: Classroom set up and requrie the power extension
A85: =IF(OR(D85<>"", F85<>"", L85<>"", O85<>""), "EVT-2026-" & TEXT(COUNTIF('DT-3 Jan26'!$A$3:$A$500, "EVT*") + COUNTIF('DT-4 Jan26'!$A$3:$A$500, "EVT*") + COUNTIF('DT-3 Feb26'!$A$3:$A$500, "EVT*") + COUNTIF(OFFSET($A$1, 1, 0, ROW()-2, 1), "EVT*") + 1, "0000"), "") -> EVT-2026-0191 | B85: 23rd Feb | C85: Mon | D85: Innovation Hub | E85: L-1 | F85: NCC Inaugration Ceremony | G85: 60 | H85: Small Event | I85: 09:30 AM | J85: 10:30 AM | M85: Kriti Kapoor | O85: Cookies (3 differnt type of cookies) displayed in the big table and tea also (Tea from Pihu Foods) arrange the normal knife for cake cutting and place the round tables for placing the cakes | P85: Confirmed (Done) | Q85: Not Required | R85: * Cookies will be arranged, tea arranged (70 pax)- ribbon cutting by 9:30 am
A86: =IF(OR(D86<>"", F86<>"", L86<>"", O86<>""), "EVT-2026-" & TEXT(COUNTIF('DT-3 Jan26'!$A$3:$A$500, "EVT*") + COUNTIF('DT-4 Jan26'!$A$3:$A$500, "EVT*") + COUNTIF('DT-3 Feb26'!$A$3:$A$500, "EVT*") + COUNTIF(OFFSET($A$1, 1, 0, ROW()-2, 1), "EVT*") + 1, "0000"), "") -> EVT-2026-0192 | B86: 23rd Feb | C86: Mon | D86: Innovation Hub | E86: L-1 | F86: Technology Showcase | H86: Small Event | I86: 10:30 AM | J86: 11:30 AM | M86: Kriti Kapoor | P86: Canceled | Q86: Not Required | R86: 7Tables to be placed, like booth- i will discus with you how to place the tables and chairs
A87: =IF(OR(D87<>"", F87<>"", L87<>"", O87<>""), "EVT-2026-" & TEXT(COUNTIF('DT-3 Jan26'!$A$3:$A$500, "EVT*") + COUNTIF('DT-4 Jan26'!$A$3:$A$500, "EVT*") + COUNTIF('DT-3 Feb26'!$A$3:$A$500, "EVT*") + COUNTIF(OFFSET($A$1, 1, 0, ROW()-2, 1), "EVT*") + 1, "0000"), "") -> EVT-2026-0193 | B87: 23rd Feb'2026 to 27th Feb | C87: Mon to Fri | D87: MR-302 | E87: L-4 | F87: AU Visitors | G87: 1 | H87: Small Event | I87: 08:00 AM | J87: 05:00 PM | M87: Ekta Sharma | O87: 10th Feb'2026 | P87: Confirmed (Done) | Q87: Not Required | R87: Water Bottles, Diet Coke & Tissue box
A88: =IF(OR(D88<>"", F88<>"", L88<>"", O88<>""), "EVT-2026-" & TEXT(COUNTIF('DT-3 Jan26'!$A$3:$A$500, "EVT*") + COUNTIF('DT-4 Jan26'!$A$3:$A$500, "EVT*") + COUNTIF('DT-3 Feb26'!$A$3:$A$500, "EVT*") + COUNTIF(OFFSET($A$1, 1, 0, ROW()-2, 1), "EVT*") + 1, "0000"), "") -> EVT-2026-0194 | B88: 23rd Feb'2026 to 27th Feb | C88: Mon to Fri | D88: MR-304 | E88: L-4 | F88: AU Visitors | G88: 1 | H88: Small Event | I88: 08:00 AM | J88: 05:00 PM | M88: Ekta Sharma | O88: 10th Feb'2026 | P88: Confirmed (Done) | Q88: Not Required | R88: Water Bottles, Diet Coke & Tissue box
A89: =IF(OR(D89<>"", F89<>"", L89<>"", O89<>""), "EVT-2026-" & TEXT(COUNTIF('DT-3 Jan26'!$A$3:$A$500, "EVT*") + COUNTIF('DT-4 Jan26'!$A$3:$A$500, "EVT*") + COUNTIF('DT-3 Feb26'!$A$3:$A$500, "EVT*") + COUNTIF(OFFSET($A$1, 1, 0, ROW()-2, 1), "EVT*") + 1, "0000"), "") -> EVT-2026-0195 | B89: 23/02/2026 to 26th Feb | C89: Mon | D89: 1.D403 (4P) | E89: L-1 | F89: AU Visitors | G89: 1 | H89: Small Event | I89: 07:00 AM | J89: 05:00 PM | M89: Kriti Kapoor | O89: 9th Feb'2026 | P89: Canceled | Q89: Not Required | R89: Water bottles, Conference Pad, Mentos Candies, Coke Pentnoic Pen, white board markers and tissue box
A90: =IF(OR(D90<>"", F90<>"", L90<>"", O90<>""), "EVT-2026-" & TEXT(COUNTIF('DT-3 Jan26'!$A$3:$A$500, "EVT*") + COUNTIF('DT-4 Jan26'!$A$3:$A$500, "EVT*") + COUNTIF('DT-3 Feb26'!$A$3:$A$500, "EVT*") + COUNTIF(OFFSET($A$1, 1, 0, ROW()-2, 1), "EVT*") + 1, "0000"), "") -> EVT-2026-0196 | B90: 46077 | C90: Tue | D90: 1.D403 (4P) | E90: L-1 | F90: AU Visitors | G90: 1 | H90: Small Event | I90: 08:00 AM | J90: 05:00 PM | M90: Kriti Kapoor | O90: 9th Feb'2026 | P90: Confirmed (Done) | Q90: Not Required | R90: Water bottles, Diary, Pen, white board markers and tissue box _ PLEASE CHECK ALL THE ITEMS SHOULD BE PLACED AND RECHECKED THE WHITE BOARD MARKERS
A91: =IF(OR(D91<>"", F91<>"", L91<>"", O91<>""), "EVT-2026-" & TEXT(COUNTIF('DT-3 Jan26'!$A$3:$A$500, "EVT*") + COUNTIF('DT-4 Jan26'!$A$3:$A$500, "EVT*") + COUNTIF('DT-3 Feb26'!$A$3:$A$500, "EVT*") + COUNTIF(OFFSET($A$1, 1, 0, ROW()-2, 1), "EVT*") + 1, "0000"), "") -> EVT-2026-0197 | B91: 46077 | C91: Tue | D91: DT4 – 5.D.410 | E91: L-5 | F91: AU Visitors | G91: 1 | H91: Small Event | I91: 08:00 AM | J91: 05:00 PM | M91: Shikha Saxena | O91: 10th Feb'2026 | P91: Confirmed (Done) | Q91: Not Required | R91: Check in by 7:50 am, Water bottles, tissue box, sanitizer and put offline signage room
A92: =IF(OR(D92<>"", F92<>"", L92<>"", O92<>""), "EVT-2026-" & TEXT(COUNTIF('DT-3 Jan26'!$A$3:$A$500, "EVT*") + COUNTIF('DT-4 Jan26'!$A$3:$A$500, "EVT*") + COUNTIF('DT-3 Feb26'!$A$3:$A$500, "EVT*") + COUNTIF(OFFSET($A$1, 1, 0, ROW()-2, 1), "EVT*") + 1, "0000"), "") -> EVT-2026-0198 | B92: 46077 | C92: Tue | D92: Hackable space | E92: L-5 | F92: Ops Academy Training session part 2 - Ops Excellence (Strong return Pillar) | G92: 20 | H92: Small Event | I92: 03:00 PM | J92: 04:00 PM | M92: Martin | O92: 9th Feb'2026 | P92: Confirmed (Done) | Q92: Not Required | R92: Theater style- require white board with White Board Marker
A93: =IF(OR(D93<>"", F93<>"", L93<>"", O93<>""), "EVT-2026-" & TEXT(COUNTIF('DT-3 Jan26'!$A$3:$A$500, "EVT*") + COUNTIF('DT-4 Jan26'!$A$3:$A$500, "EVT*") + COUNTIF('DT-3 Feb26'!$A$3:$A$500, "EVT*") + COUNTIF(OFFSET($A$1, 1, 0, ROW()-2, 1), "EVT*") + 1, "0000"), "") -> EVT-2026-0199 | B93: 46077 | C93: Tue | D93: Receration Area | E93: L-5 | F93: Fin Crime & Fraud Operations. | G93: 35 | H93: Small Event | I93: 03:30 PM | J93: 04:30 PM | M93: Ratri Bhattacharya | O93: 9th Feb'2026 | P93: Confirmed (Done) | Q93: Not Required | R93: no set up requried- they will use the space for the games
A94: =IF(OR(D94<>"", F94<>"", L94<>"", O94<>""), "EVT-2026-" & TEXT(COUNTIF('DT-3 Jan26'!$A$3:$A$500, "EVT*") + COUNTIF('DT-4 Jan26'!$A$3:$A$500, "EVT*") + COUNTIF('DT-3 Feb26'!$A$3:$A$500, "EVT*") + COUNTIF(OFFSET($A$1, 1, 0, ROW()-2, 1), "EVT*") + 1, "0000"), "") -> EVT-2026-0200 | B94: 46077 | C94: Tue | D94: 1.F603 (10P) | E94: L-1 | F94: AU Visitors | G94: 1 | H94: Small Event | I94: 08:00 AM | J94: 05:00 PM | M94: Kriti Kapoor | O94: 9th Feb'2026 | P94: Confirmed (Done) | Q94: Not Required | R94: Water bottles, and tissue box
A95: =IF(OR(D95<>"", F95<>"", L95<>"", O95<>""), "EVT-2026-" & TEXT(COUNTIF('DT-3 Jan26'!$A$3:$A$500, "EVT*") + COUNTIF('DT-4 Jan26'!$A$3:$A$500, "EVT*") + COUNTIF('DT-3 Feb26'!$A$3:$A$500, "EVT*") + COUNTIF(OFFSET($A$1, 1, 0, ROW()-2, 1), "EVT*") + 1, "0000"), "") -> EVT-2026-0201 | B95: 46077 | C95: Tue | D95: Innovation Hub | E95: L-1 | F95: Steve’s townhall | G95: 150 | H95: Big Event | I95: 11:30 AM | J95: 01:15 PM | M95: Kriti Kapoor | O95: 9th Feb'2026 | P95: Confirmed (Done) | Q95: Not Required | R95: plates, cutlery, Tissue box and water bottles for the speakers - Kriti will check with Parul
A96: =IF(OR(D96<>"", F96<>"", L96<>"", O96<>""), "EVT-2026-" & TEXT(COUNTIF('DT-3 Jan26'!$A$3:$A$500, "EVT*") + COUNTIF('DT-4 Jan26'!$A$3:$A$500, "EVT*") + COUNTIF('DT-3 Feb26'!$A$3:$A$500, "EVT*") + COUNTIF(OFFSET($A$1, 1, 0, ROW()-2, 1), "EVT*") + 1, "0000"), "") -> EVT-2026-0202 | B96: 46077 | C96: Tue | D96: Receration Area | E96: L-5 | F96: Fin Crime & Fraud Operations. | H96: Small Event | I96: 03:30 PM | J96: 04:30 PM | M96: Ratri Bhattacharya | O96: 9th Feb'2026 | P96: Confirmed (Done) | Q96: Not Required | R96: no set up requried- they will use the space for the games
A97: =IF(OR(D97<>"", F97<>"", L97<>"", O97<>""), "EVT-2026-" & TEXT(COUNTIF('DT-3 Jan26'!$A$3:$A$500, "EVT*") + COUNTIF('DT-4 Jan26'!$A$3:$A$500, "EVT*") + COUNTIF('DT-3 Feb26'!$A$3:$A$500, "EVT*") + COUNTIF(OFFSET($A$1, 1, 0, ROW()-2, 1), "EVT*") + 1, "0000"), "") -> EVT-2026-0203 | B97: 46077 | C97: Tue | D97: Innovation Hub | E97: L-1 | F97: Tech Training | G97: 35 | H97: Small Event | I97: 02:30 PM | J97: 04:00 PM | M97: Parul Wadhera | O97: 6th Feb26 | P97: Confirmed (Done) | Q97: Not Required | R97: Theater style
A98: =IF(OR(D98<>"", F98<>"", L98<>"", O98<>""), "EVT-2026-" & TEXT(COUNTIF('DT-3 Jan26'!$A$3:$A$500, "EVT*") + COUNTIF('DT-4 Jan26'!$A$3:$A$500, "EVT*") + COUNTIF('DT-3 Feb26'!$A$3:$A$500, "EVT*") + COUNTIF(OFFSET($A$1, 1, 0, ROW()-2, 1), "EVT*") + 1, "0000"), "") -> EVT-2026-0204 | B98: 46077 | C98: Tue | D98: Zone E Breakout Area | E98: L-4 | F98: Tech Onboarding - | G98: 30 | H98: Small Event | I98: 02:00 PM | J98: 05:00 PM | L98: No | M98: Soamya | O98: 46008 | P98: Confirmed (Done) | Q98: Not Required | R98: Theater style
A99: =IF(OR(D99<>"", F99<>"", L99<>"", O99<>""), "EVT-2026-" & TEXT(COUNTIF('DT-3 Jan26'!$A$3:$A$500, "EVT*") + COUNTIF('DT-4 Jan26'!$A$3:$A$500, "EVT*") + COUNTIF('DT-3 Feb26'!$A$3:$A$500, "EVT*") + COUNTIF(OFFSET($A$1, 1, 0, ROW()-2, 1), "EVT*") + 1, "0000"), "") -> EVT-2026-0205 | B99: 46078 | C99: Wed | D99: DT4 – 5.D.410 | E99: L-5 | F99: AU Visitors | G99: 1 | H99: Small Event | I99: 08:00 AM | J99: 05:00 PM | M99: Shikha Saxena | O99: 10th Feb'2026 | P99: Confirmed (Done) | Q99: Not Required | R99: Check in by 7:50 am, Water bottles, tissue box, sanitizer and put offline signage room
A100: =IF(OR(D100<>"", F100<>"", L100<>"", O100<>""), "EVT-2026-" & TEXT(COUNTIF('DT-3 Jan26'!$A$3:$A$500, "EVT*") + COUNTIF('DT-4 Jan26'!$A$3:$A$500, "EVT*") + COUNTIF('DT-3 Feb26'!$A$3:$A$500, "EVT*") + COUNTIF(OFFSET($A$1, 1, 0, ROW()-2, 1), "EVT*") + 1, "0000"), "") -> EVT-2026-0206 | B100: 46078 | C100: Wed | D100: Innovation Hub | E100: L-1 | F100: Tech Onboarding - | G100: 30 | H100: Small Event | I100: 02:00 PM | J100: 05:00 PM | L100: No | M100: Soamya | O100: 46008 | P100: Confirmed (Done) | Q100: Not Required | R100: Theater style
...

Sheet DT-3 Mar26
A1: 🏠 ⮌ RETURN TO DASHBOARD | D1: DOWNTOWN-3 EVENT OPERATIONS TRACKER • MAR26 | N1: 🟢 Green: Confirmed | 🟡 Yellow: Pending | 🔴 Red: Canceled
A2: Event ID | B2: Event Date | C2: Day | D2: Location | E2: Event Type / Title | F2: Capacity | G2: Event Scale | H2: Event Start Time | I2: Event End Time | J2: F& B | K2: Logistic Support | L2: Booked By | M2: Requester Email | N2: Booking Date | O2: Status | P2: Feedback Form | Q2: Remarks | R2: Booking Taken By
A3: =IF(OR(D3<>"", E3<>"", K3<>"", N3<>""), "EVT-2026-" & TEXT(COUNTIF('DT-3 Jan26'!$A$3:$A$500, "EVT*") + COUNTIF('DT-4 Jan26'!$A$3:$A$500, "EVT*") + COUNTIF('DT-3 Feb26'!$A$3:$A$500, "EVT*") + COUNTIF('DT-4 Feb26'!$A$3:$A$500, "EVT*") + COUNTIF(OFFSET($A$1, 1, 0, ROW()-2, 1), "EVT*") + 1, "0000"), "") | B3: 46082 | C3: Sun | G3: Small Event | O3: Confirmed (Done) | P3: Not Required
A4: =IF(OR(D4<>"", E4<>"", K4<>"", N4<>""), "EVT-2026-" & TEXT(COUNTIF('DT-3 Jan26'!$A$3:$A$500, "EVT*") + COUNTIF('DT-4 Jan26'!$A$3:$A$500, "EVT*") + COUNTIF('DT-3 Feb26'!$A$3:$A$500, "EVT*") + COUNTIF('DT-4 Feb26'!$A$3:$A$500, "EVT*") + COUNTIF(OFFSET($A$1, 1, 0, ROW()-2, 1), "EVT*") + 1, "0000"), "") | B4: 46083 | C4: Mon | G4: Small Event | O4: Confirmed (Done) | P4: Not Required
A5: =IF(OR(D5<>"", E5<>"", K5<>"", N5<>""), "EVT-2026-" & TEXT(COUNTIF('DT-3 Jan26'!$A$3:$A$500, "EVT*") + COUNTIF('DT-4 Jan26'!$A$3:$A$500, "EVT*") + COUNTIF('DT-3 Feb26'!$A$3:$A$500, "EVT*") + COUNTIF('DT-4 Feb26'!$A$3:$A$500, "EVT*") + COUNTIF(OFFSET($A$1, 1, 0, ROW()-2, 1), "EVT*") + 1, "0000"), "") | B5: 46083 | C5: Mon | G5: Small Event | O5: Confirmed (Done) | P5: Not Required
A6: =IF(OR(D6<>"", E6<>"", K6<>"", N6<>""), "EVT-2026-" & TEXT(COUNTIF('DT-3 Jan26'!$A$3:$A$500, "EVT*") + COUNTIF('DT-4 Jan26'!$A$3:$A$500, "EVT*") + COUNTIF('DT-3 Feb26'!$A$3:$A$500, "EVT*") + COUNTIF('DT-4 Feb26'!$A$3:$A$500, "EVT*") + COUNTIF(OFFSET($A$1, 1, 0, ROW()-2, 1), "EVT*") + 1, "0000"), "") | B6: 46085 | C6: Wed | G6: Small Event | O6: Confirmed (Done) | P6: Not Required
A7: =IF(OR(D7<>"", E7<>"", K7<>"", N7<>""), "EVT-2026-" & TEXT(COUNTIF('DT-3 Jan26'!$A$3:$A$500, "EVT*") + COUNTIF('DT-4 Jan26'!$A$3:$A$500, "EVT*") + COUNTIF('DT-3 Feb26'!$A$3:$A$500, "EVT*") + COUNTIF('DT-4 Feb26'!$A$3:$A$500, "EVT*") + COUNTIF(OFFSET($A$1, 1, 0, ROW()-2, 1), "EVT*") + 1, "0000"), "") -> EVT-2026-0227 | B7: 46086 | C7: Thu | D7: Breakout area+Cafeteria | E7: TV Screens Testing | G7: Small Event | H7: 08:00 AM | I7: 05:00 PM | L7: Sahil Kumar | N7: 2nd Mar | O7: Confirmed (Done) | P7: Not Required | Q7: No set up required - Testing
A8: =IF(OR(D8<>"", E8<>"", K8<>"", N8<>""), "EVT-2026-" & TEXT(COUNTIF('DT-3 Jan26'!$A$3:$A$500, "EVT*") + COUNTIF('DT-4 Jan26'!$A$3:$A$500, "EVT*") + COUNTIF('DT-3 Feb26'!$A$3:$A$500, "EVT*") + COUNTIF('DT-4 Feb26'!$A$3:$A$500, "EVT*") + COUNTIF(OFFSET($A$1, 1, 0, ROW()-2, 1), "EVT*") + 1, "0000"), "") -> EVT-2026-0228 | B8: 46087 | C8: Fri | D8: Breakout area+Cafeteria | E8: TV Screens Testing | G8: Small Event | H8: 08:00 AM | I8: 05:00 PM | L8: Sahil Kumar | N8: 2nd Mar | O8: Confirmed (Done) | P8: Not Required | Q8: No set up required - Testing
A9: =IF(OR(D9<>"", E9<>"", K9<>"", N9<>""), "EVT-2026-" & TEXT(COUNTIF('DT-3 Jan26'!$A$3:$A$500, "EVT*") + COUNTIF('DT-4 Jan26'!$A$3:$A$500, "EVT*") + COUNTIF('DT-3 Feb26'!$A$3:$A$500, "EVT*") + COUNTIF('DT-4 Feb26'!$A$3:$A$500, "EVT*") + COUNTIF(OFFSET($A$1, 1, 0, ROW()-2, 1), "EVT*") + 1, "0000"), "") -> EVT-2026-0229 | B9: 46088 | C9: Sat | D9: Hiring Drive | F9: 100+ | G9: Big Event | H9: 08:00 AM | I9: 05:00 PM | L9: Anshika | O9: Confirmed (Done) | P9: Not Required | Q9: Details shared with team
A10: =IF(OR(D10<>"", E10<>"", K10<>"", N10<>""), "EVT-2026-" & TEXT(COUNTIF('DT-3 Jan26'!$A$3:$A$500, "EVT*") + COUNTIF('DT-4 Jan26'!$A$3:$A$500, "EVT*") + COUNTIF('DT-3 Feb26'!$A$3:$A$500, "EVT*") + COUNTIF('DT-4 Feb26'!$A$3:$A$500, "EVT*") + COUNTIF(OFFSET($A$1, 1, 0, ROW()-2, 1), "EVT*") + 1, "0000"), "") | B10: 46089 | C10: Sun | G10: Small Event | O10: Confirmed (Done) | P10: Not Required
A11: =IF(OR(D11<>"", E11<>"", K11<>"", N11<>""), "EVT-2026-" & TEXT(COUNTIF('DT-3 Jan26'!$A$3:$A$500, "EVT*") + COUNTIF('DT-4 Jan26'!$A$3:$A$500, "EVT*") + COUNTIF('DT-3 Feb26'!$A$3:$A$500, "EVT*") + COUNTIF('DT-4 Feb26'!$A$3:$A$500, "EVT*") + COUNTIF(OFFSET($A$1, 1, 0, ROW()-2, 1), "EVT*") + 1, "0000"), "") -> EVT-2026-0230 | B11: 46090 | C11: Mon | D11: MR-305 and 306 | E11: New Joiners Induction | F11: 40 | G11: Small Event | H11: 08:00 AM | I11: 05:00 PM | L11: Deshraj | O11: Confirmed (Done) | P11: Not Required | Q11: place 40 writing pads chairs
A12: =IF(OR(D12<>"", E12<>"", K12<>"", N12<>""), "EVT-2026-" & TEXT(COUNTIF('DT-3 Jan26'!$A$3:$A$500, "EVT*") + COUNTIF('DT-4 Jan26'!$A$3:$A$500, "EVT*") + COUNTIF('DT-3 Feb26'!$A$3:$A$500, "EVT*") + COUNTIF('DT-4 Feb26'!$A$3:$A$500, "EVT*") + COUNTIF(OFFSET($A$1, 1, 0, ROW()-2, 1), "EVT*") + 1, "0000"), "") -> EVT-2026-0231 | B12: 46090 | C12: Mon | D12: Breakout Area | E12: New Joiners Induction | F12: 40 | G12: Small Event | H12: 08:00 AM | I12: 05:00 PM | L12: Deshraj | O12: Confirmed (Done) | P12: Not Required | Q12: Classroomset up - confirmed by Deshraj
